Workbook
Name 是否经营农险: [12]封面!$B$25
Name 类型: OFFSET([18]字段!$L$11,,,COUNTA([18]字段!$L$1:$L$65536),)
Name 开户行: OFFSET([18]字段!$M$11,,,COUNTA([18]字段!$M$1:$M$65536),)
Name 关于: #REF!
Name 古2: #REF!
Name 公司类型: [12]封面!$B$4
Name 公司类别: [12]封面!#REF!
Name 部门: OFFSET([18]字段!$C$11,,,COUNTA([18]字段!$C$1:$C$65536),)
Name Year_1MC: [3]偿付能力计算!#REF!
Name Total_Pay: #REF!
Name Total_asset_PV: #REF!
Name TorF: [5]目录!$B$123:$B$164,[5]目录!$D$123:$D$164
Name TAX: [1]Inputs!$D$220
Name SURR_NP_TBL: [1]CSV!$V$1:$W$5
Name SURR_MORT_LOAD_TBL: [1]Mortality_Assump!$A$46:$IV$47
Name SURR_MORT: [1]Inputs!$D$193
Name Total_Payment: Scheduled_Payment+Extra_Payment
Name SURR_INT_MTH: [1]Inputs!$E$197
Name SURR_CIRCSA_LOAD_TBL: [1]RES_SURR_BASIS!#REF!
Name SURR_CIRCAP_TBL: [1]Inputs!$C$202:$E$206
Name SURR_CIRCAP_LOAD_TBL: [1]RES_SURR_BASIS!$A$37:$IV$41
Name SURR_CIRC_TBL: [1]Inputs!$C$202:$D$206
Name SURR_CIRC_LOAD_TBL: [1]RES_SURR_BASIS!$A$31:$IV$35
Name ST_DATE: [1]Results!#REF!
Name SOLVE: #REF!
Name SM_TBL: #REF!
Name SM_RES: [1]Inputs!$D$228
Name SURR_NP_MTD: [1]Inputs!$D$195
Name SM_COL: #REF!
Name 责任人: OFFSET([18]字段!$F$11,,,COUNTA([18]字段!$F$1:$F$65536),)
Name SCN_NO: [1]Inputs!$D$62
Name Scheduled_Monthly_Payment: #REF!
Name Scheduled_Interest_Rate: #REF!
Name SALES_SORT: '[2]Dashboard data'!$B$70:$D$99
Name SALES_FCST_ROWS: '[2]Sales Fcst'!$A$20:$IV$34,'[2]Sales Fcst'!$A$54:$IV$68,'[2]Sales Fcst'!$A$87:$IV$101
Name SA: [1]Inputs!$D$18
Name RES_TERM: [1]Inputs!$D$168
Name RES_SURR_TBL: [1]RES_SURR_BASIS!$A$2:$IV$65536
Name RES_MORT_LOAD_TBL: [1]Mortality_Assump!$A$40:$IV$41
Name RES_MORT_LOAD_DPER: [1]Inputs!$D$188
Name RES_MTD_ADJ: [1]Inputs!$D$166
Name RES_INT_MTH: [1]Inputs!$E$167
Name RES_CIRC_LOAD_TBL: [1]RES_SURR_BASIS!$A$14:$IV$18
Name Reg_Curve_Low: [3]曲线输入!$AH$2
Name RE_PREM: [1]Inputs!$E$69
Name RDR_ANN: [1]Inputs!$D$221
Name 支票号: OFFSET([18]支票领购与使用输入!$J$11,,,COUNTA([18]支票领购与使用输入!$J$1:$J$65536),)
Name PY_SALES: '[2]P&L (PY Act)'!$B$5:$T$35
Name PREM_SA: #REF!
Name unit: #REF!
Name PREM_RDR_MTH: #REF!
Name PREM_RDR_DMTH: #REF!
Name PREM_RDR: #REF!
Name PREM_PTERM: #REF!
Name PREM_PREM_F: #REF!
Name PREM_POL_TERM: #REF!
Name PREM_TERM: [1]Inputs!$D$21
Name PREM_MULT_TIME: #REF!
Name PREM_MULT_NAME: #REF!
Name PREM_MULT_INDEX: #REF!

Sheet 资产明细
A2: 45657 | B2: 资产唯一识别码/AssetUniqueIdentification | C2: 资产名称/AssetName | D2: 保险账户分类/InsuranceAccountType | E2: 资产配置分类一级/SAAAssetTypeLevel1 | F2: 资产配置分类二级/SAAAssetTypeLevel2 | G2: 资产配置分类三级/SAAAssetTypeLevel3 | H2: ALM五级分类/ALMClassificationLevel5 | I2: 偿付能力分类/SolvencyType | J2: 会计分类/AccountingType | K2: 资产组合名称/PortfolioName | L2: 建模类型/ModelType | M2: 净价市场价值/CleanMarketValue | N2: 风险暴露/EX | O2: 应收利息风险暴露/InterestEX | P2: 购买价格/PurchasePrice | Q2: 摊余成本/AmortizedCost | R2: 净价账面价值/CleanAccountingValue | S2: 应收利息/AccruedInterest | T2: 付息频率/Frequency | U2: 购买日/StartDate | V2: 首次付息日/FirstCouponDate | W2: 到期日/EndDate | X2: 特殊条款/SpecialTerms | Y2: 预期投资收益率/ExpectedReturn | Z2: 基准曲线/BenchmarkCurve | AA2: 信用利差风险因子/CreditSpreadRiskFactor | AB2: 非流动性溢价风险因子/IlliquidityPremiumRiskFactor | AC2: 权益风险因子/EquityRiskFactor | AD2: 面值/Notional | AE2: 面值2/Notional2 | AF2: 面值3/Notional3 | AG2: 面值4/Notional4 | AH2: 面值5/Notional5 | AI2: 提前还本日2/Date2 | AJ2: 提前还本日3/Date3 | AK2: 提前还本日4/Date4 | AL2: 提前还本日5/Date5 | AM2: 票息率/CouponRate | AN2: 票息率2/CouponRate2 | AO2: 票息率3/CouponRate3 | AP2: 票息率4/CouponRate4 | AQ2: 票息率5/CouponRate5 | AR2: 票息日期2/CouponRateDate2 | AS2: 票息日期3/CouponRateDate3 | AT2: 票息日期4/CouponRateDate4 | AU2: 票息日期5/CouponRateDate5 | AV2: 行权判断1/OptionExcercise1 | AW2: 行权判断2/OptionExcercise2 | AX2: 行权判断3/OptionExcercise3 | AY2: 行权判断4/OptionExcercise4 | AZ2: 行权判断5/OptionExcercise5 | BA2: 行权日期1/OptionExcerciseDate1 | BB2: 行权日期2/OptionExcerciseDate2 | BC2: 行权日期3/OptionExcerciseDate3 | BD2: 行权日期4/OptionExcerciseDate4 | BE2: 行权日期5/OptionExcerciseDate5 | BF2: 实际利率/CostYTM | BG2: 分红率/DividendYield | BH2: AFS资产历史累计浮盈浮亏/AFSAccumulatedUnrealisedGain | BI2: AFS资产当期浮盈浮亏变现比/AFSCurrentGainRealizationRatio | BJ2: 违约风险1/PDMarginal1 | BK2: 违约损失率1/LossGivenDefault1 | BL2: 违约风险2/PDMarginal2 | BM2: 违约损失率2/LossGivenDefault2 | BN2: 预计信用变化/ExpectedCreditState
A3: 3 | B3: 国债_3Y | C3: 国债_3Y | D3: 传统账户 | E3: 固定收益类 | F3: 国债 | G3: 国债_3Y | I3: Generic_国债_3Y | J3: AFS | K3: 国债_3Y | L3: 标准固收类 | M3: ==IF($D3=配置调整!$A$5,VLOOKUP($K3,配置调整!$B$4:$O$29,6,0)*配置调整!$A$6,IF($D3=配置调整!$A$8,VLOOKUP($K3,配置调整!$B$4:$O$29,6,0)*配置调整!$A$9,IF($D3=配置调整!$A$11,VLOOKUP($K3,配置调整!$B$4:$O$29,6,0)*配置调整!$A$12,FALSE))) -> 98950474 | N3: ==M3 -> 98950474 | O3: 0 | P3: ==M3 -> 98950474 | Q3: ==M3 -> 98950474 | R3: ==M3 -> 98950474 | S3: 0 | T3: 1 | U3: ==IF(OR(L3="标准固收类",L3="非标固收类"),$A$2,"") -> 45657 | V3: ==IF(OR(L3="标准固收类",L3="非标固收类"),EOMONTH($A$2,12),"") -> 46022 | W3: ==IF(OR(L3="标准固收类",L3="非标固收类"),EOMONTH($A$2,A3*12),"") -> 46752 | X3: 不适用 | Y3: ==VLOOKUP(资产明细!K3,配置调整!$B$4:$C$29,2,0) -> 0.011872 | Z3: Govt | AD3: ==P3 -> 98950474 | AM3: ==IF(OR(L3="标准固收类",L3="非标固收类"),Y3,"") -> 0.011872 | BF3: ==AM3 -> 0.011872 | BG3: ==IF(OR(L3="标准固收类",L3="非标固收类"),"",MIN(Y3,2%)) | BH3: 0 | BI3: 0.85
A4: 5 | B4: 国债_5Y | C4: 国债_5Y | D4: 传统账户 | E4: 固定收益类 | F4: 国债 | G4: 国债_5Y | I4: Generic_国债_5Y | J4: AFS | K4: 国债_5Y | L4: 标准固收类 | M4: ==IF($D4=配置调整!$A$5,VLOOKUP($K4,配置调整!$B$4:$O$29,6,0)*配置调整!$A$6,IF($D4=配置调整!$A$8,VLOOKUP($K4,配置调整!$B$4:$O$29,6,0)*配置调整!$A$9,IF($D4=配置调整!$A$11,VLOOKUP($K4,配置调整!$B$4:$O$29,6,0)*配置调整!$A$12,FALSE))) -> 2.0840971e+08 | N4: ==M4 -> 2.0840971e+08 | O4: 0 | P4: ==M4 -> 2.0840971e+08 | Q4: ==M4 -> 2.0840971e+08 | R4: ==M4 -> 2.0840971e+08 | S4: 0 | T4: 1 | U4: ==IF(OR(L4="标准固收类",L4="非标固收类"),$A$2,"") -> 45657 | V4: ==IF(OR(L4="标准固收类",L4="非标固收类"),EOMONTH($A$2,12),"") -> 46022 | W4: ==IF(OR(L4="标准固收类",L4="非标固收类"),EOMONTH($A$2,A4*12),"") -> 47483 | X4: 不适用 | Y4: ==VLOOKUP(资产明细!K4,配置调整!$B$4:$C$29,2,0) -> 0.014152 | Z4: Govt | AD4: ==P4 -> 2.0840971e+08 | AM4: ==IF(OR(L4="标准固收类",L4="非标固收类"),Y4,"") -> 0.014152 | BF4: ==AM4 -> 0.014152 | BG4: ==IF(OR(L4="标准固收类",L4="非标固收类"),"",MIN(Y4,2%)) | BH4: 0 | BI4: 0.85
A5: 10 | B5: 国债_10Y | C5: 国债_10Y | D5: 传统账户 | E5: 固定收益类 | F5: 国债 | G5: 国债_10Y | I5: Generic_国债_10Y | J5: AFS | K5: 国债_10Y | L5: 标准固收类 | M5: ==IF($D5=配置调整!$A$5,VLOOKUP($K5,配置调整!$B$4:$O$29,6,0)*配置调整!$A$6,IF($D5=配置调整!$A$8,VLOOKUP($K5,配置调整!$B$4:$O$29,6,0)*配置调整!$A$9,IF($D5=配置调整!$A$11,VLOOKUP($K5,配置调整!$B$4:$O$29,6,0)*配置调整!$A$12,FALSE))) -> 8.6934539e+08 | N5: ==M5 -> 8.6934539e+08 | O5: 0 | P5: ==M5 -> 8.6934539e+08 | Q5: ==M5 -> 8.6934539e+08 | R5: ==M5 -> 8.6934539e+08 | S5: 0 | T5: 1 | U5: ==IF(OR(L5="标准固收类",L5="非标固收类"),$A$2,"") -> 45657 | V5: ==IF(OR(L5="标准固收类",L5="非标固收类"),EOMONTH($A$2,12),"") -> 46022 | W5: ==IF(OR(L5="标准固收类",L5="非标固收类"),EOMONTH($A$2,A5*12),"") -> 49309 | X5: 不适用 | Y5: ==VLOOKUP(资产明细!K5,配置调整!$B$4:$C$29,2,0) -> 0.016752 | Z5: Govt | AD5: ==P5 -> 8.6934539e+08 | AM5: ==IF(OR(L5="标准固收类",L5="非标固收类"),Y5,"") -> 0.016752 | BF5: ==AM5 -> 0.016752 | BG5: ==IF(OR(L5="标准固收类",L5="非标固收类"),"",MIN(Y5,2%)) | BH5: 0 | BI5: 0.85
A6: 20 | B6: 国债_20Y | C6: 国债_20Y | D6: 传统账户 | E6: 固定收益类 | F6: 国债 | G6: 国债_20Y | I6: Generic_国债_20Y | J6: AFS | K6: 国债_20Y | L6: 标准固收类 | M6: ==IF($D6=配置调整!$A$5,VLOOKUP($K6,配置调整!$B$4:$O$29,6,0)*配置调整!$A$6,IF($D6=配置调整!$A$8,VLOOKUP($K6,配置调整!$B$4:$O$29,6,0)*配置调整!$A$9,IF($D6=配置调整!$A$11,VLOOKUP($K6,配置调整!$B$4:$O$29,6,0)*配置调整!$A$12,FALSE))) -> 3.8019957e+09 | N6: ==M6 -> 3.8019957e+09 | O6: 0 | P6: ==M6 -> 3.8019957e+09 | Q6: ==M6 -> 3.8019957e+09 | R6: ==M6 -> 3.8019957e+09 | S6: 0 | T6: 1 | U6: ==IF(OR(L6="标准固收类",L6="非标固收类"),$A$2,"") -> 45657 | V6: ==IF(OR(L6="标准固收类",L6="非标固收类"),EOMONTH($A$2,12),"") -> 46022 | W6: ==IF(OR(L6="标准固收类",L6="非标固收类"),EOMONTH($A$2,A6*12),"") -> 52962 | X6: 不适用 | Y6: ==VLOOKUP(资产明细!K6,配置调整!$B$4:$C$29,2,0) -> 0.019747 | Z6: Govt | AD6: ==P6 -> 3.8019957e+09 | AM6: ==IF(OR(L6="标准固收类",L6="非标固收类"),Y6,"") -> 0.019747 | BF6: ==AM6 -> 0.019747 | BG6: ==IF(OR(L6="标准固收类",L6="非标固收类"),"",MIN(Y6,2%)) | BH6: 0 | BI6: 0.85
A7: 50 | B7: 国债_50Y | C7: 国债_50Y | D7: 传统账户 | E7: 固定收益类 | F7: 国债 | G7: 国债_50Y | I7: Generic_国债_50Y | J7: AFS | K7: 国债_50Y | L7: 标准固收类 | M7: ==IF($D7=配置调整!$A$5,VLOOKUP($K7,配置调整!$B$4:$O$29,6,0)*配置调整!$A$6,IF($D7=配置调整!$A$8,VLOOKUP($K7,配置调整!$B$4:$O$29,6,0)*配置调整!$A$9,IF($D7=配置调整!$A$11,VLOOKUP($K7,配置调整!$B$4:$O$29,6,0)*配置调整!$A$12,FALSE))) -> 5.5148303e+09 | N7: ==M7 -> 5.5148303e+09 | O7: 0 | P7: ==M7 -> 5.5148303e+09 | Q7: ==M7 -> 5.5148303e+09 | R7: ==M7 -> 5.5148303e+09 | S7: 0 | T7: 1 | U7: ==IF(OR(L7="标准固收类",L7="非标固收类"),$A$2,"") -> 45657 | V7: ==IF(OR(L7="标准固收类",L7="非标固收类"),EOMONTH($A$2,12),"") -> 46022 | W7: ==IF(OR(L7="标准固收类",L7="非标固收类"),EOMONTH($A$2,A7*12),"") -> 63919 | X7: 不适用 | Y7: ==VLOOKUP(资产明细!K7,配置调整!$B$4:$C$29,2,0) -> 0.019875 | Z7: Govt | AD7: ==P7 -> 5.5148303e+09 | AM7: ==IF(OR(L7="标准固收类",L7="非标固收类"),Y7,"") -> 0.019875 | BF7: ==AM7 -> 0.019875 | BG7: ==IF(OR(L7="标准固收类",L7="非标固收类"),"",MIN(Y7,2%)) | BH7: 0 | BI7: 0.85
A8: 3 | B8: 高等级信用债_3Y | C8: 高等级信用债_3Y | D8: 传统账户 | E8: 固定收益类 | F8: 高等级信用债 | G8: 高等级信用债_3Y | I8: Generic_高等级信用债_3Y | J8: AFS | K8: 信用债_3Y | L8: 标准固收类 | M8: ==IF($D8=配置调整!$A$5,VLOOKUP($K8,配置调整!$B$4:$O$29,6,0)*配置调整!$A$6,IF($D8=配置调整!$A$8,VLOOKUP($K8,配置调整!$B$4:$O$29,6,0)*配置调整!$A$9,IF($D8=配置调整!$A$11,VLOOKUP($K8,配置调整!$B$4:$O$29,6,0)*配置调整!$A$12,FALSE))) -> 1.8185257e+09 | N8: ==M8 -> 1.8185257e+09 | O8: 0 | P8: ==M8 -> 1.8185257e+09 | Q8: ==M8 -> 1.8185257e+09 | R8: ==M8 -> 1.8185257e+09 | S8: 0 | T8: 1 | U8: ==IF(OR(L8="标准固收类",L8="非标固收类"),$A$2,"") -> 45657 | V8: ==IF(OR(L8="标准固收类",L8="非标固收类"),EOMONTH($A$2,12),"") -> 46022 | W8: ==IF(OR(L8="标准固收类",L8="非标固收类"),EOMONTH($A$2,A8*12),"") -> 46752 | X8: 不适用 | Y8: ==VLOOKUP(资产明细!K8,配置调整!$B$4:$C$29,2,0) -> 0.017501 | Z8: Govt | AA8: CORIG0-3 | AD8: ==P8 -> 1.8185257e+09 | AM8: ==IF(OR(L8="标准固收类",L8="非标固收类"),Y8,"") -> 0.017501 | BF8: ==AM8 -> 0.017501 | BG8: ==IF(OR(L8="标准固收类",L8="非标固收类"),"",MIN(Y8,2%)) | BH8: 0 | BI8: 0.85
A9: 5 | B9: 高等级信用债_5Y | C9: 高等级信用债_5Y | D9: 传统账户 | E9: 固定收益类 | F9: 高等级信用债 | G9: 高等级信用债_5Y | I9: Generic_高等级信用债_5Y | J9: AFS | K9: 信用债_5Y | L9: 标准固收类 | M9: ==IF($D9=配置调整!$A$5,VLOOKUP($K9,配置调整!$B$4:$O$29,6,0)*配置调整!$A$6,IF($D9=配置调整!$A$8,VLOOKUP($K9,配置调整!$B$4:$O$29,6,0)*配置调整!$A$9,IF($D9=配置调整!$A$11,VLOOKUP($K9,配置调整!$B$4:$O$29,6,0)*配置调整!$A$12,FALSE))) -> 1.5992956e+08 | N9: ==M9 -> 1.5992956e+08 | O9: 0 | P9: ==M9 -> 1.5992956e+08 | Q9: ==M9 -> 1.5992956e+08 | R9: ==M9 -> 1.5992956e+08 | S9: 0 | T9: 1 | U9: ==IF(OR(L9="标准固收类",L9="非标固收类"),$A$2,"") -> 45657 | V9: ==IF(OR(L9="标准固收类",L9="非标固收类"),EOMONTH($A$2,12),"") -> 46022 | W9: ==IF(OR(L9="标准固收类",L9="非标固收类"),EOMONTH($A$2,A9*12),"") -> 47483 | X9: 不适用 | Y9: ==VLOOKUP(资产明细!K9,配置调整!$B$4:$C$29,2,0) -> 0.018727 | Z9: Govt | AA9: CORIG3+ | AD9: ==P9 -> 1.5992956e+08 | AM9: ==IF(OR(L9="标准固收类",L9="非标固收类"),Y9,"") -> 0.018727 | BF9: ==AM9 -> 0.018727 | BG9: ==IF(OR(L9="标准固收类",L9="非标固收类"),"",MIN(Y9,2%)) | BH9: 0 | BI9: 0.85
A10: 10 | B10: 高等级信用债_10Y | C10: 高等级信用债_10Y | D10: 传统账户 | E10: 固定收益类 | F10: 高等级信用债 | G10: 高等级信用债_10Y | I10: Generic_高等级信用债_10Y | J10: AFS | K10: 信用债_10Y | L10: 标准固收类 | M10: ==IF($D10=配置调整!$A$5,VLOOKUP($K10,配置调整!$B$4:$O$29,6,0)*配置调整!$A$6,IF($D10=配置调整!$A$8,VLOOKUP($K10,配置调整!$B$4:$O$29,6,0)*配置调整!$A$9,IF($D10=配置调整!$A$11,VLOOKUP($K10,配置调整!$B$4:$O$29,6,0)*配置调整!$A$12,FALSE))) -> 1.0469498e+09 | N10: ==M10 -> 1.0469498e+09 | O10: 0 | P10: ==M10 -> 1.0469498e+09 | Q10: ==M10 -> 1.0469498e+09 | R10: ==M10 -> 1.0469498e+09 | S10: 0 | T10: 1 | U10: ==IF(OR(L10="标准固收类",L10="非标固收类"),$A$2,"") -> 45657 | V10: ==IF(OR(L10="标准固收类",L10="非标固收类"),EOMONTH($A$2,12),"") -> 46022 | W10: ==IF(OR(L10="标准固收类",L10="非标固收类"),EOMONTH($A$2,A10*12),"") -> 49309 | X10: 不适用 | Y10: ==VLOOKUP(资产明细!K10,配置调整!$B$4:$C$29,2,0) -> 0.021173 | Z10: Govt | AA10: CORIG3+ | AD10: ==P10 -> 1.0469498e+09 | AM10: ==IF(OR(L10="标准固收类",L10="非标固收类"),Y10,"") -> 0.021173 | BF10: ==AM10 -> 0.021173 | BG10: ==IF(OR(L10="标准固收类",L10="非标固收类"),"",MIN(Y10,2%)) | BH10: 0 | BI10: 0.85
A11: 3 | B11: 非标资产_3Y | C11: 非标资产_3Y | D11: 传统账户 | E11: 固定收益类 | F11: 非标资产 | G11: 非标资产_3Y | I11: Generic_非标资产_3Y | J11: AFS | K11: 非标资产_3Y | L11: 非标固收类 | M11: ==IF($D11=配置调整!$A$5,VLOOKUP($K11,配置调整!$B$4:$O$29,6,0)*配置调整!$A$6,IF($D11=配置调整!$A$8,VLOOKUP($K11,配置调整!$B$4:$O$29,6,0)*配置调整!$A$9,IF($D11=配置调整!$A$11,VLOOKUP($K11,配置调整!$B$4:$O$29,6,0)*配置调整!$A$12,FALSE))) -> 7.6756732e+08 | N11: ==M11 -> 7.6756732e+08 | O11: 0 | P11: ==M11 -> 7.6756732e+08 | Q11: ==M11 -> 7.6756732e+08 | R11: ==M11 -> 7.6756732e+08 | S11: 0 | T11: 1 | U11: ==IF(OR(L11="标准固收类",L11="非标固收类"),$A$2,"") -> 45657 | V11: ==IF(OR(L11="标准固收类",L11="非标固收类"),EOMONTH($A$2,12),"") -> 46022 | W11: ==IF(OR(L11="标准固收类",L11="非标固收类"),EOMONTH($A$2,A11*12),"") -> 46752 | X11: 不适用 | Y11: ==VLOOKUP(资产明细!K11,配置调整!$B$4:$C$29,2,0) -> 0.024290322 | Z11: Govt | AA11: CORIG3+ | AB11: IP 3Y | AD11: ==P11 -> 7.6756732e+08 | AM11: ==IF(OR(L11="标准固收类",L11="非标固收类"),Y11,"") -> 0.024290322 | BF11: ==AM11 -> 0.024290322 | BG11: ==IF(OR(L11="标准固收类",L11="非标固收类"),"",MIN(Y11,2%)) | BH11: 0 | BI11: 0.85
A12: 5 | B12: 非标资产_5Y | C12: 非标资产_5Y | D12: 传统账户 | E12: 固定收益类 | F12: 非标资产 | G12: 非标资产_5Y | I12: Generic_非标资产_5Y | J12: AFS | K12: 非标资产_5Y | L12: 非标固收类 | M12: ==IF($D12=配置调整!$A$5,VLOOKUP($K12,配置调整!$B$4:$O$29,6,0)*配置调整!$A$6,IF($D12=配置调整!$A$8,VLOOKUP($K12,配置调整!$B$4:$O$29,6,0)*配置调整!$A$9,IF($D12=配置调整!$A$11,VLOOKUP($K12,配置调整!$B$4:$O$29,6,0)*配置调整!$A$12,FALSE))) -> 5.0298086e+08 | N12: ==M12 -> 5.0298086e+08 | O12: 0 | P12: ==M12 -> 5.0298086e+08 | Q12: ==M12 -> 5.0298086e+08 | R12: ==M12 -> 5.0298086e+08 | S12: 0 | T12: 1 | U12: ==IF(OR(L12="标准固收类",L12="非标固收类"),$A$2,"") -> 45657 | V12: ==IF(OR(L12="标准固收类",L12="非标固收类"),EOMONTH($A$2,12),"") -> 46022 | W12: ==IF(OR(L12="标准固收类",L12="非标固收类"),EOMONTH($A$2,A12*12),"") -> 47483 | X12: 不适用 | Y12: ==VLOOKUP(资产明细!K12,配置调整!$B$4:$C$29,2,0) -> 0.025629035 | Z12: Govt | AA12: CORIG3+ | AB12: IP 5Y | AD12: ==P12 -> 5.0298086e+08 | AM12: ==IF(OR(L12="标准固收类",L12="非标固收类"),Y12,"") -> 0.025629035 | BF12: ==AM12 -> 0.025629035 | BG12: ==IF(OR(L12="标准固收类",L12="非标固收类"),"",MIN(Y12,2%)) | BH12: 0 | BI12: 0.85
B13: A股 | C13: A股 | D13: 传统账户 | E13: 权益类 | F13: 上市普通股票 | G13: A股 | I13: Generic_A股 | J13: AFS | K13: A股 | L13: 权益类 | M13: ==IF($D13=配置调整!$A$5,VLOOKUP($K13,配置调整!$B$4:$O$29,6,0)*配置调整!$A$6,IF($D13=配置调整!$A$8,VLOOKUP($K13,配置调整!$B$4:$O$29,6,0)*配置调整!$A$9,IF($D13=配置调整!$A$11,VLOOKUP($K13,配置调整!$B$4:$O$29,6,0)*配置调整!$A$12,FALSE))) -> 267518.43 | N13: ==M13 -> 267518.43 | O13: 0 | P13: ==M13 -> 267518.43 | Q13: ==M13 -> 267518.43 | R13: ==M13 -> 267518.43 | S13: 0 | U13: ==IF(OR(L13="标准固收类",L13="非标固收类"),$A$2,"") | V13: ==IF(OR(L13="标准固收类",L13="非标固收类"),EOMONTH($A$2,12),"") | W13: ==IF(OR(L13="标准固收类",L13="非标固收类"),EOMONTH($A$2,A13*12),"") | Y13: ==VLOOKUP(资产明细!K13,配置调整!$B$4:$C$29,2,0) -> 0.06 | Z13: Govt | AC13: A Shares | AD13: ==P13 -> 267518.43 | AM13: ==IF(OR(L13="标准固收类",L13="非标固收类"),Y13,"") | BF13: ==AM13 | BG13: ==IF(OR(L13="标准固收类",L13="非标固收类"),"",MIN(Y13,2%)) -> 0.02 | BH13: 0 | BI13: 0.85
B14: H股 | C14: H股 | D14: 传统账户 | E14: 权益类 | F14: 上市普通股票 | G14: H股 | I14: Generic_H股 | J14: AFS | K14: H股 | L14: 权益类 | M14: ==IF($D14=配置调整!$A$5,VLOOKUP($K14,配置调整!$B$4:$O$29,6,0)*配置调整!$A$6,IF($D14=配置调整!$A$8,VLOOKUP($K14,配置调整!$B$4:$O$29,6,0)*配置调整!$A$9,IF($D14=配置调整!$A$11,VLOOKUP($K14,配置调整!$B$4:$O$29,6,0)*配置调整!$A$12,FALSE))) -> 90343545 | N14: ==M14 -> 90343545 | O14: 0 | P14: ==M14 -> 90343545 | Q14: ==M14 -> 90343545 | R14: ==M14 -> 90343545 | S14: 0 | U14: ==IF(OR(L14="标准固收类",L14="非标固收类"),$A$2,"") | V14: ==IF(OR(L14="标准固收类",L14="非标固收类"),EOMONTH($A$2,12),"") | W14: ==IF(OR(L14="标准固收类",L14="非标固收类"),EOMONTH($A$2,A14*12),"") | Y14: ==VLOOKUP(资产明细!K14,配置调整!$B$4:$C$29,2,0) -> 0.07 | Z14: Govt | AC14: H Shares | AD14: ==P14 -> 90343545 | AM14: ==IF(OR(L14="标准固收类",L14="非标固收类"),Y14,"") | BF14: ==AM14 | BG14: ==IF(OR(L14="标准固收类",L14="非标固收类"),"",MIN(Y14,2%)) -> 0.02 | BH14: 0 | BI14: 0.85
B15: MSCI发达市场 | C15: MSCI发达市场 | D15: 传统账户 | E15: 权益类 | F15: 上市普通股票 | G15: MSCI发达市场 | I15: Generic_MSCI发达市场 | J15: AFS | K15: MSCI发达市场 | L15: 权益类 | M15: ==IF($D15=配置调整!$A$5,VLOOKUP($K15,配置调整!$B$4:$O$29,6,0)*配置调整!$A$6,IF($D15=配置调整!$A$8,VLOOKUP($K15,配置调整!$B$4:$O$29,6,0)*配置调整!$A$9,IF($D15=配置调整!$A$11,VLOOKUP($K15,配置调整!$B$4:$O$29,6,0)*配置调整!$A$12,FALSE))) -> 1.2721636e+08 | N15: ==M15 -> 1.2721636e+08 | O15: 0 | P15: ==M15 -> 1.2721636e+08 | Q15: ==M15 -> 1.2721636e+08 | R15: ==M15 -> 1.2721636e+08 | S15: 0 | U15: ==IF(OR(L15="标准固收类",L15="非标固收类"),$A$2,"") | V15: ==IF(OR(L15="标准固收类",L15="非标固收类"),EOMONTH($A$2,12),"") | W15: ==IF(OR(L15="标准固收类",L15="非标固收类"),EOMONTH($A$2,A15*12),"") | Y15: ==VLOOKUP(资产明细!K15,配置调整!$B$4:$C$29,2,0) -> 0.08 | Z15: Govt | AC15: MSCI DM Shares | AD15: ==P15 -> 1.2721636e+08 | AM15: ==IF(OR(L15="标准固收类",L15="非标固收类"),Y15,"") | BF15: ==AM15 | BG15: ==IF(OR(L15="标准固收类",L15="非标固收类"),"",MIN(Y15,2%)) -> 0.02 | BH15: 0 | BI15: 0.85
B16: MSCI新兴市场 | C16: MSCI新兴市场 | D16: 传统账户 | E16: 权益类 | F16: 上市普通股票 | G16: MSCI新兴市场 | I16: Generic_MSCI新兴市场 | J16: AFS | K16: MSCI新兴市场 | L16: 权益类 | M16: ==IF($D16=配置调整!$A$5,VLOOKUP($K16,配置调整!$B$4:$O$29,6,0)*配置调整!$A$6,IF($D16=配置调整!$A$8,VLOOKUP($K16,配置调整!$B$4:$O$29,6,0)*配置调整!$A$9,IF($D16=配置调整!$A$11,VLOOKUP($K16,配置调整!$B$4:$O$29,6,0)*配置调整!$A$12,FALSE))) -> 6.7889524e+08 | N16: ==M16 -> 6.7889524e+08 | O16: 0 | P16: ==M16 -> 6.7889524e+08 | Q16: ==M16 -> 6.7889524e+08 | R16: ==M16 -> 6.7889524e+08 | S16: 0 | U16: ==IF(OR(L16="标准固收类",L16="非标固收类"),$A$2,"") | V16: ==IF(OR(L16="标准固收类",L16="非标固收类"),EOMONTH($A$2,12),"") | W16: ==IF(OR(L16="标准固收类",L16="非标固收类"),EOMONTH($A$2,A16*12),"") | Y16: ==VLOOKUP(资产明细!K16,配置调整!$B$4:$C$29,2,0) -> 0.085 | Z16: Govt | AC16: MSCI EM Shares | AD16: ==P16 -> 6.7889524e+08 | AM16: ==IF(OR(L16="标准固收类",L16="非标固收类"),Y16,"") | BF16: ==AM16 | BG16: ==IF(OR(L16="标准固收类",L16="非标固收类"),"",MIN(Y16,2%)) -> 0.02 | BH16: 0 | BI16: 0.85
B17: 债券基金 | C17: 债券基金 | D17: 传统账户 | E17: 权益类 | F17: 债券基金 | G17: 债券基金 | I17: Generic_债券基金 | J17: AFS | K17: 债券基金 | L17: 权益类 | M17: ==IF($D17=配置调整!$A$5,VLOOKUP($K17,配置调整!$B$4:$O$29,6,0)*配置调整!$A$6,IF($D17=配置调整!$A$8,VLOOKUP($K17,配置调整!$B$4:$O$29,6,0)*配置调整!$A$9,IF($D17=配置调整!$A$11,VLOOKUP($K17,配置调整!$B$4:$O$29,6,0)*配置调整!$A$12,FALSE))) -> 267518.43 | N17: ==M17 -> 267518.43 | O17: 0 | P17: ==M17 -> 267518.43 | Q17: ==M17 -> 267518.43 | R17: ==M17 -> 267518.43 | S17: 0 | U17: ==IF(OR(L17="标准固收类",L17="非标固收类"),$A$2,"") | V17: ==IF(OR(L17="标准固收类",L17="非标固收类"),EOMONTH($A$2,12),"") | W17: ==IF(OR(L17="标准固收类",L17="非标固收类"),EOMONTH($A$2,A17*12),"") | Y17: ==VLOOKUP(资产明细!K17,配置调整!$B$4:$C$29,2,0) -> 0.028487288 | Z17: Govt | AC17: FI Fund | AD17: ==P17 -> 267518.43 | AM17: ==IF(OR(L17="标准固收类",L17="非标固收类"),Y17,"") | BF17: ==AM17 | BG17: ==IF(OR(L17="标准固收类",L17="非标固收类"),"",MIN(Y17,2%)) -> 0.02 | BH17: 0 | BI17: 0.85
B18: 货币基金 | C18: 货币基金 | D18: 传统账户 | E18: 权益类 | F18: 货币基金 | G18: 货币基金 | I18: Generic_货币基金 | J18: AFS | K18: 货币基金 | L18: 权益类 | M18: ==IF($D18=配置调整!$A$5,VLOOKUP($K18,配置调整!$B$4:$O$29,6,0)*配置调整!$A$6,IF($D18=配置调整!$A$8,VLOOKUP($K18,配置调整!$B$4:$O$29,6,0)*配置调整!$A$9,IF($D18=配置调整!$A$11,VLOOKUP($K18,配置调整!$B$4:$O$29,6,0)*配置调整!$A$12,FALSE))) -> 267518.43 | N18: ==M18 -> 267518.43 | O18: 0 | P18: ==M18 -> 267518.43 | Q18: ==M18 -> 267518.43 | R18: ==M18 -> 267518.43 | S18: 0 | U18: ==IF(OR(L18="标准固收类",L18="非标固收类"),$A$2,"") | V18: ==IF(OR(L18="标准固收类",L18="非标固收类"),EOMONTH($A$2,12),"") | W18: ==IF(OR(L18="标准固收类",L18="非标固收类"),EOMONTH($A$2,A18*12),"") | Y18: ==VLOOKUP(资产明细!K18,配置调整!$B$4:$C$29,2,0) -> 0.015 | Z18: Govt | AC18: Monetary Fund | AD18: ==P18 -> 267518.43 | AM18: ==IF(OR(L18="标准固收类",L18="非标固收类"),Y18,"") | BF18: ==AM18 | BG18: ==IF(OR(L18="标准固收类",L18="非标固收类"),"",MIN(Y18,2%)) -> 0.015 | BH18: 0 | BI18: 0.85
B19: 混合基金 | C19: 混合基金 | D19: 传统账户 | E19: 权益类 | F19: 混合基金 | G19: 混合基金 | I19: Generic_混合基金 | J19: AFS | K19: 混合基金 | L19: 权益类 | M19: ==IF($D19=配置调整!$A$5,VLOOKUP($K19,配置调整!$B$4:$O$29,6,0)*配置调整!$A$6,IF($D19=配置调整!$A$8,VLOOKUP($K19,配置调整!$B$4:$O$29,6,0)*配置调整!$A$9,IF($D19=配置调整!$A$11,VLOOKUP($K19,配置调整!$B$4:$O$29,6,0)*配置调整!$A$12,FALSE))) -> 2.8761567e+08 | N19: ==M19 -> 2.8761567e+08 | O19: 0 | P19: ==M19 -> 2.8761567e+08 | Q19: ==M19 -> 2.8761567e+08 | R19: ==M19 -> 2.8761567e+08 | S19: 0 | U19: ==IF(OR(L19="标准固收类",L19="非标固收类"),$A$2,"") | V19: ==IF(OR(L19="标准固收类",L19="非标固收类"),EOMONTH($A$2,12),"") | W19: ==IF(OR(L19="标准固收类",L19="非标固收类"),EOMONTH($A$2,A19*12),"") | Y19: ==VLOOKUP(资产明细!K19,配置调整!$B$4:$C$29,2,0) -> 0.05 | Z19: Govt | AC19: Mixed Fund | AD19: ==P19 -> 2.8761567e+08 | AM19: ==IF(OR(L19="标准固收类",L19="非标固收类"),Y19,"") | BF19: ==AM19 | BG19: ==IF(OR(L19="标准固收类",L19="非标固收类"),"",MIN(Y19,2%)) -> 0.02 | BH19: 0 | BI19: 0.85
B20: 股票基金 | C20: 股票基金 | D20: 传统账户 | E20: 权益类 | F20: 股票基金 | G20: 股票基金 | I20: Generic_股票基金 | J20: AFS | K20: 股票基金 | L20: 权益类 | M20: ==IF($D20=配置调整!$A$5,VLOOKUP($K20,配置调整!$B$4:$O$29,6,0)*配置调整!$A$6,IF($D20=配置调整!$A$8,VLOOKUP($K20,配置调整!$B$4:$O$29,6,0)*配置调整!$A$9,IF($D20=配置调整!$A$11,VLOOKUP($K20,配置调整!$B$4:$O$29,6,0)*配置调整!$A$12,FALSE))) -> 267518.43 | N20: ==M20 -> 267518.43 | O20: 0 | P20: ==M20 -> 267518.43 | Q20: ==M20 -> 267518.43 | R20: ==M20 -> 267518.43 | S20: 0 | U20: ==IF(OR(L20="标准固收类",L20="非标固收类"),$A$2,"") | V20: ==IF(OR(L20="标准固收类",L20="非标固收类"),EOMONTH($A$2,12),"") | W20: ==IF(OR(L20="标准固收类",L20="非标固收类"),EOMONTH($A$2,A20*12),"") | Y20: ==VLOOKUP(资产明细!K20,配置调整!$B$4:$C$29,2,0) -> 0.055 | Z20: Govt | AC20: Equity Fund | AD20: ==P20 -> 267518.43 | AM20: ==IF(OR(L20="标准固收类",L20="非标固收类"),Y20,"") | BF20: ==AM20 | BG20: ==IF(OR(L20="标准固收类",L20="非标固收类"),"",Y20) -> 0.055 | BH20: 0 | BI20: 0.85
B21: 优先股 | C21: 优先股 | D21: 传统账户 | E21: 权益类 | F21: 优先股 | G21: 优先股 | I21: Generic_优先股 | J21: AFS | K21: 优先股 | L21: 权益类 | M21: ==IF($D21=配置调整!$A$5,VLOOKUP($K21,配置调整!$B$4:$O$29,6,0)*配置调整!$A$6,IF($D21=配置调整!$A$8,VLOOKUP($K21,配置调整!$B$4:$O$29,6,0)*配置调整!$A$9,IF($D21=配置调整!$A$11,VLOOKUP($K21,配置调整!$B$4:$O$29,6,0)*配置调整!$A$12,FALSE))) -> 267518.43 | N21: ==M21 -> 267518.43 | O21: 0 | P21: ==M21 -> 267518.43 | Q21: ==M21 -> 267518.43 | R21: ==M21 -> 267518.43 | S21: 0 | U21: ==IF(OR(L21="标准固收类",L21="非标固收类"),$A$2,"") | V21: ==IF(OR(L21="标准固收类",L21="非标固收类"),EOMONTH($A$2,12),"") | W21: ==IF(OR(L21="标准固收类",L21="非标固收类"),EOMONTH($A$2,A21*12),"") | Y21: ==VLOOKUP(资产明细!K21,配置调整!$B$4:$C$29,2,0) -> 0.043 | Z21: Govt | AC21: LT Equity | AD21: ==P21 -> 267518.43 | AM21: ==IF(OR(L21="标准固收类",L21="非标固收类"),Y21,"") | BF21: ==AM21 | BG21: ==IF(OR(L21="标准固收类",L21="非标固收类"),"",MIN(Y21,2%)) -> 0.02 | BH21: 0 | BI21: 0.85
B22: 长期股权投资 | C22: 长期股权投资 | D22: 传统账户 | E22: 权益类 | F22: 股权投资 | G22: 长期股权投资 | I22: Generic_长期股权投资 | J22: AFS | K22: 长期股权投资 | L22: 权益类 | M22: ==IF($D22=配置调整!$A$5,VLOOKUP($K22,配置调整!$B$4:$O$29,6,0)*配置调整!$A$6,IF($D22=配置调整!$A$8,VLOOKUP($K22,配置调整!$B$4:$O$29,6,0)*配置调整!$A$9,IF($D22=配置调整!$A$11,VLOOKUP($K22,配置调整!$B$4:$O$29,6,0)*配置调整!$A$12,FALSE))) -> 267518.43 | N22: ==M22 -> 267518.43 | O22: 0 | P22: ==M22 -> 267518.43 | Q22: ==M22 -> 267518.43 | R22: ==M22 -> 267518.43 | S22: 0 | U22: ==IF(OR(L22="标准固收类",L22="非标固收类"),$A$2,"") | V22: ==IF(OR(L22="标准固收类",L22="非标固收类"),EOMONTH($A$2,12),"") | W22: ==IF(OR(L22="标准固收类",L22="非标固收类"),EOMONTH($A$2,A22*12),"") | Y22: ==VLOOKUP(资产明细!K22,配置调整!$B$4:$C$29,2,0) -> 0.05 | Z22: Govt | AC22: LT Equity | AD22: ==P22 -> 267518.43 | AM22: ==IF(OR(L22="标准固收类",L22="非标固收类"),Y22,"") | BF22: ==AM22 | BG22: ==IF(OR(L22="标准固收类",L22="非标固收类"),"",MIN(Y22,2%)) -> 0.02 | BH22: 0 | BI22: 0.85
B23: 未上市股权 | C23: 未上市股权 | D23: 传统账户 | E23: 权益类 | F23: 股权投资 | G23: 未上市股权 | I23: Generic_未上市股权 | J23: AFS | K23: 未上市股权 | L23: 权益类 | M23: ==IF($D23=配置调整!$A$5,VLOOKUP($K23,配置调整!$B$4:$O$29,6,0)*配置调整!$A$6,IF($D23=配置调整!$A$8,VLOOKUP($K23,配置调整!$B$4:$O$29,6,0)*配置调整!$A$9,IF($D23=配置调整!$A$11,VLOOKUP($K23,配置调整!$B$4:$O$29,6,0)*配置调整!$A$12,FALSE))) -> 1.6745297e+08 | N23: ==M23 -> 1.6745297e+08 | O23: 0 | P23: ==M23 -> 1.6745297e+08 | Q23: ==M23 -> 1.6745297e+08 | R23: ==M23 -> 1.6745297e+08 | S23: 0 | U23: ==IF(OR(L23="标准固收类",L23="非标固收类"),$A$2,"") | V23: ==IF(OR(L23="标准固收类",L23="非标固收类"),EOMONTH($A$2,12),"") | W23: ==IF(OR(L23="标准固收类",L23="非标固收类"),EOMONTH($A$2,A23*12),"") | Y23: ==VLOOKUP(资产明细!K23,配置调整!$B$4:$C$29,2,0) -> 0.086 | Z23: Govt | AC23: LT Equity | AD23: ==P23 -> 1.6745297e+08 | AM23: ==IF(OR(L23="标准固收类",L23="非标固收类"),Y23,"") | BF23: ==AM23 | BG23: ==IF(OR(L23="标准固收类",L23="非标固收类"),"",MIN(Y23,2%)) -> 0.02 | BH23: 0 | BI23: 0.85
B24: 固收产品 | C24: 固收产品 | D24: 传统账户 | E24: 固定收益类 | F24: 固收产品 | G24: 固收产品 | I24: Generic_固收产品 | J24: AFS | K24: 固收产品 | L24: 权益类 | M24: ==IF($D24=配置调整!$A$5,VLOOKUP($K24,配置调整!$B$4:$O$29,6,0)*配置调整!$A$6,IF($D24=配置调整!$A$8,VLOOKUP($K24,配置调整!$B$4:$O$29,6,0)*配置调整!$A$9,IF($D24=配置调整!$A$11,VLOOKUP($K24,配置调整!$B$4:$O$29,6,0)*配置调整!$A$12,FALSE))) -> 2.6877295e+09 | N24: ==M24 -> 2.6877295e+09 | O24: 0 | P24: ==M24 -> 2.6877295e+09 | Q24: ==M24 -> 2.6877295e+09 | R24: ==M24 -> 2.6877295e+09 | S24: 0 | U24: ==IF(OR(L24="标准固收类",L24="非标固收类"),$A$2,"") | V24: ==IF(OR(L24="标准固收类",L24="非标固收类"),EOMONTH($A$2,12),"") | W24: ==IF(OR(L24="标准固收类",L24="非标固收类"),EOMONTH($A$2,A24*12),"") | Y24: ==VLOOKUP(资产明细!K24,配置调整!$B$4:$C$29,2,0) -> 0.03481604 | Z24: Govt | AC24: FI Fund | AD24: ==P24 -> 2.6877295e+09 | AM24: ==IF(OR(L24="标准固收类",L24="非标固收类"),Y24,"") | BF24: ==AM24 | BG24: ==IF(OR(L24="标准固收类",L24="非标固收类"),"",MIN(Y24,2%)) -> 0.02 | BH24: 0 | BI24: 0.85
B25: 现金类 | C25: 现金类 | D25: 传统账户 | E25: 现金类 | F25: 现金类 | G25: 现金类 | I25: Generic_现金类 | J25: AFS | K25: 现金类 | L25: 现金类 | M25: ==IF($D25=配置调整!$A$5,VLOOKUP($K25,配置调整!$B$4:$O$29,6,0)*配置调整!$A$6,IF($D25=配置调整!$A$8,VLOOKUP($K25,配置调整!$B$4:$O$29,6,0)*配置调整!$A$9,IF($D25=配置调整!$A$11,VLOOKUP($K25,配置调整!$B$4:$O$29,6,0)*配置调整!$A$12,FALSE))) -> 8.2994137e+08 | N25: ==M25 -> 8.2994137e+08 | O25: 0 | P25: ==M25 -> 8.2994137e+08 | Q25: ==M25 -> 8.2994137e+08 | R25: ==M25 -> 8.2994137e+08 | S25: 0 | U25: ==IF(OR(L25="标准固收类",L25="非标固收类"),$A$2,"") | V25: ==IF(OR(L25="标准固收类",L25="非标固收类"),EOMONTH($A$2,12),"") | W25: ==IF(OR(L25="标准固收类",L25="非标固收类"),EOMONTH($A$2,A25*12),"") | Y25: ==VLOOKUP(资产明细!K25,配置调整!$B$4:$C$29,2,0) -> 0.015 | Z25: Govt | AD25: ==P25 -> 8.2994137e+08 | AM25: ==IF(OR(L25="标准固收类",L25="非标固收类"),Y25,"") | BF25: ==AM25 | BG25: ==IF(OR(L25="标准固收类",L25="非标固收类"),"",MIN(Y25,2%)) -> 0.015 | BH25: 0 | BI25: 0.85
A26: 3 | B26: 其他信用产品 | C26: 其他信用产品 | D26: 传统账户 | E26: 固定收益类 | F26: 其他信用产品 | G26: 其他信用产品 | I26: Generic_其他信用产品 | J26: AFS | K26: 其他信用产品 | L26: 标准固收类 | M26: ==IF($D26=配置调整!$A$5,VLOOKUP($K26,配置调整!$B$4:$O$29,6,0)*配置调整!$A$6,IF($D26=配置调整!$A$8,VLOOKUP($K26,配置调整!$B$4:$O$29,6,0)*配置调整!$A$9,IF($D26=配置调整!$A$11,VLOOKUP($K26,配置调整!$B$4:$O$29,6,0)*配置调整!$A$12,FALSE))) -> 3.2773084e+09 | N26: ==M26 -> 3.2773084e+09 | O26: 0 | P26: ==M26 -> 3.2773084e+09 | Q26: ==M26 -> 3.2773084e+09 | R26: ==M26 -> 3.2773084e+09 | S26: 0 | T26: 1 | U26: ==IF(OR(L26="标准固收类",L26="非标固收类"),$A$2,"") -> 45657 | V26: ==IF(OR(L26="标准固收类",L26="非标固收类"),EOMONTH($A$2,12),"") -> 46022 | W26: ==IF(OR(L26="标准固收类",L26="非标固收类"),EOMONTH($A$2,A26*12),"") -> 46752 | X26: 不适用 | Y26: ==VLOOKUP(资产明细!K26,配置调整!$B$4:$C$29,2,0) -> 0.031651664 | Z26: Govt | AA26: MTNIG3+ | AD26: ==P26 -> 3.2773084e+09 | AM26: ==IF(OR(L26="标准固收类",L26="非标固收类"),Y26,"") -> 0.031651664 | BF26: ==AM26 -> 0.031651664 | BG26: ==IF(OR(L26="标准固收类",L26="非标固收类"),"",MIN(Y26,2%)) | BH26: 0 | BI26: 0.85
A27: 5 | B27: 存款 | C27: 存款 | D27: 传统账户 | E27: 固定收益类 | F27: 存款 | G27: 存款 | I27: Generic_存款 | J27: AFS | K27: 存款 | L27: 标准固收类 | M27: ==IF($D27=配置调整!$A$5,VLOOKUP($K27,配置调整!$B$4:$O$29,6,0)*配置调整!$A$6,IF($D27=配置调整!$A$8,VLOOKUP($K27,配置调整!$B$4:$O$29,6,0)*配置调整!$A$9,IF($D27=配置调整!$A$11,VLOOKUP($K27,配置调整!$B$4:$O$29,6,0)*配置调整!$A$12,FALSE))) -> 1.2022584e+09 | N27: ==M27 -> 1.2022584e+09 | O27: 0 | P27: ==M27 -> 1.2022584e+09 | Q27: ==M27 -> 1.2022584e+09 | R27: ==M27 -> 1.2022584e+09 | S27: 0 | T27: 1 | U27: ==IF(OR(L27="标准固收类",L27="非标固收类"),$A$2,"") -> 45657 | V27: ==IF(OR(L27="标准固收类",L27="非标固收类"),EOMONTH($A$2,12),"") -> 46022 | W27: ==IF(OR(L27="标准固收类",L27="非标固收类"),EOMONTH($A$2,A27*12),"") -> 47483 | X27: 不适用 | Y27: ==VLOOKUP(资产明细!K27,配置调整!$B$4:$C$29,2,0) -> 0.028 | Z27: Govt | AA27: CORIG0-3 | AD27: ==P27 -> 1.2022584e+09 | AM27: ==IF(OR(L27="标准固收类",L27="非标固收类"),Y27,"") -> 0.028 | BF27: ==AM27 -> 0.028 | BG27: ==IF(OR(L27="标准固收类",L27="非标固收类"),"",MIN(Y27,2%)) | BH27: 0 | BI27: 0.85
B28: 不动产 | C28: 不动产 | D28: 传统账户 | E28: 不动产 | F28: 不动产 | G28: 不动产 | I28: Generic_不动产 | J28: AFS | K28: 不动产 | L28: 权益类 | M28: ==IF($D28=配置调整!$A$5,VLOOKUP($K28,配置调整!$B$4:$O$29,6,0)*配置调整!$A$6,IF($D28=配置调整!$A$8,VLOOKUP($K28,配置调整!$B$4:$O$29,6,0)*配置调整!$A$9,IF($D28=配置调整!$A$11,VLOOKUP($K28,配置调整!$B$4:$O$29,6,0)*配置调整!$A$12,FALSE))) -> 2.6119919e+09 | N28: ==M28 -> 2.6119919e+09 | O28: 0 | P28: ==M28 -> 2.6119919e+09 | Q28: ==M28 -> 2.6119919e+09 | R28: ==M28 -> 2.6119919e+09 | S28: 0 | U28: ==IF(OR(L28="标准固收类",L28="非标固收类"),$A$2,"") | V28: ==IF(OR(L28="标准固收类",L28="非标固收类"),EOMONTH($A$2,12),"") | W28: ==IF(OR(L28="标准固收类",L28="非标固收类"),EOMONTH($A$2,A28*12),"") | Y28: ==VLOOKUP(资产明细!K28,配置调整!$B$4:$C$29,2,0) -> 0.065 | Z28: Govt | AC28: Real Estate Index | AD28: ==P28 -> 2.6119919e+09 | AM28: ==IF(OR(L28="标准固收类",L28="非标固收类"),Y28,"") | BF28: ==AM28 | BG28: ==IF(OR(L28="标准固收类",L28="非标固收类"),"",MIN(Y28,2%)) -> 0.02 | BH28: 0 | BI28: 0.85
A29: 3 | B29: 国债_3Y2 | C29: 国债_3Y | D29: 万能账户 | E29: 固定收益类 | F29: 国债 | G29: 国债_3Y | I29: Generic_国债_3Y | J29: AFS | K29: 国债_3Y | L29: 标准固收类 | M29: ==IF($D29=配置调整!$A$5,VLOOKUP($K29,配置调整!$B$4:$O$29,6,0)*配置调整!$A$6,IF($D29=配置调整!$A$8,VLOOKUP($K29,配置调整!$B$4:$O$29,6,0)*配置调整!$A$9,IF($D29=配置调整!$A$11,VLOOKUP($K29,配置调整!$B$4:$O$29,6,0)*配置调整!$A$12,FALSE))) -> 98950474 | N29: ==M29 -> 98950474 | O29: 0 | P29: ==M29 -> 98950474 | Q29: ==M29 -> 98950474 | R29: ==M29 -> 98950474 | S29: 0 | T29: 1 | U29: ==IF(OR(L29="标准固收类",L29="非标固收类"),$A$2,"") -> 45657 | V29: ==IF(OR(L29="标准固收类",L29="非标固收类"),EOMONTH($A$2,12),"") -> 46022 | W29: ==IF(OR(L29="标准固收类",L29="非标固收类"),EOMONTH($A$2,A29*12),"") -> 46752 | X29: 不适用 | Y29: ==VLOOKUP(资产明细!K29,配置调整!$B$4:$C$29,2,0) -> 0.011872 | Z29: Govt | AD29: ==P29 -> 98950474 | AM29: ==IF(OR(L29="标准固收类",L29="非标固收类"),Y29,"") -> 0.011872 | BF29: ==AM29 -> 0.011872 | BG29: ==IF(OR(L29="标准固收类",L29="非标固收类"),"",MIN(Y29,2%)) | BH29: 0 | BI29: 0.85
A30: 5 | B30: 国债_5Y2 | C30: 国债_5Y | D30: 万能账户 | E30: 固定收益类 | F30: 国债 | G30: 国债_5Y | I30: Generic_国债_5Y | J30: AFS | K30: 国债_5Y | L30: 标准固收类 | M30: ==IF($D30=配置调整!$A$5,VLOOKUP($K30,配置调整!$B$4:$O$29,6,0)*配置调整!$A$6,IF($D30=配置调整!$A$8,VLOOKUP($K30,配置调整!$B$4:$O$29,6,0)*配置调整!$A$9,IF($D30=配置调整!$A$11,VLOOKUP($K30,配置调整!$B$4:$O$29,6,0)*配置调整!$A$12,FALSE))) -> 2.0840971e+08 | N30: ==M30 -> 2.0840971e+08 | O30: 0 | P30: ==M30 -> 2.0840971e+08 | Q30: ==M30 -> 2.0840971e+08 | R30: ==M30 -> 2.0840971e+08 | S30: 0 | T30: 1 | U30: ==IF(OR(L30="标准固收类",L30="非标固收类"),$A$2,"") -> 45657 | V30: ==IF(OR(L30="标准固收类",L30="非标固收类"),EOMONTH($A$2,12),"") -> 46022 | W30: ==IF(OR(L30="标准固收类",L30="非标固收类"),EOMONTH($A$2,A30*12),"") -> 47483 | X30: 不适用 | Y30: ==VLOOKUP(资产明细!K30,配置调整!$B$4:$C$29,2,0) -> 0.014152 | Z30: Govt | AD30: ==P30 -> 2.0840971e+08 | AM30: ==IF(OR(L30="标准固收类",L30="非标固收类"),Y30,"") -> 0.014152 | BF30: ==AM30 -> 0.014152 | BG30: ==IF(OR(L30="标准固收类",L30="非标固收类"),"",MIN(Y30,2%)) | BH30: 0 | BI30: 0.85
A31: 10 | B31: 国债_10Y2 | C31: 国债_10Y | D31: 万能账户 | E31: 固定收益类 | F31: 国债 | G31: 国债_10Y | I31: Generic_国债_10Y | J31: AFS | K31: 国债_10Y | L31: 标准固收类 | M31: ==IF($D31=配置调整!$A$5,VLOOKUP($K31,配置调整!$B$4:$O$29,6,0)*配置调整!$A$6,IF($D31=配置调整!$A$8,VLOOKUP($K31,配置调整!$B$4:$O$29,6,0)*配置调整!$A$9,IF($D31=配置调整!$A$11,VLOOKUP($K31,配置调整!$B$4:$O$29,6,0)*配置调整!$A$12,FALSE))) -> 8.6934539e+08 | N31: ==M31 -> 8.6934539e+08 | O31: 0 | P31: ==M31 -> 8.6934539e+08 | Q31: ==M31 -> 8.6934539e+08 | R31: ==M31 -> 8.6934539e+08 | S31: 0 | T31: 1 | U31: ==IF(OR(L31="标准固收类",L31="非标固收类"),$A$2,"") -> 45657 | V31: ==IF(OR(L31="标准固收类",L31="非标固收类"),EOMONTH($A$2,12),"") -> 46022 | W31: ==IF(OR(L31="标准固收类",L31="非标固收类"),EOMONTH($A$2,A31*12),"") -> 49309 | X31: 不适用 | Y31: ==VLOOKUP(资产明细!K31,配置调整!$B$4:$C$29,2,0) -> 0.016752 | Z31: Govt | AD31: ==P31 -> 8.6934539e+08 | AM31: ==IF(OR(L31="标准固收类",L31="非标固收类"),Y31,"") -> 0.016752 | BF31: ==AM31 -> 0.016752 | BG31: ==IF(OR(L31="标准固收类",L31="非标固收类"),"",MIN(Y31,2%)) | BH31: 0 | BI31: 0.85
A32: 20 | B32: 国债_20Y2 | C32: 国债_20Y | D32: 万能账户 | E32: 固定收益类 | F32: 国债 | G32: 国债_20Y | I32: Generic_国债_20Y | J32: AFS | K32: 国债_20Y | L32: 标准固收类 | M32: ==IF($D32=配置调整!$A$5,VLOOKUP($K32,配置调整!$B$4:$O$29,6,0)*配置调整!$A$6,IF($D32=配置调整!$A$8,VLOOKUP($K32,配置调整!$B$4:$O$29,6,0)*配置调整!$A$9,IF($D32=配置调整!$A$11,VLOOKUP($K32,配置调整!$B$4:$O$29,6,0)*配置调整!$A$12,FALSE))) -> 3.8019957e+09 | N32: ==M32 -> 3.8019957e+09 | O32: 0 | P32: ==M32 -> 3.8019957e+09 | Q32: ==M32 -> 3.8019957e+09 | R32: ==M32 -> 3.8019957e+09 | S32: 0 | T32: 1 | U32: ==IF(OR(L32="标准固收类",L32="非标固收类"),$A$2,"") -> 45657 | V32: ==IF(OR(L32="标准固收类",L32="非标固收类"),EOMONTH($A$2,12),"") -> 46022 | W32: ==IF(OR(L32="标准固收类",L32="非标固收类"),EOMONTH($A$2,A32*12),"") -> 52962 | X32: 不适用 | Y32: ==VLOOKUP(资产明细!K32,配置调整!$B$4:$C$29,2,0) -> 0.019747 | Z32: Govt | AD32: ==P32 -> 3.8019957e+09 | AM32: ==IF(OR(L32="标准固收类",L32="非标固收类"),Y32,"") -> 0.019747 | BF32: ==AM32 -> 0.019747 | BG32: ==IF(OR(L32="标准固收类",L32="非标固收类"),"",MIN(Y32,2%)) | BH32: 0 | BI32: 0.85
A33: 50 | B33: 国债_50Y2 | C33: 国债_50Y | D33: 万能账户 | E33: 固定收益类 | F33: 国债 | G33: 国债_50Y | I33: Generic_国债_50Y | J33: AFS | K33: 国债_50Y | L33: 标准固收类 | M33: ==IF($D33=配置调整!$A$5,VLOOKUP($K33,配置调整!$B$4:$O$29,6,0)*配置调整!$A$6,IF($D33=配置调整!$A$8,VLOOKUP($K33,配置调整!$B$4:$O$29,6,0)*配置调整!$A$9,IF($D33=配置调整!$A$11,VLOOKUP($K33,配置调整!$B$4:$O$29,6,0)*配置调整!$A$12,FALSE))) -> 5.5148303e+09 | N33: ==M33 -> 5.5148303e+09 | O33: 0 | P33: ==M33 -> 5.5148303e+09 | Q33: ==M33 -> 5.5148303e+09 | R33: ==M33 -> 5.5148303e+09 | S33: 0 | T33: 1 | U33: ==IF(OR(L33="标准固收类",L33="非标固收类"),$A$2,"") -> 45657 | V33: ==IF(OR(L33="标准固收类",L33="非标固收类"),EOMONTH($A$2,12),"") -> 46022 | W33: ==IF(OR(L33="标准固收类",L33="非标固收类"),EOMONTH($A$2,A33*12),"") -> 63919 | X33: 不适用 | Y33: ==VLOOKUP(资产明细!K33,配置调整!$B$4:$C$29,2,0) -> 0.019875 | Z33: Govt | AD33: ==P33 -> 5.5148303e+09 | AM33: ==IF(OR(L33="标准固收类",L33="非标固收类"),Y33,"") -> 0.019875 | BF33: ==AM33 -> 0.019875 | BG33: ==IF(OR(L33="标准固收类",L33="非标固收类"),"",MIN(Y33,2%)) | BH33: 0 | BI33: 0.85
A34: 3 | B34: 高等级信用债_3Y2 | C34: 高等级信用债_3Y | D34: 万能账户 | E34: 固定收益类 | F34: 高等级信用债 | G34: 高等级信用债_3Y | I34: Generic_高等级信用债_3Y | J34: AFS | K34: 信用债_3Y | L34: 标准固收类 | M34: ==IF($D34=配置调整!$A$5,VLOOKUP($K34,配置调整!$B$4:$O$29,6,0)*配置调整!$A$6,IF($D34=配置调整!$A$8,VLOOKUP($K34,配置调整!$B$4:$O$29,6,0)*配置调整!$A$9,IF($D34=配置调整!$A$11,VLOOKUP($K34,配置调整!$B$4:$O$29,6,0)*配置调整!$A$12,FALSE))) -> 1.8185257e+09 | N34: ==M34 -> 1.8185257e+09 | O34: 0 | P34: ==M34 -> 1.8185257e+09 | Q34: ==M34 -> 1.8185257e+09 | R34: ==M34 -> 1.8185257e+09 | S34: 0 | T34: 1 | U34: ==IF(OR(L34="标准固收类",L34="非标固收类"),$A$2,"") -> 45657 | V34: ==IF(OR(L34="标准固收类",L34="非标固收类"),EOMONTH($A$2,12),"") -> 46022 | W34: ==IF(OR(L34="标准固收类",L34="非标固收类"),EOMONTH($A$2,A34*12),"") -> 46752 | X34: 不适用 | Y34: ==VLOOKUP(资产明细!K34,配置调整!$B$4:$C$29,2,0) -> 0.017501 | Z34: Govt | AA34: CORIG0-3 | AD34: ==P34 -> 1.8185257e+09 | AM34: ==IF(OR(L34="标准固收类",L34="非标固收类"),Y34,"") -> 0.017501 | BF34: ==AM34 -> 0.017501 | BG34: ==IF(OR(L34="标准固收类",L34="非标固收类"),"",MIN(Y34,2%)) | BH34: 0 | BI34: 0.85
A35: 5 | B35: 高等级信用债_5Y2 | C35: 高等级信用债_5Y | D35: 万能账户 | E35: 固定收益类 | F35: 高等级信用债 | G35: 高等级信用债_5Y | I35: Generic_高等级信用债_5Y | J35: AFS | K35: 信用债_5Y | L35: 标准固收类 | M35: ==IF($D35=配置调整!$A$5,VLOOKUP($K35,配置调整!$B$4:$O$29,6,0)*配置调整!$A$6,IF($D35=配置调整!$A$8,VLOOKUP($K35,配置调整!$B$4:$O$29,6,0)*配置调整!$A$9,IF($D35=配置调整!$A$11,VLOOKUP($K35,配置调整!$B$4:$O$29,6,0)*配置调整!$A$12,FALSE))) -> 1.5992956e+08 | N35: ==M35 -> 1.5992956e+08 | O35: 0 | P35: ==M35 -> 1.5992956e+08 | Q35: ==M35 -> 1.5992956e+08 | R35: ==M35 -> 1.5992956e+08 | S35: 0 | T35: 1 | U35: ==IF(OR(L35="标准固收类",L35="非标固收类"),$A$2,"") -> 45657 | V35: ==IF(OR(L35="标准固收类",L35="非标固收类"),EOMONTH($A$2,12),"") -> 46022 | W35: ==IF(OR(L35="标准固收类",L35="非标固收类"),EOMONTH($A$2,A35*12),"") -> 47483 | X35: 不适用 | Y35: ==VLOOKUP(资产明细!K35,配置调整!$B$4:$C$29,2,0) -> 0.018727 | Z35: Govt | AA35: CORIG3+ | AD35: ==P35 -> 1.5992956e+08 | AM35: ==IF(OR(L35="标准固收类",L35="非标固收类"),Y35,"") -> 0.018727 | BF35: ==AM35 -> 0.018727 | BG35: ==IF(OR(L35="标准固收类",L35="非标固收类"),"",MIN(Y35,2%)) | BH35: 0 | BI35: 0.85
A36: 10 | B36: 高等级信用债_10Y2 | C36: 高等级信用债_10Y | D36: 万能账户 | E36: 固定收益类 | F36: 高等级信用债 | G36: 高等级信用债_10Y | I36: Generic_高等级信用债_10Y | J36: AFS | K36: 信用债_10Y | L36: 标准固收类 | M36: ==IF($D36=配置调整!$A$5,VLOOKUP($K36,配置调整!$B$4:$O$29,6,0)*配置调整!$A$6,IF($D36=配置调整!$A$8,VLOOKUP($K36,配置调整!$B$4:$O$29,6,0)*配置调整!$A$9,IF($D36=配置调整!$A$11,VLOOKUP($K36,配置调整!$B$4:$O$29,6,0)*配置调整!$A$12,FALSE))) -> 1.0469498e+09 | N36: ==M36 -> 1.0469498e+09 | O36: 0 | P36: ==M36 -> 1.0469498e+09 | Q36: ==M36 -> 1.0469498e+09 | R36: ==M36 -> 1.0469498e+09 | S36: 0 | T36: 1 | U36: ==IF(OR(L36="标准固收类",L36="非标固收类"),$A$2,"") -> 45657 | V36: ==IF(OR(L36="标准固收类",L36="非标固收类"),EOMONTH($A$2,12),"") -> 46022 | W36: ==IF(OR(L36="标准固收类",L36="非标固收类"),EOMONTH($A$2,A36*12),"") -> 49309 | X36: 不适用 | Y36: ==VLOOKUP(资产明细!K36,配置调整!$B$4:$C$29,2,0) -> 0.021173 | Z36: Govt | AA36: CORIG3+ | AD36: ==P36 -> 1.0469498e+09 | AM36: ==IF(OR(L36="标准固收类",L36="非标固收类"),Y36,"") -> 0.021173 | BF36: ==AM36 -> 0.021173 | BG36: ==IF(OR(L36="标准固收类",L36="非标固收类"),"",MIN(Y36,2%)) | BH36: 0 | BI36: 0.85
A37: 3 | B37: 非标资产_3Y2 | C37: 非标资产_3Y | D37: 万能账户 | E37: 固定收益类 | F37: 非标资产 | G37: 非标资产_3Y | I37: Generic_非标资产_3Y | J37: AFS | K37: 非标资产_3Y | L37: 非标固收类 | M37: ==IF($D37=配置调整!$A$5,VLOOKUP($K37,配置调整!$B$4:$O$29,6,0)*配置调整!$A$6,IF($D37=配置调整!$A$8,VLOOKUP($K37,配置调整!$B$4:$O$29,6,0)*配置调整!$A$9,IF($D37=配置调整!$A$11,VLOOKUP($K37,配置调整!$B$4:$O$29,6,0)*配置调整!$A$12,FALSE))) -> 7.6756732e+08 | N37: ==M37 -> 7.6756732e+08 | O37: 0 | P37: ==M37 -> 7.6756732e+08 | Q37: ==M37 -> 7.6756732e+08 | R37: ==M37 -> 7.6756732e+08 | S37: 0 | T37: 1 | U37: ==IF(OR(L37="标准固收类",L37="非标固收类"),$A$2,"") -> 45657 | V37: ==IF(OR(L37="标准固收类",L37="非标固收类"),EOMONTH($A$2,12),"") -> 46022 | W37: ==IF(OR(L37="标准固收类",L37="非标固收类"),EOMONTH($A$2,A37*12),"") -> 46752 | X37: 不适用 | Y37: ==VLOOKUP(资产明细!K37,配置调整!$B$4:$C$29,2,0) -> 0.024290322 | Z37: Govt | AA37: CORIG3+ | AB37: IP 3Y | AD37: ==P37 -> 7.6756732e+08 | AM37: ==IF(OR(L37="标准固收类",L37="非标固收类"),Y37,"") -> 0.024290322 | BF37: ==AM37 -> 0.024290322 | BG37: ==IF(OR(L37="标准固收类",L37="非标固收类"),"",MIN(Y37,2%)) | BH37: 0 | BI37: 0.85
A38: 5 | B38: 非标资产_5Y2 | C38: 非标资产_5Y | D38: 万能账户 | E38: 固定收益类 | F38: 非标资产 | G38: 非标资产_5Y | I38: Generic_非标资产_5Y | J38: AFS | K38: 非标资产_5Y | L38: 非标固收类 | M38: ==IF($D38=配置调整!$A$5,VLOOKUP($K38,配置调整!$B$4:$O$29,6,0)*配置调整!$A$6,IF($D38=配置调整!$A$8,VLOOKUP($K38,配置调整!$B$4:$O$29,6,0)*配置调整!$A$9,IF($D38=配置调整!$A$11,VLOOKUP($K38,配置调整!$B$4:$O$29,6,0)*配置调整!$A$12,FALSE))) -> 5.0298086e+08 | N38: ==M38 -> 5.0298086e+08 | O38: 0 | P38: ==M38 -> 5.0298086e+08 | Q38: ==M38 -> 5.0298086e+08 | R38: ==M38 -> 5.0298086e+08 | S38: 0 | T38: 1 | U38: ==IF(OR(L38="标准固收类",L38="非标固收类"),$A$2,"") -> 45657 | V38: ==IF(OR(L38="标准固收类",L38="非标固收类"),EOMONTH($A$2,12),"") -> 46022 | W38: ==IF(OR(L38="标准固收类",L38="非标固收类"),EOMONTH($A$2,A38*12),"") -> 47483 | X38: 不适用 | Y38: ==VLOOKUP(资产明细!K38,配置调整!$B$4:$C$29,2,0) -> 0.025629035 | Z38: Govt | AA38: CORIG3+ | AB38: IP 5Y | AD38: ==P38 -> 5.0298086e+08 | AM38: ==IF(OR(L38="标准固收类",L38="非标固收类"),Y38,"") -> 0.025629035 | BF38: ==AM38 -> 0.025629035 | BG38: ==IF(OR(L38="标准固收类",L38="非标固收类"),"",MIN(Y38,2%)) | BH38: 0 | BI38: 0.85
B39: A股2 | C39: A股 | D39: 万能账户 | E39: 权益类 | F39: 上市普通股票 | G39: A股 | I39: Generic_A股 | J39: AFS | K39: A股 | L39: 权益类 | M39: ==IF($D39=配置调整!$A$5,VLOOKUP($K39,配置调整!$B$4:$O$29,6,0)*配置调整!$A$6,IF($D39=配置调整!$A$8,VLOOKUP($K39,配置调整!$B$4:$O$29,6,0)*配置调整!$A$9,IF($D39=配置调整!$A$11,VLOOKUP($K39,配置调整!$B$4:$O$29,6,0)*配置调整!$A$12,FALSE))) -> 267518.43 | N39: ==M39 -> 267518.43 | O39: 0 | P39: ==M39 -> 267518.43 | Q39: ==M39 -> 267518.43 | R39: ==M39 -> 267518.43 | S39: 0 | U39: ==IF(OR(L39="标准固收类",L39="非标固收类"),$A$2,"") | V39: ==IF(OR(L39="标准固收类",L39="非标固收类"),EOMONTH($A$2,12),"") | W39: ==IF(OR(L39="标准固收类",L39="非标固收类"),EOMONTH($A$2,A39*12),"") | Y39: ==VLOOKUP(资产明细!K39,配置调整!$B$4:$C$29,2,0) -> 0.06 | Z39: Govt | AC39: A Shares | AD39: ==P39 -> 267518.43 | AM39: ==IF(OR(L39="标准固收类",L39="非标固收类"),Y39,"") | BF39: ==AM39 | BG39: ==IF(OR(L39="标准固收类",L39="非标固收类"),"",MIN(Y39,2%)) -> 0.02 | BH39: 0 | BI39: 0.85
B40: H股2 | C40: H股 | D40: 万能账户 | E40: 权益类 | F40: 上市普通股票 | G40: H股 | I40: Generic_H股 | J40: AFS | K40: H股 | L40: 权益类 | M40: ==IF($D40=配置调整!$A$5,VLOOKUP($K40,配置调整!$B$4:$O$29,6,0)*配置调整!$A$6,IF($D40=配置调整!$A$8,VLOOKUP($K40,配置调整!$B$4:$O$29,6,0)*配置调整!$A$9,IF($D40=配置调整!$A$11,VLOOKUP($K40,配置调整!$B$4:$O$29,6,0)*配置调整!$A$12,FALSE))) -> 90343545 | N40: ==M40 -> 90343545 | O40: 0 | P40: ==M40 -> 90343545 | Q40: ==M40 -> 90343545 | R40: ==M40 -> 90343545 | S40: 0 | U40: ==IF(OR(L40="标准固收类",L40="非标固收类"),$A$2,"") | V40: ==IF(OR(L40="标准固收类",L40="非标固收类"),EOMONTH($A$2,12),"") | W40: ==IF(OR(L40="标准固收类",L40="非标固收类"),EOMONTH($A$2,A40*12),"") | Y40: ==VLOOKUP(资产明细!K40,配置调整!$B$4:$C$29,2,0) -> 0.07 | Z40: Govt | AC40: H Shares | AD40: ==P40 -> 90343545 | AM40: ==IF(OR(L40="标准固收类",L40="非标固收类"),Y40,"") | BF40: ==AM40 | BG40: ==IF(OR(L40="标准固收类",L40="非标固收类"),"",MIN(Y40,2%)) -> 0.02 | BH40: 0 | BI40: 0.85
B41: MSCI发达市场2 | C41: MSCI发达市场 | D41: 万能账户 | E41: 权益类 | F41: 上市普通股票 | G41: MSCI发达市场 | I41: Generic_MSCI发达市场 | J41: AFS | K41: MSCI发达市场 | L41: 权益类 | M41: ==IF($D41=配置调整!$A$5,VLOOKUP($K41,配置调整!$B$4:$O$29,6,0)*配置调整!$A$6,IF($D41=配置调整!$A$8,VLOOKUP($K41,配置调整!$B$4:$O$29,6,0)*配置调整!$A$9,IF($D41=配置调整!$A$11,VLOOKUP($K41,配置调整!$B$4:$O$29,6,0)*配置调整!$A$12,FALSE))) -> 1.2721636e+08 | N41: ==M41 -> 1.2721636e+08 | O41: 0 | P41: ==M41 -> 1.2721636e+08 | Q41: ==M41 -> 1.2721636e+08 | R41: ==M41 -> 1.2721636e+08 | S41: 0 | U41: ==IF(OR(L41="标准固收类",L41="非标固收类"),$A$2,"") | V41: ==IF(OR(L41="标准固收类",L41="非标固收类"),EOMONTH($A$2,12),"") | W41: ==IF(OR(L41="标准固收类",L41="非标固收类"),EOMONTH($A$2,A41*12),"") | Y41: ==VLOOKUP(资产明细!K41,配置调整!$B$4:$C$29,2,0) -> 0.08 | Z41: Govt | AC41: MSCI DM Shares | AD41: ==P41 -> 1.2721636e+08 | AM41: ==IF(OR(L41="标准固收类",L41="非标固收类"),Y41,"") | BF41: ==AM41 | BG41: ==IF(OR(L41="标准固收类",L41="非标固收类"),"",MIN(Y41,2%)) -> 0.02 | BH41: 0 | BI41: 0.85
B42: MSCI新兴市场2 | C42: MSCI新兴市场 | D42: 万能账户 | E42: 权益类 | F42: 上市普通股票 | G42: MSCI新兴市场 | I42: Generic_MSCI新兴市场 | J42: AFS | K42: MSCI新兴市场 | L42: 权益类 | M42: ==IF($D42=配置调整!$A$5,VLOOKUP($K42,配置调整!$B$4:$O$29,6,0)*配置调整!$A$6,IF($D42=配置调整!$A$8,VLOOKUP($K42,配置调整!$B$4:$O$29,6,0)*配置调整!$A$9,IF($D42=配置调整!$A$11,VLOOKUP($K42,配置调整!$B$4:$O$29,6,0)*配置调整!$A$12,FALSE))) -> 6.7889524e+08 | N42: ==M42 -> 6.7889524e+08 | O42: 0 | P42: ==M42 -> 6.7889524e+08 | Q42: ==M42 -> 6.7889524e+08 | R42: ==M42 -> 6.7889524e+08 | S42: 0 | U42: ==IF(OR(L42="标准固收类",L42="非标固收类"),$A$2,"") | V42: ==IF(OR(L42="标准固收类",L42="非标固收类"),EOMONTH($A$2,12),"") | W42: ==IF(OR(L42="标准固收类",L42="非标固收类"),EOMONTH($A$2,A42*12),"") | Y42: ==VLOOKUP(资产明细!K42,配置调整!$B$4:$C$29,2,0) -> 0.085 | Z42: Govt | AC42: MSCI EM Shares | AD42: ==P42 -> 6.7889524e+08 | AM42: ==IF(OR(L42="标准固收类",L42="非标固收类"),Y42,"") | BF42: ==AM42 | BG42: ==IF(OR(L42="标准固收类",L42="非标固收类"),"",MIN(Y42,2%)) -> 0.02 | BH42: 0 | BI42: 0.85
B43: 债券基金2 | C43: 债券基金 | D43: 万能账户 | E43: 权益类 | F43: 债券基金 | G43: 债券基金 | I43: Generic_债券基金 | J43: AFS | K43: 债券基金 | L43: 权益类 | M43: ==IF($D43=配置调整!$A$5,VLOOKUP($K43,配置调整!$B$4:$O$29,6,0)*配置调整!$A$6,IF($D43=配置调整!$A$8,VLOOKUP($K43,配置调整!$B$4:$O$29,6,0)*配置调整!$A$9,IF($D43=配置调整!$A$11,VLOOKUP($K43,配置调整!$B$4:$O$29,6,0)*配置调整!$A$12,FALSE))) -> 267518.43 | N43: ==M43 -> 267518.43 | O43: 0 | P43: ==M43 -> 267518.43 | Q43: ==M43 -> 267518.43 | R43: ==M43 -> 267518.43 | S43: 0 | U43: ==IF(OR(L43="标准固收类",L43="非标固收类"),$A$2,"") | V43: ==IF(OR(L43="标准固收类",L43="非标固收类"),EOMONTH($A$2,12),"") | W43: ==IF(OR(L43="标准固收类",L43="非标固收类"),EOMONTH($A$2,A43*12),"") | Y43: ==VLOOKUP(资产明细!K43,配置调整!$B$4:$C$29,2,0) -> 0.028487288 | Z43: Govt | AC43: FI Fund | AD43: ==P43 -> 267518.43 | AM43: ==IF(OR(L43="标准固收类",L43="非标固收类"),Y43,"") | BF43: ==AM43 | BG43: ==IF(OR(L43="标准固收类",L43="非标固收类"),"",MIN(Y43,2%)) -> 0.02 | BH43: 0 | BI43: 0.85
B44: 货币基金2 | C44: 货币基金 | D44: 万能账户 | E44: 权益类 | F44: 货币基金 | G44: 货币基金 | I44: Generic_货币基金 | J44: AFS | K44: 货币基金 | L44: 权益类 | M44: ==IF($D44=配置调整!$A$5,VLOOKUP($K44,配置调整!$B$4:$O$29,6,0)*配置调整!$A$6,IF($D44=配置调整!$A$8,VLOOKUP($K44,配置调整!$B$4:$O$29,6,0)*配置调整!$A$9,IF($D44=配置调整!$A$11,VLOOKUP($K44,配置调整!$B$4:$O$29,6,0)*配置调整!$A$12,FALSE))) -> 267518.43 | N44: ==M44 -> 267518.43 | O44: 0 | P44: ==M44 -> 267518.43 | Q44: ==M44 -> 267518.43 | R44: ==M44 -> 267518.43 | S44: 0 | U44: ==IF(OR(L44="标准固收类",L44="非标固收类"),$A$2,"") | V44: ==IF(OR(L44="标准固收类",L44="非标固收类"),EOMONTH($A$2,12),"") | W44: ==IF(OR(L44="标准固收类",L44="非标固收类"),EOMONTH($A$2,A44*12),"") | Y44: ==VLOOKUP(资产明细!K44,配置调整!$B$4:$C$29,2,0) -> 0.015 | Z44: Govt | AC44: Monetary Fund | AD44: ==P44 -> 267518.43 | AM44: ==IF(OR(L44="标准固收类",L44="非标固收类"),Y44,"") | BF44: ==AM44 | BG44: ==IF(OR(L44="标准固收类",L44="非标固收类"),"",MIN(Y44,2%)) -> 0.015 | BH44: 0 | BI44: 0.85
B45: 混合基金2 | C45: 混合基金 | D45: 万能账户 | E45: 权益类 | F45: 混合基金 | G45: 混合基金 | I45: Generic_混合基金 | J45: AFS | K45: 混合基金 | L45: 权益类 | M45: ==IF($D45=配置调整!$A$5,VLOOKUP($K45,配置调整!$B$4:$O$29,6,0)*配置调整!$A$6,IF($D45=配置调整!$A$8,VLOOKUP($K45,配置调整!$B$4:$O$29,6,0)*配置调整!$A$9,IF($D45=配置调整!$A$11,VLOOKUP($K45,配置调整!$B$4:$O$29,6,0)*配置调整!$A$12,FALSE))) -> 2.8761567e+08 | N45: ==M45 -> 2.8761567e+08 | O45: 0 | P45: ==M45 -> 2.8761567e+08 | Q45: ==M45 -> 2.8761567e+08 | R45: ==M45 -> 2.8761567e+08 | S45: 0 | U45: ==IF(OR(L45="标准固收类",L45="非标固收类"),$A$2,"") | V45: ==IF(OR(L45="标准固收类",L45="非标固收类"),EOMONTH($A$2,12),"") | W45: ==IF(OR(L45="标准固收类",L45="非标固收类"),EOMONTH($A$2,A45*12),"") | Y45: ==VLOOKUP(资产明细!K45,配置调整!$B$4:$C$29,2,0) -> 0.05 | Z45: Govt | AC45: Mixed Fund | AD45: ==P45 -> 2.8761567e+08 | AM45: ==IF(OR(L45="标准固收类",L45="非标固收类"),Y45,"") | BF45: ==AM45 | BG45: ==IF(OR(L45="标准固收类",L45="非标固收类"),"",MIN(Y45,2%)) -> 0.02 | BH45: 0 | BI45: 0.85
B46: 股票基金2 | C46: 股票基金 | D46: 万能账户 | E46: 权益类 | F46: 股票基金 | G46: 股票基金 | I46: Generic_股票基金 | J46: AFS | K46: 股票基金 | L46: 权益类 | M46: ==IF($D46=配置调整!$A$5,VLOOKUP($K46,配置调整!$B$4:$O$29,6,0)*配置调整!$A$6,IF($D46=配置调整!$A$8,VLOOKUP($K46,配置调整!$B$4:$O$29,6,0)*配置调整!$A$9,IF($D46=配置调整!$A$11,VLOOKUP($K46,配置调整!$B$4:$O$29,6,0)*配置调整!$A$12,FALSE))) -> 267518.43 | N46: ==M46 -> 267518.43 | O46: 0 | P46: ==M46 -> 267518.43 | Q46: ==M46 -> 267518.43 | R46: ==M46 -> 267518.43 | S46: 0 | U46: ==IF(OR(L46="标准固收类",L46="非标固收类"),$A$2,"") | V46: ==IF(OR(L46="标准固收类",L46="非标固收类"),EOMONTH($A$2,12),"") | W46: ==IF(OR(L46="标准固收类",L46="非标固收类"),EOMONTH($A$2,A46*12),"") | Y46: ==VLOOKUP(资产明细!K46,配置调整!$B$4:$C$29,2,0) -> 0.055 | Z46: Govt | AC46: Equity Fund | AD46: ==P46 -> 267518.43 | AM46: ==IF(OR(L46="标准固收类",L46="非标固收类"),Y46,"") | BF46: ==AM46 | BG46: 0.085446062 | BH46: 0 | BI46: 0.85
B47: 优先股2 | C47: 优先股 | D47: 万能账户 | E47: 权益类 | F47: 优先股 | G47: 优先股 | I47: Generic_优先股 | J47: AFS | K47: 优先股 | L47: 权益类 | M47: ==IF($D47=配置调整!$A$5,VLOOKUP($K47,配置调整!$B$4:$O$29,6,0)*配置调整!$A$6,IF($D47=配置调整!$A$8,VLOOKUP($K47,配置调整!$B$4:$O$29,6,0)*配置调整!$A$9,IF($D47=配置调整!$A$11,VLOOKUP($K47,配置调整!$B$4:$O$29,6,0)*配置调整!$A$12,FALSE))) -> 267518.43 | N47: ==M47 -> 267518.43 | O47: 0 | P47: ==M47 -> 267518.43 | Q47: ==M47 -> 267518.43 | R47: ==M47 -> 267518.43 | S47: 0 | U47: ==IF(OR(L47="标准固收类",L47="非标固收类"),$A$2,"") | V47: ==IF(OR(L47="标准固收类",L47="非标固收类"),EOMONTH($A$2,12),"") | W47: ==IF(OR(L47="标准固收类",L47="非标固收类"),EOMONTH($A$2,A47*12),"") | Y47: ==VLOOKUP(资产明细!K47,配置调整!$B$4:$C$29,2,0) -> 0.043 | Z47: Govt | AC47: LT Equity | AD47: ==P47 -> 267518.43 | AM47: ==IF(OR(L47="标准固收类",L47="非标固收类"),Y47,"") | BF47: ==AM47 | BG47: ==IF(OR(L47="标准固收类",L47="非标固收类"),"",MIN(Y47,2%)) -> 0.02 | BH47: 0 | BI47: 0.85
B48: 长期股权投资2 | C48: 长期股权投资 | D48: 万能账户 | E48: 权益类 | F48: 股权投资 | G48: 长期股权投资 | I48: Generic_长期股权投资 | J48: AFS | K48: 长期股权投资 | L48: 权益类 | M48: ==IF($D48=配置调整!$A$5,VLOOKUP($K48,配置调整!$B$4:$O$29,6,0)*配置调整!$A$6,IF($D48=配置调整!$A$8,VLOOKUP($K48,配置调整!$B$4:$O$29,6,0)*配置调整!$A$9,IF($D48=配置调整!$A$11,VLOOKUP($K48,配置调整!$B$4:$O$29,6,0)*配置调整!$A$12,FALSE))) -> 267518.43 | N48: ==M48 -> 267518.43 | O48: 0 | P48: ==M48 -> 267518.43 | Q48: ==M48 -> 267518.43 | R48: ==M48 -> 267518.43 | S48: 0 | U48: ==IF(OR(L48="标准固收类",L48="非标固收类"),$A$2,"") | V48: ==IF(OR(L48="标准固收类",L48="非标固收类"),EOMONTH($A$2,12),"") | W48: ==IF(OR(L48="标准固收类",L48="非标固收类"),EOMONTH($A$2,A48*12),"") | Y48: ==VLOOKUP(资产明细!K48,配置调整!$B$4:$C$29,2,0) -> 0.05 | Z48: Govt | AC48: LT Equity | AD48: ==P48 -> 267518.43 | AM48: ==IF(OR(L48="标准固收类",L48="非标固收类"),Y48,"") | BF48: ==AM48 | BG48: ==IF(OR(L48="标准固收类",L48="非标固收类"),"",MIN(Y48,2%)) -> 0.02 | BH48: 0 | BI48: 0.85
B49: 未上市股权2 | C49: 未上市股权 | D49: 万能账户 | E49: 权益类 | F49: 股权投资 | G49: 未上市股权 | I49: Generic_未上市股权 | J49: AFS | K49: 未上市股权 | L49: 权益类 | M49: ==IF($D49=配置调整!$A$5,VLOOKUP($K49,配置调整!$B$4:$O$29,6,0)*配置调整!$A$6,IF($D49=配置调整!$A$8,VLOOKUP($K49,配置调整!$B$4:$O$29,6,0)*配置调整!$A$9,IF($D49=配置调整!$A$11,VLOOKUP($K49,配置调整!$B$4:$O$29,6,0)*配置调整!$A$12,FALSE))) -> 1.6745297e+08 | N49: ==M49 -> 1.6745297e+08 | O49: 0 | P49: ==M49 -> 1.6745297e+08 | Q49: ==M49 -> 1.6745297e+08 | R49: ==M49 -> 1.6745297e+08 | S49: 0 | U49: ==IF(OR(L49="标准固收类",L49="非标固收类"),$A$2,"") | V49: ==IF(OR(L49="标准固收类",L49="非标固收类"),EOMONTH($A$2,12),"") | W49: ==IF(OR(L49="标准固收类",L49="非标固收类"),EOMONTH($A$2,A49*12),"") | Y49: ==VLOOKUP(资产明细!K49,配置调整!$B$4:$C$29,2,0) -> 0.086 | Z49: Govt | AC49: LT Equity | AD49: ==P49 -> 1.6745297e+08 | AM49: ==IF(OR(L49="标准固收类",L49="非标固收类"),Y49,"") | BF49: ==AM49 | BG49: ==IF(OR(L49="标准固收类",L49="非标固收类"),"",MIN(Y49,2%)) -> 0.02 | BH49: 0 | BI49: 0.85
B50: 固收产品2 | C50: 固收产品 | D50: 万能账户 | E50: 固定收益类 | F50: 固收产品 | G50: 固收产品 | I50: Generic_固收产品 | J50: AFS | K50: 固收产品 | L50: 权益类 | M50: ==IF($D50=配置调整!$A$5,VLOOKUP($K50,配置调整!$B$4:$O$29,6,0)*配置调整!$A$6,IF($D50=配置调整!$A$8,VLOOKUP($K50,配置调整!$B$4:$O$29,6,0)*配置调整!$A$9,IF($D50=配置调整!$A$11,VLOOKUP($K50,配置调整!$B$4:$O$29,6,0)*配置调整!$A$12,FALSE))) -> 2.6877295e+09 | N50: ==M50 -> 2.6877295e+09 | O50: 0 | P50: ==M50 -> 2.6877295e+09 | Q50: ==M50 -> 2.6877295e+09 | R50: ==M50 -> 2.6877295e+09 | S50: 0 | U50: ==IF(OR(L50="标准固收类",L50="非标固收类"),$A$2,"") | V50: ==IF(OR(L50="标准固收类",L50="非标固收类"),EOMONTH($A$2,12),"") | W50: ==IF(OR(L50="标准固收类",L50="非标固收类"),EOMONTH($A$2,A50*12),"") | Y50: ==VLOOKUP(资产明细!K50,配置调整!$B$4:$C$29,2,0) -> 0.03481604 | Z50: Govt | AC50: FI Fund | AD50: ==P50 -> 2.6877295e+09 | AM50: ==IF(OR(L50="标准固收类",L50="非标固收类"),Y50,"") | BF50: ==AM50 | BG50: ==IF(OR(L50="标准固收类",L50="非标固收类"),"",MIN(Y50,2%)) -> 0.02 | BH50: 0 | BI50: 0.85
B51: 现金类2 | C51: 现金类 | D51: 万能账户 | E51: 现金类 | F51: 现金类 | G51: 现金类 | I51: Generic_现金类 | J51: AFS | K51: 现金类 | L51: 现金类 | M51: ==IF($D51=配置调整!$A$5,VLOOKUP($K51,配置调整!$B$4:$O$29,6,0)*配置调整!$A$6,IF($D51=配置调整!$A$8,VLOOKUP($K51,配置调整!$B$4:$O$29,6,0)*配置调整!$A$9,IF($D51=配置调整!$A$11,VLOOKUP($K51,配置调整!$B$4:$O$29,6,0)*配置调整!$A$12,FALSE))) -> 8.2994137e+08 | N51: ==M51 -> 8.2994137e+08 | O51: 0 | P51: ==M51 -> 8.2994137e+08 | Q51: ==M51 -> 8.2994137e+08 | R51: ==M51 -> 8.2994137e+08 | S51: 0 | U51: ==IF(OR(L51="标准固收类",L51="非标固收类"),$A$2,"") | V51: ==IF(OR(L51="标准固收类",L51="非标固收类"),EOMONTH($A$2,12),"") | W51: ==IF(OR(L51="标准固收类",L51="非标固收类"),EOMONTH($A$2,A51*12),"") | Y51: ==VLOOKUP(资产明细!K51,配置调整!$B$4:$C$29,2,0) -> 0.015 | Z51: Govt | AD51: ==P51 -> 8.2994137e+08 | AM51: ==IF(OR(L51="标准固收类",L51="非标固收类"),Y51,"") | BF51: ==AM51 | BG51: ==IF(OR(L51="标准固收类",L51="非标固收类"),"",MIN(Y51,2%)) -> 0.015 | BH51: 0 | BI51: 0.85
A52: 3 | B52: 其他信用产品2 | C52: 其他信用产品 | D52: 万能账户 | E52: 固定收益类 | F52: 其他信用产品 | G52: 其他信用产品 | I52: Generic_其他信用产品 | J52: AFS | K52: 其他信用产品 | L52: 标准固收类 | M52: ==IF($D52=配置调整!$A$5,VLOOKUP($K52,配置调整!$B$4:$O$29,6,0)*配置调整!$A$6,IF($D52=配置调整!$A$8,VLOOKUP($K52,配置调整!$B$4:$O$29,6,0)*配置调整!$A$9,IF($D52=配置调整!$A$11,VLOOKUP($K52,配置调整!$B$4:$O$29,6,0)*配置调整!$A$12,FALSE))) -> 3.2773084e+09 | N52: ==M52 -> 3.2773084e+09 | O52: 0 | P52: ==M52 -> 3.2773084e+09 | Q52: ==M52 -> 3.2773084e+09 | R52: ==M52 -> 3.2773084e+09 | S52: 0 | T52: 1 | U52: ==IF(OR(L52="标准固收类",L52="非标固收类"),$A$2,"") -> 45657 | V52: ==IF(OR(L52="标准固收类",L52="非标固收类"),EOMONTH($A$2,12),"") -> 46022 | W52: ==IF(OR(L52="标准固收类",L52="非标固收类"),EOMONTH($A$2,A52*12),"") -> 46752 | X52: 不适用 | Y52: ==VLOOKUP(资产明细!K52,配置调整!$B$4:$C$29,2,0) -> 0.031651664 | Z52: Govt | AA52: MTNIG3+ | AD52: ==P52 -> 3.2773084e+09 | AM52: ==IF(OR(L52="标准固收类",L52="非标固收类"),Y52,"") -> 0.031651664 | BF52: ==AM52 -> 0.031651664 | BG52: ==IF(OR(L52="标准固收类",L52="非标固收类"),"",MIN(Y52,2%)) | BH52: 0 | BI52: 0.85
A53: 5 | B53: 存款2 | C53: 存款 | D53: 万能账户 | E53: 固定收益类 | F53: 存款 | G53: 存款 | I53: Generic_存款 | J53: AFS | K53: 存款 | L53: 标准固收类 | M53: ==IF($D53=配置调整!$A$5,VLOOKUP($K53,配置调整!$B$4:$O$29,6,0)*配置调整!$A$6,IF($D53=配置调整!$A$8,VLOOKUP($K53,配置调整!$B$4:$O$29,6,0)*配置调整!$A$9,IF($D53=配置调整!$A$11,VLOOKUP($K53,配置调整!$B$4:$O$29,6,0)*配置调整!$A$12,FALSE))) -> 1.2022584e+09 | N53: ==M53 -> 1.2022584e+09 | O53: 0 | P53: ==M53 -> 1.2022584e+09 | Q53: ==M53 -> 1.2022584e+09 | R53: ==M53 -> 1.2022584e+09 | S53: 0 | T53: 1 | U53: ==IF(OR(L53="标准固收类",L53="非标固收类"),$A$2,"") -> 45657 | V53: ==IF(OR(L53="标准固收类",L53="非标固收类"),EOMONTH($A$2,12),"") -> 46022 | W53: ==IF(OR(L53="标准固收类",L53="非标固收类"),EOMONTH($A$2,A53*12),"") -> 47483 | X53: 不适用 | Y53: ==VLOOKUP(资产明细!K53,配置调整!$B$4:$C$29,2,0) -> 0.028 | Z53: Govt | AA53: CORIG0-3 | AD53: ==P53 -> 1.2022584e+09 | AM53: ==IF(OR(L53="标准固收类",L53="非标固收类"),Y53,"") -> 0.028 | BF53: ==AM53 -> 0.028 | BG53: ==IF(OR(L53="标准固收类",L53="非标固收类"),"",MIN(Y53,2%)) | BH53: 0 | BI53: 0.85
B54: 不动产2 | C54: 不动产 | D54: 万能账户 | E54: 不动产 | F54: 不动产 | G54: 不动产 | I54: Generic_不动产 | J54: AFS | K54: 不动产 | L54: 权益类 | M54: ==IF($D54=配置调整!$A$5,VLOOKUP($K54,配置调整!$B$4:$O$29,6,0)*配置调整!$A$6,IF($D54=配置调整!$A$8,VLOOKUP($K54,配置调整!$B$4:$O$29,6,0)*配置调整!$A$9,IF($D54=配置调整!$A$11,VLOOKUP($K54,配置调整!$B$4:$O$29,6,0)*配置调整!$A$12,FALSE))) -> 2.6119919e+09 | N54: ==M54 -> 2.6119919e+09 | O54: 0 | P54: ==M54 -> 2.6119919e+09 | Q54: ==M54 -> 2.6119919e+09 | R54: ==M54 -> 2.6119919e+09 | S54: 0 | U54: ==IF(OR(L54="标准固收类",L54="非标固收类"),$A$2,"") | V54: ==IF(OR(L54="标准固收类",L54="非标固收类"),EOMONTH($A$2,12),"") | W54: ==IF(OR(L54="标准固收类",L54="非标固收类"),EOMONTH($A$2,A54*12),"") | Y54: ==VLOOKUP(资产明细!K54,配置调整!$B$4:$C$29,2,0) -> 0.065 | Z54: Govt | AC54: Real Estate Index | AD54: ==P54 -> 2.6119919e+09 | AM54: ==IF(OR(L54="标准固收类",L54="非标固收类"),Y54,"") | BF54: ==AM54 | BG54: ==IF(OR(L54="标准固收类",L54="非标固收类"),"",MIN(Y54,2%)) -> 0.02 | BH54: 0 | BI54: 0.85
A55: 3 | B55: 国债_3Y3 | C55: 国债_3Y | D55: 分红账户 | E55: 固定收益类 | F55: 国债 | G55: 国债_3Y | I55: Generic_国债_3Y | J55: AFS | K55: 国债_3Y | L55: 标准固收类 | M55: ==IF($D55=配置调整!$A$5,VLOOKUP($K55,配置调整!$B$4:$O$29,6,0)*配置调整!$A$6,IF($D55=配置调整!$A$8,VLOOKUP($K55,配置调整!$B$4:$O$29,6,0)*配置调整!$A$9,IF($D55=配置调整!$A$11,VLOOKUP($K55,配置调整!$B$4:$O$29,6,0)*配置调整!$A$12,FALSE))) -> 98950474 | N55: ==M55 -> 98950474 | O55: 0 | P55: ==M55 -> 98950474 | Q55: ==M55 -> 98950474 | R55: ==M55 -> 98950474 | S55: 0 | T55: 1 | U55: ==IF(OR(L55="标准固收类",L55="非标固收类"),$A$2,"") -> 45657 | V55: ==IF(OR(L55="标准固收类",L55="非标固收类"),EOMONTH($A$2,12),"") -> 46022 | W55: ==IF(OR(L55="标准固收类",L55="非标固收类"),EOMONTH($A$2,A55*12),"") -> 46752 | X55: 不适用 | Y55: ==VLOOKUP(资产明细!K55,配置调整!$B$4:$C$29,2,0) -> 0.011872 | Z55: Govt | AD55: ==P55 -> 98950474 | AM55: ==IF(OR(L55="标准固收类",L55="非标固收类"),Y55,"") -> 0.011872 | BF55: ==AM55 -> 0.011872 | BG55: ==IF(OR(L55="标准固收类",L55="非标固收类"),"",MIN(Y55,2%)) | BH55: 0 | BI55: 0.85
A56: 5 | B56: 国债_5Y3 | C56: 国债_5Y | D56: 分红账户 | E56: 固定收益类 | F56: 国债 | G56: 国债_5Y | I56: Generic_国债_5Y | J56: AFS | K56: 国债_5Y | L56: 标准固收类 | M56: ==IF($D56=配置调整!$A$5,VLOOKUP($K56,配置调整!$B$4:$O$29,6,0)*配置调整!$A$6,IF($D56=配置调整!$A$8,VLOOKUP($K56,配置调整!$B$4:$O$29,6,0)*配置调整!$A$9,IF($D56=配置调整!$A$11,VLOOKUP($K56,配置调整!$B$4:$O$29,6,0)*配置调整!$A$12,FALSE))) -> 2.0840971e+08 | N56: ==M56 -> 2.0840971e+08 | O56: 0 | P56: ==M56 -> 2.0840971e+08 | Q56: ==M56 -> 2.0840971e+08 | R56: ==M56 -> 2.0840971e+08 | S56: 0 | T56: 1 | U56: ==IF(OR(L56="标准固收类",L56="非标固收类"),$A$2,"") -> 45657 | V56: ==IF(OR(L56="标准固收类",L56="非标固收类"),EOMONTH($A$2,12),"") -> 46022 | W56: ==IF(OR(L56="标准固收类",L56="非标固收类"),EOMONTH($A$2,A56*12),"") -> 47483 | X56: 不适用 | Y56: ==VLOOKUP(资产明细!K56,配置调整!$B$4:$C$29,2,0) -> 0.014152 | Z56: Govt | AD56: ==P56 -> 2.0840971e+08 | AM56: ==IF(OR(L56="标准固收类",L56="非标固收类"),Y56,"") -> 0.014152 | BF56: ==AM56 -> 0.014152 | BG56: ==IF(OR(L56="标准固收类",L56="非标固收类"),"",MIN(Y56,2%)) | BH56: 0 | BI56: 0.85
A57: 10 | B57: 国债_10Y3 | C57: 国债_10Y | D57: 分红账户 | E57: 固定收益类 | F57: 国债 | G57: 国债_10Y | I57: Generic_国债_10Y | J57: AFS | K57: 国债_10Y | L57: 标准固收类 | M57: ==IF($D57=配置调整!$A$5,VLOOKUP($K57,配置调整!$B$4:$O$29,6,0)*配置调整!$A$6,IF($D57=配置调整!$A$8,VLOOKUP($K57,配置调整!$B$4:$O$29,6,0)*配置调整!$A$9,IF($D57=配置调整!$A$11,VLOOKUP($K57,配置调整!$B$4:$O$29,6,0)*配置调整!$A$12,FALSE))) -> 8.6934539e+08 | N57: ==M57 -> 8.6934539e+08 | O57: 0 | P57: ==M57 -> 8.6934539e+08 | Q57: ==M57 -> 8.6934539e+08 | R57: ==M57 -> 8.6934539e+08 | S57: 0 | T57: 1 | U57: ==IF(OR(L57="标准固收类",L57="非标固收类"),$A$2,"") -> 45657 | V57: ==IF(OR(L57="标准固收类",L57="非标固收类"),EOMONTH($A$2,12),"") -> 46022 | W57: ==IF(OR(L57="标准固收类",L57="非标固收类"),EOMONTH($A$2,A57*12),"") -> 49309 | X57: 不适用 | Y57: ==VLOOKUP(资产明细!K57,配置调整!$B$4:$C$29,2,0) -> 0.016752 | Z57: Govt | AD57: ==P57 -> 8.6934539e+08 | AM57: ==IF(OR(L57="标准固收类",L57="非标固收类"),Y57,"") -> 0.016752 | BF57: ==AM57 -> 0.016752 | BG57: ==IF(OR(L57="标准固收类",L57="非标固收类"),"",MIN(Y57,2%)) | BH57: 0 | BI57: 0.85
A58: 20 | B58: 国债_20Y3 | C58: 国债_20Y | D58: 分红账户 | E58: 固定收益类 | F58: 国债 | G58: 国债_20Y | I58: Generic_国债_20Y | J58: AFS | K58: 国债_20Y | L58: 标准固收类 | M58: ==IF($D58=配置调整!$A$5,VLOOKUP($K58,配置调整!$B$4:$O$29,6,0)*配置调整!$A$6,IF($D58=配置调整!$A$8,VLOOKUP($K58,配置调整!$B$4:$O$29,6,0)*配置调整!$A$9,IF($D58=配置调整!$A$11,VLOOKUP($K58,配置调整!$B$4:$O$29,6,0)*配置调整!$A$12,FALSE))) -> 3.8019957e+09 | N58: ==M58 -> 3.8019957e+09 | O58: 0 | P58: ==M58 -> 3.8019957e+09 | Q58: ==M58 -> 3.8019957e+09 | R58: ==M58 -> 3.8019957e+09 | S58: 0 | T58: 1 | U58: ==IF(OR(L58="标准固收类",L58="非标固收类"),$A$2,"") -> 45657 | V58: ==IF(OR(L58="标准固收类",L58="非标固收类"),EOMONTH($A$2,12),"") -> 46022 | W58: ==IF(OR(L58="标准固收类",L58="非标固收类"),EOMONTH($A$2,A58*12),"") -> 52962 | X58: 不适用 | Y58: ==VLOOKUP(资产明细!K58,配置调整!$B$4:$C$29,2,0) -> 0.019747 | Z58: Govt | AD58: ==P58 -> 3.8019957e+09 | AM58: ==IF(OR(L58="标准固收类",L58="非标固收类"),Y58,"") -> 0.019747 | BF58: ==AM58 -> 0.019747 | BG58: ==IF(OR(L58="标准固收类",L58="非标固收类"),"",MIN(Y58,2%)) | BH58: 0 | BI58: 0.85
A59: 50 | B59: 国债_50Y3 | C59: 国债_50Y | D59: 分红账户 | E59: 固定收益类 | F59: 国债 | G59: 国债_50Y | I59: Generic_国债_50Y | J59: AFS | K59: 国债_50Y | L59: 标准固收类 | M59: ==IF($D59=配置调整!$A$5,VLOOKUP($K59,配置调整!$B$4:$O$29,6,0)*配置调整!$A$6,IF($D59=配置调整!$A$8,VLOOKUP($K59,配置调整!$B$4:$O$29,6,0)*配置调整!$A$9,IF($D59=配置调整!$A$11,VLOOKUP($K59,配置调整!$B$4:$O$29,6,0)*配置调整!$A$12,FALSE))) -> 5.5148303e+09 | N59: ==M59 -> 5.5148303e+09 | O59: 0 | P59: ==M59 -> 5.5148303e+09 | Q59: ==M59 -> 5.5148303e+09 | R59: ==M59 -> 5.5148303e+09 | S59: 0 | T59: 1 | U59: ==IF(OR(L59="标准固收类",L59="非标固收类"),$A$2,"") -> 45657 | V59: ==IF(OR(L59="标准固收类",L59="非标固收类"),EOMONTH($A$2,12),"") -> 46022 | W59: ==IF(OR(L59="标准固收类",L59="非标固收类"),EOMONTH($A$2,A59*12),"") -> 63919 | X59: 不适用 | Y59: ==VLOOKUP(资产明细!K59,配置调整!$B$4:$C$29,2,0) -> 0.019875 | Z59: Govt | AD59: ==P59 -> 5.5148303e+09 | AM59: ==IF(OR(L59="标准固收类",L59="非标固收类"),Y59,"") -> 0.019875 | BF59: ==AM59 -> 0.019875 | BG59: ==IF(OR(L59="标准固收类",L59="非标固收类"),"",MIN(Y59,2%)) | BH59: 0 | BI59: 0.85
A60: 3 | B60: 高等级信用债_3Y3 | C60: 高等级信用债_3Y | D60: 分红账户 | E60: 固定收益类 | F60: 高等级信用债 | G60: 高等级信用债_3Y | I60: Generic_高等级信用债_3Y | J60: AFS | K60: 信用债_3Y | L60: 标准固收类 | M60: ==IF($D60=配置调整!$A$5,VLOOKUP($K60,配置调整!$B$4:$O$29,6,0)*配置调整!$A$6,IF($D60=配置调整!$A$8,VLOOKUP($K60,配置调整!$B$4:$O$29,6,0)*配置调整!$A$9,IF($D60=配置调整!$A$11,VLOOKUP($K60,配置调整!$B$4:$O$29,6,0)*配置调整!$A$12,FALSE))) -> 1.8185257e+09 | N60: ==M60 -> 1.8185257e+09 | O60: 0 | P60: ==M60 -> 1.8185257e+09 | Q60: ==M60 -> 1.8185257e+09 | R60: ==M60 -> 1.8185257e+09 | S60: 0 | T60: 1 | U60: ==IF(OR(L60="标准固收类",L60="非标固收类"),$A$2,"") -> 45657 | V60: ==IF(OR(L60="标准固收类",L60="非标固收类"),EOMONTH($A$2,12),"") -> 46022 | W60: ==IF(OR(L60="标准固收类",L60="非标固收类"),EOMONTH($A$2,A60*12),"") -> 46752 | X60: 不适用 | Y60: ==VLOOKUP(资产明细!K60,配置调整!$B$4:$C$29,2,0) -> 0.017501 | Z60: Govt | AA60: CORIG0-3 | AD60: ==P60 -> 1.8185257e+09 | AM60: ==IF(OR(L60="标准固收类",L60="非标固收类"),Y60,"") -> 0.017501 | BF60: ==AM60 -> 0.017501 | BG60: ==IF(OR(L60="标准固收类",L60="非标固收类"),"",MIN(Y60,2%)) | BH60: 0 | BI60: 0.85
A61: 5 | B61: 高等级信用债_5Y3 | C61: 高等级信用债_5Y | D61: 分红账户 | E61: 固定收益类 | F61: 高等级信用债 | G61: 高等级信用债_5Y | I61: Generic_高等级信用债_5Y | J61: AFS | K61: 信用债_5Y | L61: 标准固收类 | M61: ==IF($D61=配置调整!$A$5,VLOOKUP($K61,配置调整!$B$4:$O$29,6,0)*配置调整!$A$6,IF($D61=配置调整!$A$8,VLOOKUP($K61,配置调整!$B$4:$O$29,6,0)*配置调整!$A$9,IF($D61=配置调整!$A$11,VLOOKUP($K61,配置调整!$B$4:$O$29,6,0)*配置调整!$A$12,FALSE))) -> 1.5992956e+08 | N61: ==M61 -> 1.5992956e+08 | O61: 0 | P61: ==M61 -> 1.5992956e+08 | Q61: ==M61 -> 1.5992956e+08 | R61: ==M61 -> 1.5992956e+08 | S61: 0 | T61: 1 | U61: ==IF(OR(L61="标准固收类",L61="非标固收类"),$A$2,"") -> 45657 | V61: ==IF(OR(L61="标准固收类",L61="非标固收类"),EOMONTH($A$2,12),"") -> 46022 | W61: ==IF(OR(L61="标准固收类",L61="非标固收类"),EOMONTH($A$2,A61*12),"") -> 47483 | X61: 不适用 | Y61: ==VLOOKUP(资产明细!K61,配置调整!$B$4:$C$29,2,0) -> 0.018727 | Z61: Govt | AA61: CORIG3+ | AD61: ==P61 -> 1.5992956e+08 | AM61: ==IF(OR(L61="标准固收类",L61="非标固收类"),Y61,"") -> 0.018727 | BF61: ==AM61 -> 0.018727 | BG61: ==IF(OR(L61="标准固收类",L61="非标固收类"),"",MIN(Y61,2%)) | BH61: 0 | BI61: 0.85
A62: 10 | B62: 高等级信用债_10Y3 | C62: 高等级信用债_10Y | D62: 分红账户 | E62: 固定收益类 | F62: 高等级信用债 | G62: 高等级信用债_10Y | I62: Generic_高等级信用债_10Y | J62: AFS | K62: 信用债_10Y | L62: 标准固收类 | M62: ==IF($D62=配置调整!$A$5,VLOOKUP($K62,配置调整!$B$4:$O$29,6,0)*配置调整!$A$6,IF($D62=配置调整!$A$8,VLOOKUP($K62,配置调整!$B$4:$O$29,6,0)*配置调整!$A$9,IF($D62=配置调整!$A$11,VLOOKUP($K62,配置调整!$B$4:$O$29,6,0)*配置调整!$A$12,FALSE))) -> 1.0469498e+09 | N62: ==M62 -> 1.0469498e+09 | O62: 0 | P62: ==M62 -> 1.0469498e+09 | Q62: ==M62 -> 1.0469498e+09 | R62: ==M62 -> 1.0469498e+09 | S62: 0 | T62: 1 | U62: ==IF(OR(L62="标准固收类",L62="非标固收类"),$A$2,"") -> 45657 | V62: ==IF(OR(L62="标准固收类",L62="非标固收类"),EOMONTH($A$2,12),"") -> 46022 | W62: ==IF(OR(L62="标准固收类",L62="非标固收类"),EOMONTH($A$2,A62*12),"") -> 49309 | X62: 不适用 | Y62: ==VLOOKUP(资产明细!K62,配置调整!$B$4:$C$29,2,0) -> 0.021173 | Z62: Govt | AA62: CORIG3+ | AD62: ==P62 -> 1.0469498e+09 | AM62: ==IF(OR(L62="标准固收类",L62="非标固收类"),Y62,"") -> 0.021173 | BF62: ==AM62 -> 0.021173 | BG62: ==IF(OR(L62="标准固收类",L62="非标固收类"),"",MIN(Y62,2%)) | BH62: 0 | BI62: 0.85
A63: 3 | B63: 非标资产_3Y3 | C63: 非标资产_3Y | D63: 分红账户 | E63: 固定收益类 | F63: 非标资产 | G63: 非标资产_3Y | I63: Generic_非标资产_3Y | J63: AFS | K63: 非标资产_3Y | L63: 非标固收类 | M63: ==IF($D63=配置调整!$A$5,VLOOKUP($K63,配置调整!$B$4:$O$29,6,0)*配置调整!$A$6,IF($D63=配置调整!$A$8,VLOOKUP($K63,配置调整!$B$4:$O$29,6,0)*配置调整!$A$9,IF($D63=配置调整!$A$11,VLOOKUP($K63,配置调整!$B$4:$O$29,6,0)*配置调整!$A$12,FALSE))) -> 7.6756732e+08 | N63: ==M63 -> 7.6756732e+08 | O63: 0 | P63: ==M63 -> 7.6756732e+08 | Q63: ==M63 -> 7.6756732e+08 | R63: ==M63 -> 7.6756732e+08 | S63: 0 | T63: 1 | U63: ==IF(OR(L63="标准固收类",L63="非标固收类"),$A$2,"") -> 45657 | V63: ==IF(OR(L63="标准固收类",L63="非标固收类"),EOMONTH($A$2,12),"") -> 46022 | W63: ==IF(OR(L63="标准固收类",L63="非标固收类"),EOMONTH($A$2,A63*12),"") -> 46752 | X63: 不适用 | Y63: ==VLOOKUP(资产明细!K63,配置调整!$B$4:$C$29,2,0) -> 0.024290322 | Z63: Govt | AA63: CORIG3+ | AB63: IP 3Y | AD63: ==P63 -> 7.6756732e+08 | AM63: ==IF(OR(L63="标准固收类",L63="非标固收类"),Y63,"") -> 0.024290322 | BF63: ==AM63 -> 0.024290322 | BG63: ==IF(OR(L63="标准固收类",L63="非标固收类"),"",MIN(Y63,2%)) | BH63: 0 | BI63: 0.85
A64: 5 | B64: 非标资产_5Y3 | C64: 非标资产_5Y | D64: 分红账户 | E64: 固定收益类 | F64: 非标资产 | G64: 非标资产_5Y | I64: Generic_非标资产_5Y | J64: AFS | K64: 非标资产_5Y | L64: 非标固收类 | M64: ==IF($D64=配置调整!$A$5,VLOOKUP($K64,配置调整!$B$4:$O$29,6,0)*配置调整!$A$6,IF($D64=配置调整!$A$8,VLOOKUP($K64,配置调整!$B$4:$O$29,6,0)*配置调整!$A$9,IF($D64=配置调整!$A$11,VLOOKUP($K64,配置调整!$B$4:$O$29,6,0)*配置调整!$A$12,FALSE))) -> 5.0298086e+08 | N64: ==M64 -> 5.0298086e+08 | O64: 0 | P64: ==M64 -> 5.0298086e+08 | Q64: ==M64 -> 5.0298086e+08 | R64: ==M64 -> 5.0298086e+08 | S64: 0 | T64: 1 | U64: ==IF(OR(L64="标准固收类",L64="非标固收类"),$A$2,"") -> 45657 | V64: ==IF(OR(L64="标准固收类",L64="非标固收类"),EOMONTH($A$2,12),"") -> 46022 | W64: ==IF(OR(L64="标准固收类",L64="非标固收类"),EOMONTH($A$2,A64*12),"") -> 47483 | X64: 不适用 | Y64: ==VLOOKUP(资产明细!K64,配置调整!$B$4:$C$29,2,0) -> 0.025629035 | Z64: Govt | AA64: CORIG3+ | AB64: IP 5Y | AD64: ==P64 -> 5.0298086e+08 | AM64: ==IF(OR(L64="标准固收类",L64="非标固收类"),Y64,"") -> 0.025629035 | BF64: ==AM64 -> 0.025629035 | BG64: ==IF(OR(L64="标准固收类",L64="非标固收类"),"",MIN(Y64,2%)) | BH64: 0 | BI64: 0.85
B65: A股3 | C65: A股 | D65: 分红账户 | E65: 权益类 | F65: 上市普通股票 | G65: A股 | I65: Generic_A股 | J65: AFS | K65: A股 | L65: 权益类 | M65: ==IF($D65=配置调整!$A$5,VLOOKUP($K65,配置调整!$B$4:$O$29,6,0)*配置调整!$A$6,IF($D65=配置调整!$A$8,VLOOKUP($K65,配置调整!$B$4:$O$29,6,0)*配置调整!$A$9,IF($D65=配置调整!$A$11,VLOOKUP($K65,配置调整!$B$4:$O$29,6,0)*配置调整!$A$12,FALSE))) -> 267518.43 | N65: ==M65 -> 267518.43 | O65: 0 | P65: ==M65 -> 267518.43 | Q65: ==M65 -> 267518.43 | R65: ==M65 -> 267518.43 | S65: 0 | U65: ==IF(OR(L65="标准固收类",L65="非标固收类"),$A$2,"") | V65: ==IF(OR(L65="标准固收类",L65="非标固收类"),EOMONTH($A$2,12),"") | W65: ==IF(OR(L65="标准固收类",L65="非标固收类"),EOMONTH($A$2,A65*12),"") | Y65: ==VLOOKUP(资产明细!K65,配置调整!$B$4:$C$29,2,0) -> 0.06 | Z65: Govt | AC65: A Shares | AD65: ==P65 -> 267518.43 | AM65: ==IF(OR(L65="标准固收类",L65="非标固收类"),Y65,"") | BF65: ==AM65 | BG65: ==IF(OR(L65="标准固收类",L65="非标固收类"),"",MIN(Y65,2%)) -> 0.02 | BH65: 0 | BI65: 0.85
B66: H股3 | C66: H股 | D66: 分红账户 | E66: 权益类 | F66: 上市普通股票 | G66: H股 | I66: Generic_H股 | J66: AFS | K66: H股 | L66: 权益类 | M66: ==IF($D66=配置调整!$A$5,VLOOKUP($K66,配置调整!$B$4:$O$29,6,0)*配置调整!$A$6,IF($D66=配置调整!$A$8,VLOOKUP($K66,配置调整!$B$4:$O$29,6,0)*配置调整!$A$9,IF($D66=配置调整!$A$11,VLOOKUP($K66,配置调整!$B$4:$O$29,6,0)*配置调整!$A$12,FALSE))) -> 90343545 | N66: ==M66 -> 90343545 | O66: 0 | P66: ==M66 -> 90343545 | Q66: ==M66 -> 90343545 | R66: ==M66 -> 90343545 | S66: 0 | U66: ==IF(OR(L66="标准固收类",L66="非标固收类"),$A$2,"") | V66: ==IF(OR(L66="标准固收类",L66="非标固收类"),EOMONTH($A$2,12),"") | W66: ==IF(OR(L66="标准固收类",L66="非标固收类"),EOMONTH($A$2,A66*12),"") | Y66: ==VLOOKUP(资产明细!K66,配置调整!$B$4:$C$29,2,0) -> 0.07 | Z66: Govt | AC66: H Shares | AD66: ==P66 -> 90343545 | AM66: ==IF(OR(L66="标准固收类",L66="非标固收类"),Y66,"") | BF66: ==AM66 | BG66: ==IF(OR(L66="标准固收类",L66="非标固收类"),"",MIN(Y66,2%)) -> 0.02 | BH66: 0 | BI66: 0.85
B67: MSCI发达市场3 | C67: MSCI发达市场 | D67: 分红账户 | E67: 权益类 | F67: 上市普通股票 | G67: MSCI发达市场 | I67: Generic_MSCI发达市场 | J67: AFS | K67: MSCI发达市场 | L67: 权益类 | M67: ==IF($D67=配置调整!$A$5,VLOOKUP($K67,配置调整!$B$4:$O$29,6,0)*配置调整!$A$6,IF($D67=配置调整!$A$8,VLOOKUP($K67,配置调整!$B$4:$O$29,6,0)*配置调整!$A$9,IF($D67=配置调整!$A$11,VLOOKUP($K67,配置调整!$B$4:$O$29,6,0)*配置调整!$A$12,FALSE))) -> 1.2721636e+08 | N67: ==M67 -> 1.2721636e+08 | O67: 0 | P67: ==M67 -> 1.2721636e+08 | Q67: ==M67 -> 1.2721636e+08 | R67: ==M67 -> 1.2721636e+08 | S67: 0 | U67: ==IF(OR(L67="标准固收类",L67="非标固收类"),$A$2,"") | V67: ==IF(OR(L67="标准固收类",L67="非标固收类"),EOMONTH($A$2,12),"") | W67: ==IF(OR(L67="标准固收类",L67="非标固收类"),EOMONTH($A$2,A67*12),"") | Y67: ==VLOOKUP(资产明细!K67,配置调整!$B$4:$C$29,2,0) -> 0.08 | Z67: Govt | AC67: MSCI DM Shares | AD67: ==P67 -> 1.2721636e+08 | AM67: ==IF(OR(L67="标准固收类",L67="非标固收类"),Y67,"") | BF67: ==AM67 | BG67: ==IF(OR(L67="标准固收类",L67="非标固收类"),"",MIN(Y67,2%)) -> 0.02 | BH67: 0 | BI67: 0.85
B68: MSCI新兴市场3 | C68: MSCI新兴市场 | D68: 分红账户 | E68: 权益类 | F68: 上市普通股票 | G68: MSCI新兴市场 | I68: Generic_MSCI新兴市场 | J68: AFS | K68: MSCI新兴市场 | L68: 权益类 | M68: ==IF($D68=配置调整!$A$5,VLOOKUP($K68,配置调整!$B$4:$O$29,6,0)*配置调整!$A$6,IF($D68=配置调整!$A$8,VLOOKUP($K68,配置调整!$B$4:$O$29,6,0)*配置调整!$A$9,IF($D68=配置调整!$A$11,VLOOKUP($K68,配置调整!$B$4:$O$29,6,0)*配置调整!$A$12,FALSE))) -> 6.7889524e+08 | N68: ==M68 -> 6.7889524e+08 | O68: 0 | P68: ==M68 -> 6.7889524e+08 | Q68: ==M68 -> 6.7889524e+08 | R68: ==M68 -> 6.7889524e+08 | S68: 0 | U68: ==IF(OR(L68="标准固收类",L68="非标固收类"),$A$2,"") | V68: ==IF(OR(L68="标准固收类",L68="非标固收类"),EOMONTH($A$2,12),"") | W68: ==IF(OR(L68="标准固收类",L68="非标固收类"),EOMONTH($A$2,A68*12),"") | Y68: ==VLOOKUP(资产明细!K68,配置调整!$B$4:$C$29,2,0) -> 0.085 | Z68: Govt | AC68: MSCI EM Shares | AD68: ==P68 -> 6.7889524e+08 | AM68: ==IF(OR(L68="标准固收类",L68="非标固收类"),Y68,"") | BF68: ==AM68 | BG68: ==IF(OR(L68="标准固收类",L68="非标固收类"),"",MIN(Y68,2%)) -> 0.02 | BH68: 0 | BI68: 0.85
B69: 债券基金3 | C69: 债券基金 | D69: 分红账户 | E69: 权益类 | F69: 债券基金 | G69: 债券基金 | I69: Generic_债券基金 | J69: AFS | K69: 债券基金 | L69: 权益类 | M69: ==IF($D69=配置调整!$A$5,VLOOKUP($K69,配置调整!$B$4:$O$29,6,0)*配置调整!$A$6,IF($D69=配置调整!$A$8,VLOOKUP($K69,配置调整!$B$4:$O$29,6,0)*配置调整!$A$9,IF($D69=配置调整!$A$11,VLOOKUP($K69,配置调整!$B$4:$O$29,6,0)*配置调整!$A$12,FALSE))) -> 267518.43 | N69: ==M69 -> 267518.43 | O69: 0 | P69: ==M69 -> 267518.43 | Q69: ==M69 -> 267518.43 | R69: ==M69 -> 267518.43 | S69: 0 | U69: ==IF(OR(L69="标准固收类",L69="非标固收类"),$A$2,"") | V69: ==IF(OR(L69="标准固收类",L69="非标固收类"),EOMONTH($A$2,12),"") | W69: ==IF(OR(L69="标准固收类",L69="非标固收类"),EOMONTH($A$2,A69*12),"") | Y69: ==VLOOKUP(资产明细!K69,配置调整!$B$4:$C$29,2,0) -> 0.028487288 | Z69: Govt | AC69: FI Fund | AD69: ==P69 -> 267518.43 | AM69: ==IF(OR(L69="标准固收类",L69="非标固收类"),Y69,"") | BF69: ==AM69 | BG69: ==IF(OR(L69="标准固收类",L69="非标固收类"),"",MIN(Y69,2%)) -> 0.02 | BH69: 0 | BI69: 0.85
B70: 货币基金3 | C70: 货币基金 | D70: 分红账户 | E70: 权益类 | F70: 货币基金 | G70: 货币基金 | I70: Generic_货币基金 | J70: AFS | K70: 货币基金 | L70: 权益类 | M70: ==IF($D70=配置调整!$A$5,VLOOKUP($K70,配置调整!$B$4:$O$29,6,0)*配置调整!$A$6,IF($D70=配置调整!$A$8,VLOOKUP($K70,配置调整!$B$4:$O$29,6,0)*配置调整!$A$9,IF($D70=配置调整!$A$11,VLOOKUP($K70,配置调整!$B$4:$O$29,6,0)*配置调整!$A$12,FALSE))) -> 267518.43 | N70: ==M70 -> 267518.43 | O70: 0 | P70: ==M70 -> 267518.43 | Q70: ==M70 -> 267518.43 | R70: ==M70 -> 267518.43 | S70: 0 | U70: ==IF(OR(L70="标准固收类",L70="非标固收类"),$A$2,"") | V70: ==IF(OR(L70="标准固收类",L70="非标固收类"),EOMONTH($A$2,12),"") | W70: ==IF(OR(L70="标准固收类",L70="非标固收类"),EOMONTH($A$2,A70*12),"") | Y70: ==VLOOKUP(资产明细!K70,配置调整!$B$4:$C$29,2,0) -> 0.015 | Z70: Govt | AC70: Monetary Fund | AD70: ==P70 -> 267518.43 | AM70: ==IF(OR(L70="标准固收类",L70="非标固收类"),Y70,"") | BF70: ==AM70 | BG70: ==IF(OR(L70="标准固收类",L70="非标固收类"),"",MIN(Y70,2%)) -> 0.015 | BH70: 0 | BI70: 0.85
B71: 混合基金3 | C71: 混合基金 | D71: 分红账户 | E71: 权益类 | F71: 混合基金 | G71: 混合基金 | I71: Generic_混合基金 | J71: AFS | K71: 混合基金 | L71: 权益类 | M71: ==IF($D71=配置调整!$A$5,VLOOKUP($K71,配置调整!$B$4:$O$29,6,0)*配置调整!$A$6,IF($D71=配置调整!$A$8,VLOOKUP($K71,配置调整!$B$4:$O$29,6,0)*配置调整!$A$9,IF($D71=配置调整!$A$11,VLOOKUP($K71,配置调整!$B$4:$O$29,6,0)*配置调整!$A$12,FALSE))) -> 2.8761567e+08 | N71: ==M71 -> 2.8761567e+08 | O71: 0 | P71: ==M71 -> 2.8761567e+08 | Q71: ==M71 -> 2.8761567e+08 | R71: ==M71 -> 2.8761567e+08 | S71: 0 | U71: ==IF(OR(L71="标准固收类",L71="非标固收类"),$A$2,"") | V71: ==IF(OR(L71="标准固收类",L71="非标固收类"),EOMONTH($A$2,12),"") | W71: ==IF(OR(L71="标准固收类",L71="非标固收类"),EOMONTH($A$2,A71*12),"") | Y71: ==VLOOKUP(资产明细!K71,配置调整!$B$4:$C$29,2,0) -> 0.05 | Z71: Govt | AC71: Mixed Fund | AD71: ==P71 -> 2.8761567e+08 | AM71: ==IF(OR(L71="标准固收类",L71="非标固收类"),Y71,"") | BF71: ==AM71 | BG71: ==IF(OR(L71="标准固收类",L71="非标固收类"),"",MIN(Y71,2%)) -> 0.02 | BH71: 0 | BI71: 0.85
B72: 股票基金3 | C72: 股票基金 | D72: 分红账户 | E72: 权益类 | F72: 股票基金 | G72: 股票基金 | I72: Generic_股票基金 | J72: AFS | K72: 股票基金 | L72: 权益类 | M72: ==IF($D72=配置调整!$A$5,VLOOKUP($K72,配置调整!$B$4:$O$29,6,0)*配置调整!$A$6,IF($D72=配置调整!$A$8,VLOOKUP($K72,配置调整!$B$4:$O$29,6,0)*配置调整!$A$9,IF($D72=配置调整!$A$11,VLOOKUP($K72,配置调整!$B$4:$O$29,6,0)*配置调整!$A$12,FALSE))) -> 267518.43 | N72: ==M72 -> 267518.43 | O72: 0 | P72: ==M72 -> 267518.43 | Q72: ==M72 -> 267518.43 | R72: ==M72 -> 267518.43 | S72: 0 | U72: ==IF(OR(L72="标准固收类",L72="非标固收类"),$A$2,"") | V72: ==IF(OR(L72="标准固收类",L72="非标固收类"),EOMONTH($A$2,12),"") | W72: ==IF(OR(L72="标准固收类",L72="非标固收类"),EOMONTH($A$2,A72*12),"") | Y72: ==VLOOKUP(资产明细!K72,配置调整!$B$4:$C$29,2,0) -> 0.055 | Z72: Govt | AC72: Equity Fund | AD72: ==P72 -> 267518.43 | AM72: ==IF(OR(L72="标准固收类",L72="非标固收类"),Y72,"") | BF72: ==AM72 | BG72: 0.085446062 | BH72: 0 | BI72: 0.85
B73: 优先股3 | C73: 优先股 | D73: 分红账户 | E73: 权益类 | F73: 优先股 | G73: 优先股 | I73: Generic_优先股 | J73: AFS | K73: 优先股 | L73: 权益类 | M73: ==IF($D73=配置调整!$A$5,VLOOKUP($K73,配置调整!$B$4:$O$29,6,0)*配置调整!$A$6,IF($D73=配置调整!$A$8,VLOOKUP($K73,配置调整!$B$4:$O$29,6,0)*配置调整!$A$9,IF($D73=配置调整!$A$11,VLOOKUP($K73,配置调整!$B$4:$O$29,6,0)*配置调整!$A$12,FALSE))) -> 267518.43 | N73: ==M73 -> 267518.43 | O73: 0 | P73: ==M73 -> 267518.43 | Q73: ==M73 -> 267518.43 | R73: ==M73 -> 267518.43 | S73: 0 | U73: ==IF(OR(L73="标准固收类",L73="非标固收类"),$A$2,"") | V73: ==IF(OR(L73="标准固收类",L73="非标固收类"),EOMONTH($A$2,12),"") | W73: ==IF(OR(L73="标准固收类",L73="非标固收类"),EOMONTH($A$2,A73*12),"") | Y73: ==VLOOKUP(资产明细!K73,配置调整!$B$4:$C$29,2,0) -> 0.043 | Z73: Govt | AC73: LT Equity | AD73: ==P73 -> 267518.43 | AM73: ==IF(OR(L73="标准固收类",L73="非标固收类"),Y73,"") | BF73: ==AM73 | BG73: ==IF(OR(L73="标准固收类",L73="非标固收类"),"",MIN(Y73,2%)) -> 0.02 | BH73: 0 | BI73: 0.85
B74: 长期股权投资3 | C74: 长期股权投资 | D74: 分红账户 | E74: 权益类 | F74: 股权投资 | G74: 长期股权投资 | I74: Generic_长期股权投资 | J74: AFS | K74: 长期股权投资 | L74: 权益类 | M74: ==IF($D74=配置调整!$A$5,VLOOKUP($K74,配置调整!$B$4:$O$29,6,0)*配置调整!$A$6,IF($D74=配置调整!$A$8,VLOOKUP($K74,配置调整!$B$4:$O$29,6,0)*配置调整!$A$9,IF($D74=配置调整!$A$11,VLOOKUP($K74,配置调整!$B$4:$O$29,6,0)*配置调整!$A$12,FALSE))) -> 267518.43 | N74: ==M74 -> 267518.43 | O74: 0 | P74: ==M74 -> 267518.43 | Q74: ==M74 -> 267518.43 | R74: ==M74 -> 267518.43 | S74: 0 | U74: ==IF(OR(L74="标准固收类",L74="非标固收类"),$A$2,"") | V74: ==IF(OR(L74="标准固收类",L74="非标固收类"),EOMONTH($A$2,12),"") | W74: ==IF(OR(L74="标准固收类",L74="非标固收类"),EOMONTH($A$2,A74*12),"") | Y74: ==VLOOKUP(资产明细!K74,配置调整!$B$4:$C$29,2,0) -> 0.05 | Z74: Govt | AC74: LT Equity | AD74: ==P74 -> 267518.43 | AM74: ==IF(OR(L74="标准固收类",L74="非标固收类"),Y74,"") | BF74: ==AM74 | BG74: ==IF(OR(L74="标准固收类",L74="非标固收类"),"",MIN(Y74,2%)) -> 0.02 | BH74: 0 | BI74: 0.85
B75: 未上市股权3 | C75: 未上市股权 | D75: 分红账户 | E75: 权益类 | F75: 股权投资 | G75: 未上市股权 | I75: Generic_未上市股权 | J75: AFS | K75: 未上市股权 | L75: 权益类 | M75: ==IF($D75=配置调整!$A$5,VLOOKUP($K75,配置调整!$B$4:$O$29,6,0)*配置调整!$A$6,IF($D75=配置调整!$A$8,VLOOKUP($K75,配置调整!$B$4:$O$29,6,0)*配置调整!$A$9,IF($D75=配置调整!$A$11,VLOOKUP($K75,配置调整!$B$4:$O$29,6,0)*配置调整!$A$12,FALSE))) -> 1.6745297e+08 | N75: ==M75 -> 1.6745297e+08 | O75: 0 | P75: ==M75 -> 1.6745297e+08 | Q75: ==M75 -> 1.6745297e+08 | R75: ==M75 -> 1.6745297e+08 | S75: 0 | U75: ==IF(OR(L75="标准固收类",L75="非标固收类"),$A$2,"") | V75: ==IF(OR(L75="标准固收类",L75="非标固收类"),EOMONTH($A$2,12),"") | W75: ==IF(OR(L75="标准固收类",L75="非标固收类"),EOMONTH($A$2,A75*12),"") | Y75: ==VLOOKUP(资产明细!K75,配置调整!$B$4:$C$29,2,0) -> 0.086 | Z75: Govt | AC75: LT Equity | AD75: ==P75 -> 1.6745297e+08 | AM75: ==IF(OR(L75="标准固收类",L75="非标固收类"),Y75,"") | BF75: ==AM75 | BG75: ==IF(OR(L75="标准固收类",L75="非标固收类"),"",MIN(Y75,2%)) -> 0.02 | BH75: 0 | BI75: 0.85
B76: 固收产品3 | C76: 固收产品 | D76: 分红账户 | E76: 固定收益类 | F76: 固收产品 | G76: 固收产品 | I76: Generic_固收产品 | J76: AFS | K76: 固收产品 | L76: 权益类 | M76: ==IF($D76=配置调整!$A$5,VLOOKUP($K76,配置调整!$B$4:$O$29,6,0)*配置调整!$A$6,IF($D76=配置调整!$A$8,VLOOKUP($K76,配置调整!$B$4:$O$29,6,0)*配置调整!$A$9,IF($D76=配置调整!$A$11,VLOOKUP($K76,配置调整!$B$4:$O$29,6,0)*配置调整!$A$12,FALSE))) -> 2.6877295e+09 | N76: ==M76 -> 2.6877295e+09 | O76: 0 | P76: ==M76 -> 2.6877295e+09 | Q76: ==M76 -> 2.6877295e+09 | R76: ==M76 -> 2.6877295e+09 | S76: 0 | U76: ==IF(OR(L76="标准固收类",L76="非标固收类"),$A$2,"") | V76: ==IF(OR(L76="标准固收类",L76="非标固收类"),EOMONTH($A$2,12),"") | W76: ==IF(OR(L76="标准固收类",L76="非标固收类"),EOMONTH($A$2,A76*12),"") | Y76: ==VLOOKUP(资产明细!K76,配置调整!$B$4:$C$29,2,0) -> 0.03481604 | Z76: Govt | AC76: FI Fund | AD76: ==P76 -> 2.6877295e+09 | AM76: ==IF(OR(L76="标准固收类",L76="非标固收类"),Y76,"") | BF76: ==AM76 | BG76: ==IF(OR(L76="标准固收类",L76="非标固收类"),"",MIN(Y76,2%)) -> 0.02 | BH76: 0 | BI76: 0.85
B77: 现金类3 | C77: 现金类 | D77: 分红账户 | E77: 现金类 | F77: 现金类 | G77: 现金类 | I77: Generic_现金类 | J77: AFS | K77: 现金类 | L77: 现金类 | M77: ==IF($D77=配置调整!$A$5,VLOOKUP($K77,配置调整!$B$4:$O$29,6,0)*配置调整!$A$6,IF($D77=配置调整!$A$8,VLOOKUP($K77,配置调整!$B$4:$O$29,6,0)*配置调整!$A$9,IF($D77=配置调整!$A$11,VLOOKUP($K77,配置调整!$B$4:$O$29,6,0)*配置调整!$A$12,FALSE))) -> 8.2994137e+08 | N77: ==M77 -> 8.2994137e+08 | O77: 0 | P77: ==M77 -> 8.2994137e+08 | Q77: ==M77 -> 8.2994137e+08 | R77: ==M77 -> 8.2994137e+08 | S77: 0 | U77: ==IF(OR(L77="标准固收类",L77="非标固收类"),$A$2,"") | V77: ==IF(OR(L77="标准固收类",L77="非标固收类"),EOMONTH($A$2,12),"") | W77: ==IF(OR(L77="标准固收类",L77="非标固收类"),EOMONTH($A$2,A77*12),"") | Y77: ==VLOOKUP(资产明细!K77,配置调整!$B$4:$C$29,2,0) -> 0.015 | Z77: Govt | AD77: ==P77 -> 8.2994137e+08 | AM77: ==IF(OR(L77="标准固收类",L77="非标固收类"),Y77,"") | BF77: ==AM77 | BG77: ==IF(OR(L77="标准固收类",L77="非标固收类"),"",MIN(Y77,2%)) -> 0.015 | BH77: 0 | BI77: 0.85
A78: 3 | B78: 其他信用产品3 | C78: 其他信用产品 | D78: 分红账户 | E78: 固定收益类 | F78: 其他信用产品 | G78: 其他信用产品 | I78: Generic_其他信用产品 | J78: AFS | K78: 其他信用产品 | L78: 标准固收类 | M78: ==IF($D78=配置调整!$A$5,VLOOKUP($K78,配置调整!$B$4:$O$29,6,0)*配置调整!$A$6,IF($D78=配置调整!$A$8,VLOOKUP($K78,配置调整!$B$4:$O$29,6,0)*配置调整!$A$9,IF($D78=配置调整!$A$11,VLOOKUP($K78,配置调整!$B$4:$O$29,6,0)*配置调整!$A$12,FALSE))) -> 3.2773084e+09 | N78: ==M78 -> 3.2773084e+09 | O78: 0 | P78: ==M78 -> 3.2773084e+09 | Q78: ==M78 -> 3.2773084e+09 | R78: ==M78 -> 3.2773084e+09 | S78: 0 | T78: 1 | U78: ==IF(OR(L78="标准固收类",L78="非标固收类"),$A$2,"") -> 45657 | V78: ==IF(OR(L78="标准固收类",L78="非标固收类"),EOMONTH($A$2,12),"") -> 46022 | W78: ==IF(OR(L78="标准固收类",L78="非标固收类"),EOMONTH($A$2,A78*12),"") -> 46752 | X78: 不适用 | Y78: ==VLOOKUP(资产明细!K78,配置调整!$B$4:$C$29,2,0) -> 0.031651664 | Z78: Govt | AA78: MTNIG3+ | AD78: ==P78 -> 3.2773084e+09 | AM78: ==IF(OR(L78="标准固收类",L78="非标固收类"),Y78,"") -> 0.031651664 | BF78: ==AM78 -> 0.031651664 | BG78: ==IF(OR(L78="标准固收类",L78="非标固收类"),"",MIN(Y78,2%)) | BH78: 0 | BI78: 0.85
A79: 5 | B79: 存款3 | C79: 存款 | D79: 分红账户 | E79: 固定收益类 | F79: 存款 | G79: 存款 | I79: Generic_存款 | J79: AFS | K79: 存款 | L79: 标准固收类 | M79: ==IF($D79=配置调整!$A$5,VLOOKUP($K79,配置调整!$B$4:$O$29,6,0)*配置调整!$A$6,IF($D79=配置调整!$A$8,VLOOKUP($K79,配置调整!$B$4:$O$29,6,0)*配置调整!$A$9,IF($D79=配置调整!$A$11,VLOOKUP($K79,配置调整!$B$4:$O$29,6,0)*配置调整!$A$12,FALSE))) -> 1.2022584e+09 | N79: ==M79 -> 1.2022584e+09 | O79: 0 | P79: ==M79 -> 1.2022584e+09 | Q79: ==M79 -> 1.2022584e+09 | R79: ==M79 -> 1.2022584e+09 | S79: 0 | T79: 1 | U79: ==IF(OR(L79="标准固收类",L79="非标固收类"),$A$2,"") -> 45657 | V79: ==IF(OR(L79="标准固收类",L79="非标固收类"),EOMONTH($A$2,12),"") -> 46022 | W79: ==IF(OR(L79="标准固收类",L79="非标固收类"),EOMONTH($A$2,A79*12),"") -> 47483 | X79: 不适用 | Y79: ==VLOOKUP(资产明细!K79,配置调整!$B$4:$C$29,2,0) -> 0.028 | Z79: Govt | AA79: CORIG0-3 | AD79: ==P79 -> 1.2022584e+09 | AM79: ==IF(OR(L79="标准固收类",L79="非标固收类"),Y79,"") -> 0.028 | BF79: ==AM79 -> 0.028 | BG79: ==IF(OR(L79="标准固收类",L79="非标固收类"),"",MIN(Y79,2%)) | BH79: 0 | BI79: 0.85
B80: 不动产3 | C80: 不动产 | D80: 分红账户 | E80: 不动产 | F80: 不动产 | G80: 不动产 | I80: Generic_不动产 | J80: AFS | K80: 不动产 | L80: 权益类 | M80: ==IF($D80=配置调整!$A$5,VLOOKUP($K80,配置调整!$B$4:$O$29,6,0)*配置调整!$A$6,IF($D80=配置调整!$A$8,VLOOKUP($K80,配置调整!$B$4:$O$29,6,0)*配置调整!$A$9,IF($D80=配置调整!$A$11,VLOOKUP($K80,配置调整!$B$4:$O$29,6,0)*配置调整!$A$12,FALSE))) -> 2.6119919e+09 | N80: ==M80 -> 2.6119919e+09 | O80: 0 | P80: ==M80 -> 2.6119919e+09 | Q80: ==M80 -> 2.6119919e+09 | R80: ==M80 -> 2.6119919e+09 | S80: 0 | U80: ==IF(OR(L80="标准固收类",L80="非标固收类"),$A$2,"") | V80: ==IF(OR(L80="标准固收类",L80="非标固收类"),EOMONTH($A$2,12),"") | W80: ==IF(OR(L80="标准固收类",L80="非标固收类"),EOMONTH($A$2,A80*12),"") | Y80: ==VLOOKUP(资产明细!K80,配置调整!$B$4:$C$29,2,0) -> 0.065 | Z80: Govt | AC80: Real Estate Index | AD80: ==P80 -> 2.6119919e+09 | AM80: ==IF(OR(L80="标准固收类",L80="非标固收类"),Y80,"") | BF80: ==AM80 | BG80: ==IF(OR(L80="标准固收类",L80="非标固收类"),"",MIN(Y80,2%)) -> 0.02 | BH80: 0 | BI80: 0.85

Sheet 配置调整
D1: check | E1: check | F1: check | G1: 0 | H1: 1 | I1: 2 | J1: 3 | K1: 0 | L1: 1 | M1: 2 | N1: 3 | O1: 0 | P1: 1 | Q1: 2 | R1: 3 | S1: ==SUMPRODUCT(C4:C29,D4:D29) -> 0.030209238 | T1: ==SUMPRODUCT(T4:T13,D4:D13) -> 8.0976457
A2: 资产合计 | C2: 1231 | D2: 传统账户 | E2: 分红账户 | F2: 万能账户 | G2: 传统账户 | H2: 传统账户 | I2: 传统账户 | J2: 传统账户 | K2: 分红账户 | L2: 分红账户 | M2: 分红账户 | N2: 分红账户 | O2: 万能账户 | P2: 万能账户 | Q2: 万能账户 | R2: 万能账户 | S2: ==SUMPRODUCT(S4:S29,D4:D29) -> 0.050371134
A3: ==71125456854.9999*K37 -> 8.0255529e+10 | B3: 资产组合名称/PortfolioName | C3: 预期投资收益率/ExpectedReturn | D3: 配置比例 | E3: 配置比例 | F3: 配置比例 | G3: 配置比例 | H3: 配置比例 | I3: 配置比例 | J3: 配置比例 | K3: 配置比例 | L3: 配置比例 | M3: 配置比例 | N3: 配置比例 | O3: 配置比例 | P3: 配置比例 | Q3: 配置比例 | R3: 配置比例 | S3: 波动率 | V3: 预期投资收益率 | W3: 波动率 | X3: 波动率 | AB3: 节点/Tenor | AC3: Govt
A4: ==SUM(资产明细!M3:M80) -> 8.0255529e+10 | B4: 国债_3Y | C4: 0.011872 | D4: ==SUMIFS(资产明细!$M$3:$M$80,资产明细!$D$3:$D$80,配置调整!D$2,资产明细!$K$3:$K$80,配置调整!$B4)/SUMIFS(资产明细!$M$3:$M$80,资产明细!$D$3:$D$80,配置调整!D$2) -> 0.0036988283 | E4: ==SUMIFS(资产明细!$M$3:$M$80,资产明细!$D$3:$D$80,配置调整!E$2,资产明细!$K$3:$K$80,配置调整!$B4)/SUMIFS(资产明细!$M$3:$M$80,资产明细!$D$3:$D$80,配置调整!E$2) -> 0.0036988283 | F4: ==SUMIFS(资产明细!$M$3:$M$80,资产明细!$D$3:$D$80,配置调整!F$2,资产明细!$K$3:$K$80,配置调整!$B4)/SUMIFS(资产明细!$M$3:$M$80,资产明细!$D$3:$D$80,配置调整!F$2) -> 0.0036988283 | G4: ==Sheet1!L3 -> 0.0036988283 | H4: ==Sheet1!M3 -> 0.018250843 | I4: ==Sheet1!N3 -> 0.024032533 | J4: ==Sheet1!O3 -> 0.0049270319 | K4: ==G4 -> 0.0036988283 | L4: ==H4 -> 0.018250843 | M4: ==I4 -> 0.024032533 | N4: ==J4 -> 0.0049270319 | O4: ==K4 -> 0.0036988283 | P4: ==L4 -> 0.018250843 | Q4: ==M4 -> 0.024032533 | R4: ==N4 -> 0.0049270319 | S4: 0.015 | T4: 2.5 | V4: 2024Q3 | W4: 2024Q3 | X4: 2024Q2 | Z4: 中债曲线 | AB4: 1M | AC4: 0.006635
A5: 传统账户 | B5: 国债_5Y | C5: 0.014152 | D5: ==SUMIFS(资产明细!$M$3:$M$80,资产明细!$D$3:$D$80,配置调整!D$2,资产明细!$K$3:$K$80,配置调整!$B5)/SUMIFS(资产明细!$M$3:$M$80,资产明细!$D$3:$D$80,配置调整!D$2) -> 0.0077904803 | E5: ==SUMIFS(资产明细!$M$3:$M$80,资产明细!$D$3:$D$80,配置调整!E$2,资产明细!$K$3:$K$80,配置调整!$B5)/SUMIFS(资产明细!$M$3:$M$80,资产明细!$D$3:$D$80,配置调整!E$2) -> 0.0077904803 | F5: ==SUMIFS(资产明细!$M$3:$M$80,资产明细!$D$3:$D$80,配置调整!F$2,资产明细!$K$3:$K$80,配置调整!$B5)/SUMIFS(资产明细!$M$3:$M$80,资产明细!$D$3:$D$80,配置调整!F$2) -> 0.0077904803 | G5: ==Sheet1!L4 -> 0.0077904803 | H5: ==Sheet1!M4 -> 0.034165384 | I5: ==Sheet1!N4 -> 0.0025115748 | J5: ==Sheet1!O4 -> 0.0020925844 | K5: ==G5 -> 0.0077904803 | L5: ==H5 -> 0.034165384 | M5: ==I5 -> 0.0025115748 | N5: ==J5 -> 0.0020925844 | O5: ==K5 -> 0.0077904803 | P5: ==L5 -> 0.034165384 | Q5: ==M5 -> 0.0025115748 | R5: ==N5 -> 0.0020925844 | S5: 0.02 | T5: 4 | U5: 国债_10Y | V5: 0.02186 | W5: 0.046489957 | X5: 0.046682 | Y5: ==W5-X5 -> -0.00019204296 | Z5: 0.021518 | AA5: 0.016752 | AB5: 2M | AC5: 0.008532
A6: ==A3/3 -> 2.6751843e+10 | B6: 国债_10Y | C6: 0.016752 | D6: ==SUMIFS(资产明细!$M$3:$M$80,资产明细!$D$3:$D$80,配置调整!D$2,资产明细!$K$3:$K$80,配置调整!$B6)/SUMIFS(资产明细!$M$3:$M$80,资产明细!$D$3:$D$80,配置调整!D$2) -> 0.032496654 | E6: ==SUMIFS(资产明细!$M$3:$M$80,资产明细!$D$3:$D$80,配置调整!E$2,资产明细!$K$3:$K$80,配置调整!$B6)/SUMIFS(资产明细!$M$3:$M$80,资产明细!$D$3:$D$80,配置调整!E$2) -> 0.032496654 | F6: ==SUMIFS(资产明细!$M$3:$M$80,资产明细!$D$3:$D$80,配置调整!F$2,资产明细!$K$3:$K$80,配置调整!$B6)/SUMIFS(资产明细!$M$3:$M$80,资产明细!$D$3:$D$80,配置调整!F$2) -> 0.032496654 | G6: ==Sheet1!L5 -> 0.032496654 | H6: ==Sheet1!M5 -> 7.032092e-05 | I6: ==Sheet1!N5 -> 0.030616004 | J6: ==Sheet1!O5 -> 0.013735449 | K6: ==G6 -> 0.032496654 | L6: ==H6 -> 7.032092e-05 | M6: ==I6 -> 0.030616004 | N6: ==J6 -> 0.013735449 | O6: ==K6 -> 0.032496654 | P6: ==L6 -> 7.032092e-05 | Q6: ==M6 -> 0.030616004 | R6: ==N6 -> 0.013735449 | S6: 0.04 | T6: 8 | U6: 国债_30Y | V6: 0.023965 | W6: 0.10465235 | X6: 0.103864 | Y6: ==W6-X6 -> 0.00078835284 | Z6: 0.02355 | AB6: 3M | AC6: 0.00907
B7: 国债_20Y | C7: 0.019747 | D7: ==SUMIFS(资产明细!$M$3:$M$80,资产明细!$D$3:$D$80,配置调整!D$2,资产明细!$K$3:$K$80,配置调整!$B7)/SUMIFS(资产明细!$M$3:$M$80,资产明细!$D$3:$D$80,配置调整!D$2) -> 0.14212089 | E7: ==SUMIFS(资产明细!$M$3:$M$80,资产明细!$D$3:$D$80,配置调整!E$2,资产明细!$K$3:$K$80,配置调整!$B7)/SUMIFS(资产明细!$M$3:$M$80,资产明细!$D$3:$D$80,配置调整!E$2) -> 0.14212089 | F7: ==SUMIFS(资产明细!$M$3:$M$80,资产明细!$D$3:$D$80,配置调整!F$2,资产明细!$K$3:$K$80,配置调整!$B7)/SUMIFS(资产明细!$M$3:$M$80,资产明细!$D$3:$D$80,配置调整!F$2) -> 0.14212089 | G7: ==Sheet1!L6 -> 0.14212089 | H7: ==Sheet1!M6 -> 0.15746475 | I7: ==Sheet1!N6 -> 0.29297907 | J7: ==Sheet1!O6 -> 0.22835041 | K7: ==G7 -> 0.14212089 | L7: ==H7 -> 0.15746475 | M7: ==I7 -> 0.29297907 | N7: ==J7 -> 0.22835041 | O7: ==K7 -> 0.14212089 | P7: ==L7 -> 0.15746475 | Q7: ==M7 -> 0.29297907 | R7: ==N7 -> 0.22835041 | S7: 0.045 | T7: 14 | U7: 高等级信用债_3Y | V7: 0.023594836 | W7: 0.024324772 | X7: 0.023601 | Y7: ==W7-X7 -> 0.00072377152 | Z7: 0.023248 | AB7: 6M | AC7: 0.009543
A8: 分红账户 | B8: 国债_50Y | C8: 0.019875 | D8: ==SUMIFS(资产明细!$M$3:$M$80,资产明细!$D$3:$D$80,配置调整!D$2,资产明细!$K$3:$K$80,配置调整!$B8)/SUMIFS(资产明细!$M$3:$M$80,资产明细!$D$3:$D$80,配置调整!D$2) -> 0.20614768 | E8: ==SUMIFS(资产明细!$M$3:$M$80,资产明细!$D$3:$D$80,配置调整!E$2,资产明细!$K$3:$K$80,配置调整!$B8)/SUMIFS(资产明细!$M$3:$M$80,资产明细!$D$3:$D$80,配置调整!E$2) -> 0.20614768 | F8: ==SUMIFS(资产明细!$M$3:$M$80,资产明细!$D$3:$D$80,配置调整!F$2,资产明细!$K$3:$K$80,配置调整!$B8)/SUMIFS(资产明细!$M$3:$M$80,资产明细!$D$3:$D$80,配置调整!F$2) -> 0.20614768 | G8: ==Sheet1!L7 -> 0.20614768 | H8: ==Sheet1!M7 -> 0.20431444 | I8: ==Sheet1!N7 -> 0.13835296 | J8: ==Sheet1!O7 -> 0.17315448 | K8: ==G8 -> 0.20614768 | L8: ==H8 -> 0.20431444 | M8: ==I8 -> 0.13835296 | N8: ==J8 -> 0.17315448 | O8: ==K8 -> 0.20614768 | P8: ==L8 -> 0.20431444 | Q8: ==M8 -> 0.13835296 | R8: ==N8 -> 0.17315448 | S8: 0.055 | T8: 25 | U8: 高等级信用债_5Y | V8: 0.023487288 | W8: 0.033847491 | X8: 0.033473 | Y8: ==W8-X8 -> 0.0003744911 | Z8: 0.024018 | AB8: 9M | AC8: 0.010197
A9: ==A3/3 -> 2.6751843e+10 | B9: 信用债_3Y | C9: 0.017501 | D9: ==SUMIFS(资产明细!$M$3:$M$80,资产明细!$D$3:$D$80,配置调整!D$2,资产明细!$K$3:$K$80,配置调整!$B9)/SUMIFS(资产明细!$M$3:$M$80,资产明细!$D$3:$D$80,配置调整!D$2) -> 0.067977585 | E9: ==SUMIFS(资产明细!$M$3:$M$80,资产明细!$D$3:$D$80,配置调整!E$2,资产明细!$K$3:$K$80,配置调整!$B9)/SUMIFS(资产明细!$M$3:$M$80,资产明细!$D$3:$D$80,配置调整!E$2) -> 0.067977585 | F9: ==SUMIFS(资产明细!$M$3:$M$80,资产明细!$D$3:$D$80,配置调整!F$2,资产明细!$K$3:$K$80,配置调整!$B9)/SUMIFS(资产明细!$M$3:$M$80,资产明细!$D$3:$D$80,配置调整!F$2) -> 0.067977585 | G9: ==Sheet1!L8 -> 0.067977585 | H9: ==Sheet1!M8 -> 0.065288002 | I9: ==Sheet1!N8 -> 0.0092608415 | J9: ==Sheet1!O8 -> 0.0047362284 | K9: ==G9 -> 0.067977585 | L9: ==H9 -> 0.065288002 | M9: ==I9 -> 0.0092608415 | N9: ==J9 -> 0.0047362284 | O9: ==K9 -> 0.067977585 | P9: ==L9 -> 0.065288002 | Q9: ==M9 -> 0.0092608415 | R9: ==N9 -> 0.0047362284 | S9: ==W7*C9/V7 -> 0.018042415 | T9: 2.5 | U9: 非标资产_3Y | V9: 0.032748196 | W9: 0.029189726 | X9: 0.0283212 | Y9: ==W9-X9 -> 0.00086852582 | AB9: 12M | AC9: 0.010814
B10: 信用债_5Y | C10: 0.018727 | D10: ==SUMIFS(资产明细!$M$3:$M$80,资产明细!$D$3:$D$80,配置调整!D$2,资产明细!$K$3:$K$80,配置调整!$B10)/SUMIFS(资产明细!$M$3:$M$80,资产明细!$D$3:$D$80,配置调整!D$2) -> 0.0059782634 | E10: ==SUMIFS(资产明细!$M$3:$M$80,资产明细!$D$3:$D$80,配置调整!E$2,资产明细!$K$3:$K$80,配置调整!$B10)/SUMIFS(资产明细!$M$3:$M$80,资产明细!$D$3:$D$80,配置调整!E$2) -> 0.0059782634 | F10: ==SUMIFS(资产明细!$M$3:$M$80,资产明细!$D$3:$D$80,配置调整!F$2,资产明细!$K$3:$K$80,配置调整!$B10)/SUMIFS(资产明细!$M$3:$M$80,资产明细!$D$3:$D$80,配置调整!F$2) -> 0.0059782634 | G10: ==Sheet1!L9 -> 0.0059782634 | H10: ==Sheet1!M9 -> 4.1665381e-12 | I10: ==Sheet1!N9 -> 0.017289853 | J10: ==Sheet1!O9 -> 0.00087263177 | K10: ==G10 -> 0.0059782634 | L10: ==H10 -> 4.1665381e-12 | M10: ==I10 -> 0.017289853 | N10: ==J10 -> 0.00087263177 | O10: ==K10 -> 0.0059782634 | P10: ==L10 -> 4.1665381e-12 | Q10: ==M10 -> 0.017289853 | R10: ==N10 -> 0.00087263177 | S10: ==W8*C10/V8 -> 0.026987448 | T10: 4 | U10: 非标资产_5Y | V10: 0.032143778 | W10: 0.040616989 | X10: 0.0401676 | Y10: ==W10-X10 -> 0.00044938932 | AB10: 24M | AC10: 0.011375
A11: 万能账户 | B11: 信用债_10Y | C11: 0.021173 | D11: ==SUMIFS(资产明细!$M$3:$M$80,资产明细!$D$3:$D$80,配置调整!D$2,资产明细!$K$3:$K$80,配置调整!$B11)/SUMIFS(资产明细!$M$3:$M$80,资产明细!$D$3:$D$80,配置调整!D$2) -> 0.039135613 | E11: ==SUMIFS(资产明细!$M$3:$M$80,资产明细!$D$3:$D$80,配置调整!E$2,资产明细!$K$3:$K$80,配置调整!$B11)/SUMIFS(资产明细!$M$3:$M$80,资产明细!$D$3:$D$80,配置调整!E$2) -> 0.039135613 | F11: ==SUMIFS(资产明细!$M$3:$M$80,资产明细!$D$3:$D$80,配置调整!F$2,资产明细!$K$3:$K$80,配置调整!$B11)/SUMIFS(资产明细!$M$3:$M$80,资产明细!$D$3:$D$80,配置调整!F$2) -> 0.039135613 | G11: ==Sheet1!L10 -> 0.039135613 | H11: ==Sheet1!M10 -> 0.065497096 | I11: ==Sheet1!N10 -> 0.015324656 | J11: ==Sheet1!O10 -> 0.027221905 | K11: ==G11 -> 0.039135613 | L11: ==H11 -> 0.065497096 | M11: ==I11 -> 0.015324656 | N11: ==J11 -> 0.027221905 | O11: ==K11 -> 0.039135613 | P11: ==L11 -> 0.065497096 | Q11: ==M11 -> 0.015324656 | R11: ==N11 -> 0.027221905 | S11: ==[19]自定义指标!$B$10/[19]自定义指标!$B$9*S10 -> 0.043288127 | T11: 8 | U11: A股 | V11: 0.091774815 | W11: 0.25066148 | X11: 0.24764 | Y11: ==W11-X11 -> 0.0030214811 | AB11: 36M | AC11: 0.011881
A12: ==A3/3 -> 2.6751843e+10 | B12: 非标资产_3Y | C12: 0.024290322 | D12: ==SUMIFS(资产明细!$M$3:$M$80,资产明细!$D$3:$D$80,配置调整!D$2,资产明细!$K$3:$K$80,配置调整!$B12)/SUMIFS(资产明细!$M$3:$M$80,资产明细!$D$3:$D$80,配置调整!D$2) -> 0.028692128 | E12: ==SUMIFS(资产明细!$M$3:$M$80,资产明细!$D$3:$D$80,配置调整!E$2,资产明细!$K$3:$K$80,配置调整!$B12)/SUMIFS(资产明细!$M$3:$M$80,资产明细!$D$3:$D$80,配置调整!E$2) -> 0.028692128 | F12: ==SUMIFS(资产明细!$M$3:$M$80,资产明细!$D$3:$D$80,配置调整!F$2,资产明细!$K$3:$K$80,配置调整!$B12)/SUMIFS(资产明细!$M$3:$M$80,资产明细!$D$3:$D$80,配置调整!F$2) -> 0.028692128 | G12: ==Sheet1!L11 -> 0.028692128 | H12: ==Sheet1!M11 -> 0.00021312637 | I12: ==Sheet1!N11 -> 0.0074794708 | J12: ==Sheet1!O11 -> 0.0071535672 | K12: ==G12 -> 0.028692128 | L12: ==H12 -> 0.00021312637 | M12: ==I12 -> 0.0074794708 | N12: ==J12 -> 0.0071535672 | O12: ==K12 -> 0.028692128 | P12: ==L12 -> 0.00021312637 | Q12: ==M12 -> 0.0074794708 | R12: ==N12 -> 0.0071535672 | S12: ==W9*C12/V9 -> 0.021650898 | T12: 2.5 | U12: H股 | V12: 0.1021779 | W12: 0.21063241 | X12: 0.210144 | Y12: ==W12-X12 -> 0.00048840931 | AB12: 48M | AC12: 0.012961
B13: 非标资产_5Y | C13: 0.025629035 | D13: ==SUMIFS(资产明细!$M$3:$M$80,资产明细!$D$3:$D$80,配置调整!D$2,资产明细!$K$3:$K$80,配置调整!$B13)/SUMIFS(资产明细!$M$3:$M$80,资产明细!$D$3:$D$80,配置调整!D$2) -> 0.018801727 | E13: ==SUMIFS(资产明细!$M$3:$M$80,资产明细!$D$3:$D$80,配置调整!E$2,资产明细!$K$3:$K$80,配置调整!$B13)/SUMIFS(资产明细!$M$3:$M$80,资产明细!$D$3:$D$80,配置调整!E$2) -> 0.018801727 | F13: ==SUMIFS(资产明细!$M$3:$M$80,资产明细!$D$3:$D$80,配置调整!F$2,资产明细!$K$3:$K$80,配置调整!$B13)/SUMIFS(资产明细!$M$3:$M$80,资产明细!$D$3:$D$80,配置调整!F$2) -> 0.018801727 | G13: ==Sheet1!L12 -> 0.018801727 | H13: ==Sheet1!M12 -> 0.018435449 | I13: ==Sheet1!N12 -> 0.011006803 | J13: ==Sheet1!O12 -> 0.026071855 | K13: ==G13 -> 0.018801727 | L13: ==H13 -> 0.018435449 | M13: ==I13 -> 0.011006803 | N13: ==J13 -> 0.026071855 | O13: ==K13 -> 0.018801727 | P13: ==L13 -> 0.018435449 | Q13: ==M13 -> 0.011006803 | R13: ==N13 -> 0.026071855 | S13: ==W10*C13/V10 -> 0.032384938 | T13: 4 | U13: MSCI发达市场 | V13: 0.06965 | W13: 0.1673502 | X13: 0.16775 | Y13: ==W13-X13 -> -0.00039979604 | AB13: 60M | AC13: 0.014212
B14: A股 | C14: 0.06 | D14: ==SUMIFS(资产明细!$M$3:$M$80,资产明细!$D$3:$D$80,配置调整!D$2,资产明细!$K$3:$K$80,配置调整!$B14)/SUMIFS(资产明细!$M$3:$M$80,资产明细!$D$3:$D$80,配置调整!D$2) -> 1e-05 | E14: ==SUMIFS(资产明细!$M$3:$M$80,资产明细!$D$3:$D$80,配置调整!E$2,资产明细!$K$3:$K$80,配置调整!$B14)/SUMIFS(资产明细!$M$3:$M$80,资产明细!$D$3:$D$80,配置调整!E$2) -> 1e-05 | F14: ==SUMIFS(资产明细!$M$3:$M$80,资产明细!$D$3:$D$80,配置调整!F$2,资产明细!$K$3:$K$80,配置调整!$B14)/SUMIFS(资产明细!$M$3:$M$80,资产明细!$D$3:$D$80,配置调整!F$2) -> 1e-05 | G14: ==Sheet1!L13 -> 1e-05 | H14: ==Sheet1!M13 -> 0.0030906251 | I14: ==Sheet1!N13 -> 0.023195612 | J14: ==Sheet1!O13 -> 0.00013797208 | K14: ==G14 -> 1e-05 | L14: ==H14 -> 0.0030906251 | M14: ==I14 -> 0.023195612 | N14: ==J14 -> 0.00013797208 | O14: ==K14 -> 1e-05 | P14: ==L14 -> 0.0030906251 | Q14: ==M14 -> 0.023195612 | R14: ==N14 -> 0.00013797208 | S14: 0.165 | U14: MSCI新兴市场 | V14: 0.077 | W14: 0.22586533 | X14: 0.226314 | Y14: ==W14-X14 -> -0.000448669 | AB14: 72M | AC14: 0.015145
B15: H股 | C15: 0.07 | D15: ==SUMIFS(资产明细!$M$3:$M$80,资产明细!$D$3:$D$80,配置调整!D$2,资产明细!$K$3:$K$80,配置调整!$B15)/SUMIFS(资产明细!$M$3:$M$80,资产明细!$D$3:$D$80,配置调整!D$2) -> 0.0033770961 | E15: ==SUMIFS(资产明细!$M$3:$M$80,资产明细!$D$3:$D$80,配置调整!E$2,资产明细!$K$3:$K$80,配置调整!$B15)/SUMIFS(资产明细!$M$3:$M$80,资产明细!$D$3:$D$80,配置调整!E$2) -> 0.0033770961 | F15: ==SUMIFS(资产明细!$M$3:$M$80,资产明细!$D$3:$D$80,配置调整!F$2,资产明细!$K$3:$K$80,配置调整!$B15)/SUMIFS(资产明细!$M$3:$M$80,资产明细!$D$3:$D$80,配置调整!F$2) -> 0.0033770961 | G15: ==Sheet1!L14 -> 0.0033770961 | H15: ==Sheet1!M14 -> 4.9218324e-09 | I15: ==Sheet1!N14 -> 0.019530684 | J15: ==Sheet1!O14 -> 0.0086970601 | K15: ==G15 -> 0.0033770961 | L15: ==H15 -> 4.9218324e-09 | M15: ==I15 -> 0.019530684 | N15: ==J15 -> 0.0086970601 | O15: ==K15 -> 0.0033770961 | P15: ==L15 -> 4.9218324e-09 | Q15: ==M15 -> 0.019530684 | R15: ==N15 -> 0.0086970601 | S15: 0.18 | U15: 纯债基金 | V15: 0.028487288 | W15: 0.035443014 | X15: 0.035796 | Y15: ==W15-X15 -> -0.00035298607 | AB15: 84M | AC15: 0.01601
B16: MSCI发达市场 | C16: 0.08 | D16: ==SUMIFS(资产明细!$M$3:$M$80,资产明细!$D$3:$D$80,配置调整!D$2,资产明细!$K$3:$K$80,配置调整!$B16)/SUMIFS(资产明细!$M$3:$M$80,资产明细!$D$3:$D$80,配置调整!D$2) -> 0.0047554241 | E16: ==SUMIFS(资产明细!$M$3:$M$80,资产明细!$D$3:$D$80,配置调整!E$2,资产明细!$K$3:$K$80,配置调整!$B16)/SUMIFS(资产明细!$M$3:$M$80,资产明细!$D$3:$D$80,配置调整!E$2) -> 0.0047554241 | F16: ==SUMIFS(资产明细!$M$3:$M$80,资产明细!$D$3:$D$80,配置调整!F$2,资产明细!$K$3:$K$80,配置调整!$B16)/SUMIFS(资产明细!$M$3:$M$80,资产明细!$D$3:$D$80,配置调整!F$2) -> 0.0047554241 | G16: ==Sheet1!L15 -> 0.0047554241 | H16: ==Sheet1!M15 -> 0.027372612 | I16: ==Sheet1!N15 -> 0.017012064 | J16: ==Sheet1!O15 -> 0.056394661 | K16: ==G16 -> 0.0047554241 | L16: ==H16 -> 0.027372612 | M16: ==I16 -> 0.017012064 | N16: ==J16 -> 0.056394661 | O16: ==K16 -> 0.0047554241 | P16: ==L16 -> 0.027372612 | Q16: ==M16 -> 0.017012064 | R16: ==N16 -> 0.056394661 | S16: ==W13*0.9 -> 0.15061518 | U16: 混合基金 | V16: 0.066459804 | W16: 0.17649996 | X16: 0.173712 | Y16: ==W16-X16 -> 0.0027879585 | AB16: 96M | AC16: 0.01659
B17: MSCI新兴市场 | C17: 0.085 | D17: ==SUMIFS(资产明细!$M$3:$M$80,资产明细!$D$3:$D$80,配置调整!D$2,资产明细!$K$3:$K$80,配置调整!$B17)/SUMIFS(资产明细!$M$3:$M$80,资产明细!$D$3:$D$80,配置调整!D$2) -> 0.025377513 | E17: ==SUMIFS(资产明细!$M$3:$M$80,资产明细!$D$3:$D$80,配置调整!E$2,资产明细!$K$3:$K$80,配置调整!$B17)/SUMIFS(资产明细!$M$3:$M$80,资产明细!$D$3:$D$80,配置调整!E$2) -> 0.025377513 | F17: ==SUMIFS(资产明细!$M$3:$M$80,资产明细!$D$3:$D$80,配置调整!F$2,资产明细!$K$3:$K$80,配置调整!$B17)/SUMIFS(资产明细!$M$3:$M$80,资产明细!$D$3:$D$80,配置调整!F$2) -> 0.025377513 | G17: ==Sheet1!L16 -> 0.025377513 | H17: ==Sheet1!M16 -> 0.056412323 | I17: ==Sheet1!N16 -> 0.037003146 | J17: ==Sheet1!O16 -> 0.028298835 | K17: ==G17 -> 0.025377513 | L17: ==H17 -> 0.056412323 | M17: ==I17 -> 0.037003146 | N17: ==J17 -> 0.028298835 | O17: ==K17 -> 0.025377513 | P17: ==L17 -> 0.056412323 | Q17: ==M17 -> 0.037003146 | R17: ==N17 -> 0.028298835 | S17: ==W14*0.9 -> 0.2032788 | U17: 股票基金 | V17: 0.085446062 | W17: 0.22425377 | X17: 0.220681 | Y17: ==W17-X17 -> 0.0035727656 | AB17: 108M | AC17: 0.016766
B18: 债券基金 | C18: 0.028487288 | D18: ==SUMIFS(资产明细!$M$3:$M$80,资产明细!$D$3:$D$80,配置调整!D$2,资产明细!$K$3:$K$80,配置调整!$B18)/SUMIFS(资产明细!$M$3:$M$80,资产明细!$D$3:$D$80,配置调整!D$2) -> 1e-05 | E18: ==SUMIFS(资产明细!$M$3:$M$80,资产明细!$D$3:$D$80,配置调整!E$2,资产明细!$K$3:$K$80,配置调整!$B18)/SUMIFS(资产明细!$M$3:$M$80,资产明细!$D$3:$D$80,配置调整!E$2) -> 1e-05 | F18: ==SUMIFS(资产明细!$M$3:$M$80,资产明细!$D$3:$D$80,配置调整!F$2,资产明细!$K$3:$K$80,配置调整!$B18)/SUMIFS(资产明细!$M$3:$M$80,资产明细!$D$3:$D$80,配置调整!F$2) -> 1e-05 | G18: ==Sheet1!L17 -> 1e-05 | H18: ==Sheet1!M17 -> 0.00039173317 | I18: ==Sheet1!N17 -> 1.7707171e-07 | J18: ==Sheet1!O17 -> 0.00029124044 | K18: ==G18 -> 1e-05 | L18: ==H18 -> 0.00039173317 | M18: ==I18 -> 1.7707171e-07 | N18: ==J18 -> 0.00029124044 | O18: ==K18 -> 1e-05 | P18: ==L18 -> 0.00039173317 | Q18: ==M18 -> 1.7707171e-07 | R18: ==N18 -> 0.00029124044 | S18: ==W15 -> 0.035443014 | U18: 优先股 | V18: 0.055 | W18: 0.16924168 | X18: 0.170314 | Y18: ==W18-X18 -> -0.0010723229 | AB18: 120M | AC18: 0.016972
B19: 货币基金 | C19: 0.015 | D19: ==SUMIFS(资产明细!$M$3:$M$80,资产明细!$D$3:$D$80,配置调整!D$2,资产明细!$K$3:$K$80,配置调整!$B19)/SUMIFS(资产明细!$M$3:$M$80,资产明细!$D$3:$D$80,配置调整!D$2) -> 1e-05 | E19: ==SUMIFS(资产明细!$M$3:$M$80,资产明细!$D$3:$D$80,配置调整!E$2,资产明细!$K$3:$K$80,配置调整!$B19)/SUMIFS(资产明细!$M$3:$M$80,资产明细!$D$3:$D$80,配置调整!E$2) -> 1e-05 | F19: ==SUMIFS(资产明细!$M$3:$M$80,资产明细!$D$3:$D$80,配置调整!F$2,资产明细!$K$3:$K$80,配置调整!$B19)/SUMIFS(资产明细!$M$3:$M$80,资产明细!$D$3:$D$80,配置调整!F$2) -> 1e-05 | G19: ==Sheet1!L18 -> 1e-05 | H19: ==Sheet1!M18 -> 1.0556649e-138 | I19: ==Sheet1!N18 -> 0 | J19: ==Sheet1!O18 -> 0 | K19: ==G19 -> 1e-05 | L19: ==H19 -> 1.0556649e-138 | M19: ==I19 -> 0 | N19: ==J19 -> 0 | O19: ==K19 -> 1e-05 | P19: ==L19 -> 1.0556649e-138 | Q19: ==M19 -> 0 | R19: ==N19 -> 0 | S19: 0.005 | U19: 可转债 | V19: 0.05 | W19: 0.15555801 | X19: 0.155761 | Y19: ==W19-X19 -> -0.00020298881 | AB19: 180M | AC19: 0.019189
B20: 混合基金 | C20: 0.05 | D20: ==SUMIFS(资产明细!$M$3:$M$80,资产明细!$D$3:$D$80,配置调整!D$2,资产明细!$K$3:$K$80,配置调整!$B20)/SUMIFS(资产明细!$M$3:$M$80,资产明细!$D$3:$D$80,配置调整!D$2) -> 0.010751247 | E20: ==SUMIFS(资产明细!$M$3:$M$80,资产明细!$D$3:$D$80,配置调整!E$2,资产明细!$K$3:$K$80,配置调整!$B20)/SUMIFS(资产明细!$M$3:$M$80,资产明细!$D$3:$D$80,配置调整!E$2) -> 0.010751247 | F20: ==SUMIFS(资产明细!$M$3:$M$80,资产明细!$D$3:$D$80,配置调整!F$2,资产明细!$K$3:$K$80,配置调整!$B20)/SUMIFS(资产明细!$M$3:$M$80,资产明细!$D$3:$D$80,配置调整!F$2) -> 0.010751247 | G20: ==Sheet1!L19 -> 0.010751247 | H20: ==Sheet1!M19 -> 0 | I20: ==Sheet1!N19 -> 2.1006208e-59 | J20: ==Sheet1!O19 -> 0 | K20: ==G20 -> 0.010751247 | L20: ==H20 -> 0 | M20: ==I20 -> 2.1006208e-59 | N20: ==J20 -> 0 | O20: ==K20 -> 0.010751247 | P20: ==L20 -> 0 | Q20: ==M20 -> 2.1006208e-59 | R20: ==N20 -> 0 | S20: ==W16*0.9 -> 0.15884996 | U20: 长期股权投资 | V20: 0.1044455 | W20: 0.19302347 | X20: 0.194181 | Y20: ==W20-X20 -> -0.0011575277 | AB20: 240M | AC20: 0.020266
B21: 股票基金 | C21: 0.055 | D21: ==SUMIFS(资产明细!$M$3:$M$80,资产明细!$D$3:$D$80,配置调整!D$2,资产明细!$K$3:$K$80,配置调整!$B21)/SUMIFS(资产明细!$M$3:$M$80,资产明细!$D$3:$D$80,配置调整!D$2) -> 1e-05 | E21: ==SUMIFS(资产明细!$M$3:$M$80,资产明细!$D$3:$D$80,配置调整!E$2,资产明细!$K$3:$K$80,配置调整!$B21)/SUMIFS(资产明细!$M$3:$M$80,资产明细!$D$3:$D$80,配置调整!E$2) -> 1e-05 | F21: ==SUMIFS(资产明细!$M$3:$M$80,资产明细!$D$3:$D$80,配置调整!F$2,资产明细!$K$3:$K$80,配置调整!$B21)/SUMIFS(资产明细!$M$3:$M$80,资产明细!$D$3:$D$80,配置调整!F$2) -> 1e-05 | G21: ==Sheet1!L20 -> 1e-05 | H21: ==Sheet1!M20 -> 4.1777806e-10 | I21: ==Sheet1!N20 -> 1.9288294e-07 | J21: ==Sheet1!O20 -> 0.00010022122 | K21: ==G21 -> 1e-05 | L21: ==H21 -> 4.1777806e-10 | M21: ==I21 -> 1.9288294e-07 | N21: ==J21 -> 0.00010022122 | O21: ==K21 -> 1e-05 | P21: ==L21 -> 4.1777806e-10 | Q21: ==M21 -> 1.9288294e-07 | R21: ==N21 -> 0.00010022122 | S21: ==S14 -> 0.165 | U21: 未上市股权 | V21: 0.10575778 | W21: 0.27383186 | X21: 0.27446 | Y21: ==W21-X21 -> -0.00062814455 | AB21: 360M | AC21: 0.019334
B22: 优先股 | C22: 0.043 | D22: ==SUMIFS(资产明细!$M$3:$M$80,资产明细!$D$3:$D$80,配置调整!D$2,资产明细!$K$3:$K$80,配置调整!$B22)/SUMIFS(资产明细!$M$3:$M$80,资产明细!$D$3:$D$80,配置调整!D$2) -> 1e-05 | E22: ==SUMIFS(资产明细!$M$3:$M$80,资产明细!$D$3:$D$80,配置调整!E$2,资产明细!$K$3:$K$80,配置调整!$B22)/SUMIFS(资产明细!$M$3:$M$80,资产明细!$D$3:$D$80,配置调整!E$2) -> 1e-05 | F22: ==SUMIFS(资产明细!$M$3:$M$80,资产明细!$D$3:$D$80,配置调整!F$2,资产明细!$K$3:$K$80,配置调整!$B22)/SUMIFS(资产明细!$M$3:$M$80,资产明细!$D$3:$D$80,配置调整!F$2) -> 1e-05 | G22: ==Sheet1!L21 -> 1e-05 | H22: ==Sheet1!M21 -> 5.9124551e-121 | I22: ==Sheet1!N21 -> 1.5499145e-273 | J22: ==Sheet1!O21 -> 2.6197307e-112 | K22: ==G22 -> 1e-05 | L22: ==H22 -> 5.9124551e-121 | M22: ==I22 -> 1.5499145e-273 | N22: ==J22 -> 2.6197307e-112 | O22: ==K22 -> 1e-05 | P22: ==L22 -> 5.9124551e-121 | Q22: ==M22 -> 1.5499145e-273 | R22: ==N22 -> 2.6197307e-112 | S22: 0.05 | U22: 现金类 | V22: 0.015 | W22: 0 | X22: 0 | Y22: ==W22-X22 -> 0 | AB22: 480M | AC22: 0.020239
B23: 长期股权投资 | C23: 0.05 | D23: ==SUMIFS(资产明细!$M$3:$M$80,资产明细!$D$3:$D$80,配置调整!D$2,资产明细!$K$3:$K$80,配置调整!$B23)/SUMIFS(资产明细!$M$3:$M$80,资产明细!$D$3:$D$80,配置调整!D$2) -> 1e-05 | E23: ==SUMIFS(资产明细!$M$3:$M$80,资产明细!$D$3:$D$80,配置调整!E$2,资产明细!$K$3:$K$80,配置调整!$B23)/SUMIFS(资产明细!$M$3:$M$80,资产明细!$D$3:$D$80,配置调整!E$2) -> 1e-05 | F23: ==SUMIFS(资产明细!$M$3:$M$80,资产明细!$D$3:$D$80,配置调整!F$2,资产明细!$K$3:$K$80,配置调整!$B23)/SUMIFS(资产明细!$M$3:$M$80,资产明细!$D$3:$D$80,配置调整!F$2) -> 1e-05 | G23: ==Sheet1!L22 -> 1e-05 | H23: ==Sheet1!M22 -> 0 | I23: ==Sheet1!N22 -> 1.7251875e-51 | J23: ==Sheet1!O22 -> 0 | K23: ==G23 -> 1e-05 | L23: ==H23 -> 0 | M23: ==I23 -> 1.7251875e-51 | N23: ==J23 -> 0 | O23: ==K23 -> 1e-05 | P23: ==L23 -> 0 | Q23: ==M23 -> 1.7251875e-51 | R23: ==N23 -> 0 | S23: 0 | U23: 存款 | V23: 0.028 | W23: 0.013 | X23: 0.014749 | Y23: ==W23-X23 -> -0.001749 | AB23: 600M | AC23: 0.020315
B24: 未上市股权 | C24: 0.086 | D24: ==SUMIFS(资产明细!$M$3:$M$80,资产明细!$D$3:$D$80,配置调整!D$2,资产明细!$K$3:$K$80,配置调整!$B24)/SUMIFS(资产明细!$M$3:$M$80,资产明细!$D$3:$D$80,配置调整!D$2) -> 0.0062594927 | E24: ==SUMIFS(资产明细!$M$3:$M$80,资产明细!$D$3:$D$80,配置调整!E$2,资产明细!$K$3:$K$80,配置调整!$B24)/SUMIFS(资产明细!$M$3:$M$80,资产明细!$D$3:$D$80,配置调整!E$2) -> 0.0062594927 | F24: ==SUMIFS(资产明细!$M$3:$M$80,资产明细!$D$3:$D$80,配置调整!F$2,资产明细!$K$3:$K$80,配置调整!$B24)/SUMIFS(资产明细!$M$3:$M$80,资产明细!$D$3:$D$80,配置调整!F$2) -> 0.0062594927 | G24: ==Sheet1!L23 -> 0.0062594927 | H24: ==Sheet1!M23 -> 0.01509643 | I24: ==Sheet1!N23 -> 0.045674309 | J24: ==Sheet1!O23 -> 0.067780889 | K24: ==G24 -> 0.0062594927 | L24: ==H24 -> 0.01509643 | M24: ==I24 -> 0.045674309 | N24: ==J24 -> 0.067780889 | O24: ==K24 -> 0.0062594927 | P24: ==L24 -> 0.01509643 | Q24: ==M24 -> 0.045674309 | R24: ==N24 -> 0.067780889 | S24: 0.18 | U24: 保险资管产品-固收 | V24: 0.03481604 | W24: 0.048866976 | X24: 0.049024 | Y24: ==W24-X24 -> -0.00015702431
B25: 固收产品 | C25: 0.03481604 | D25: ==SUMIFS(资产明细!$M$3:$M$80,资产明细!$D$3:$D$80,配置调整!D$2,资产明细!$K$3:$K$80,配置调整!$B25)/SUMIFS(资产明细!$M$3:$M$80,资产明细!$D$3:$D$80,配置调整!D$2) -> 0.10046895 | E25: ==SUMIFS(资产明细!$M$3:$M$80,资产明细!$D$3:$D$80,配置调整!E$2,资产明细!$K$3:$K$80,配置调整!$B25)/SUMIFS(资产明细!$M$3:$M$80,资产明细!$D$3:$D$80,配置调整!E$2) -> 0.10046895 | F25: ==SUMIFS(资产明细!$M$3:$M$80,资产明细!$D$3:$D$80,配置调整!F$2,资产明细!$K$3:$K$80,配置调整!$B25)/SUMIFS(资产明细!$M$3:$M$80,资产明细!$D$3:$D$80,配置调整!F$2) -> 0.10046895 | G25: ==Sheet1!L24 -> 0.10046895 | H25: ==Sheet1!M24 -> 0.074257634 | I25: ==Sheet1!N24 -> 0.062730795 | J25: ==Sheet1!O24 -> 0.0098338199 | K25: ==G25 -> 0.10046895 | L25: ==H25 -> 0.074257634 | M25: ==I25 -> 0.062730795 | N25: ==J25 -> 0.0098338199 | O25: ==K25 -> 0.10046895 | P25: ==L25 -> 0.074257634 | Q25: ==M25 -> 0.062730795 | R25: ==N25 -> 0.0098338199 | S25: ==W24 -> 0.048866976 | U25: 不动产 | V25: 0.065 | W25: 0.07635184 | X25: 0.076668 | Y25: ==W25-X25 -> -0.00031616039
B26: 现金类 | C26: 0.015 | D26: ==SUMIFS(资产明细!$M$3:$M$80,资产明细!$D$3:$D$80,配置调整!D$2,资产明细!$K$3:$K$80,配置调整!$B26)/SUMIFS(资产明细!$M$3:$M$80,资产明细!$D$3:$D$80,配置调整!D$2) -> 0.031023708 | E26: ==SUMIFS(资产明细!$M$3:$M$80,资产明细!$D$3:$D$80,配置调整!E$2,资产明细!$K$3:$K$80,配置调整!$B26)/SUMIFS(资产明细!$M$3:$M$80,资产明细!$D$3:$D$80,配置调整!E$2) -> 0.031023708 | F26: ==SUMIFS(资产明细!$M$3:$M$80,资产明细!$D$3:$D$80,配置调整!F$2,资产明细!$K$3:$K$80,配置调整!$B26)/SUMIFS(资产明细!$M$3:$M$80,资产明细!$D$3:$D$80,配置调整!F$2) -> 0.031023708 | G26: ==Sheet1!L25 -> 0.031023708 | H26: ==Sheet1!M25 -> 0.018304982 | I26: ==Sheet1!N25 -> 0.02461286 | J26: ==Sheet1!O25 -> 0.014121954 | K26: ==G26 -> 0.031023708 | L26: ==H26 -> 0.018304982 | M26: ==I26 -> 0.02461286 | N26: ==J26 -> 0.014121954 | O26: ==K26 -> 0.031023708 | P26: ==L26 -> 0.018304982 | Q26: ==M26 -> 0.02461286 | R26: ==N26 -> 0.014121954 | S26: ==W22 -> 0 | U26: 保险资管产品-权益 | V26: 0.072788557 | W26: 0.17829435 | X26: 0.176597 | Y26: ==W26-X26 -> 0.001697354
B27: 其他信用产品 | C27: 0.031651664 | D27: ==SUMIFS(资产明细!$M$3:$M$80,资产明细!$D$3:$D$80,配置调整!D$2,资产明细!$K$3:$K$80,配置调整!$B27)/SUMIFS(资产明细!$M$3:$M$80,资产明细!$D$3:$D$80,配置调整!D$2) -> 0.12250776 | E27: ==SUMIFS(资产明细!$M$3:$M$80,资产明细!$D$3:$D$80,配置调整!E$2,资产明细!$K$3:$K$80,配置调整!$B27)/SUMIFS(资产明细!$M$3:$M$80,资产明细!$D$3:$D$80,配置调整!E$2) -> 0.12250776 | F27: ==SUMIFS(资产明细!$M$3:$M$80,资产明细!$D$3:$D$80,配置调整!F$2,资产明细!$K$3:$K$80,配置调整!$B27)/SUMIFS(资产明细!$M$3:$M$80,资产明细!$D$3:$D$80,配置调整!F$2) -> 0.12250776 | G27: ==Sheet1!L26 -> 0.12250776 | H27: ==Sheet1!M26 -> 0.13250204 | I27: ==Sheet1!N26 -> 0.10510801 | J27: ==Sheet1!O26 -> 0.20277254 | K27: ==G27 -> 0.12250776 | L27: ==H27 -> 0.13250204 | M27: ==I27 -> 0.10510801 | N27: ==J27 -> 0.20277254 | O27: ==K27 -> 0.12250776 | P27: ==L27 -> 0.13250204 | Q27: ==M27 -> 0.10510801 | R27: ==N27 -> 0.20277254 | S27: ==0.5*W15+0.5*W24 -> 0.042154995
B28: 存款 | C28: 0.028 | D28: ==SUMIFS(资产明细!$M$3:$M$80,资产明细!$D$3:$D$80,配置调整!D$2,资产明细!$K$3:$K$80,配置调整!$B28)/SUMIFS(资产明细!$M$3:$M$80,资产明细!$D$3:$D$80,配置调整!D$2) -> 0.044941143 | E28: ==SUMIFS(资产明细!$M$3:$M$80,资产明细!$D$3:$D$80,配置调整!E$2,资产明细!$K$3:$K$80,配置调整!$B28)/SUMIFS(资产明细!$M$3:$M$80,资产明细!$D$3:$D$80,配置调整!E$2) -> 0.044941143 | F28: ==SUMIFS(资产明细!$M$3:$M$80,资产明细!$D$3:$D$80,配置调整!F$2,资产明细!$K$3:$K$80,配置调整!$B28)/SUMIFS(资产明细!$M$3:$M$80,资产明细!$D$3:$D$80,配置调整!F$2) -> 0.044941143 | G28: ==Sheet1!L27 -> 0.044941143 | H28: ==Sheet1!M27 -> 0.026846011 | I28: ==Sheet1!N27 -> 0.023247765 | J28: ==Sheet1!O27 -> 0.028305428 | K28: ==G28 -> 0.044941143 | L28: ==H28 -> 0.026846011 | M28: ==I28 -> 0.023247765 | N28: ==J28 -> 0.028305428 | O28: ==K28 -> 0.044941143 | P28: ==L28 -> 0.026846011 | Q28: ==M28 -> 0.023247765 | R28: ==N28 -> 0.028305428 | S28: ==W23 -> 0.013
B29: 不动产 | C29: 0.065 | D29: ==SUMIFS(资产明细!$M$3:$M$80,资产明细!$D$3:$D$80,配置调整!D$2,资产明细!$K$3:$K$80,配置调整!$B29)/SUMIFS(资产明细!$M$3:$M$80,资产明细!$D$3:$D$80,配置调整!D$2) -> 0.097637828 | E29: ==SUMIFS(资产明细!$M$3:$M$80,资产明细!$D$3:$D$80,配置调整!E$2,资产明细!$K$3:$K$80,配置调整!$B29)/SUMIFS(资产明细!$M$3:$M$80,资产明细!$D$3:$D$80,配置调整!E$2) -> 0.097637828 | F29: ==SUMIFS(资产明细!$M$3:$M$80,资产明细!$D$3:$D$80,配置调整!F$2,资产明细!$K$3:$K$80,配置调整!$B29)/SUMIFS(资产明细!$M$3:$M$80,资产明细!$D$3:$D$80,配置调整!F$2) -> 0.097637828 | G29: ==Sheet1!L28 -> 0.097637828 | H29: ==Sheet1!M28 -> 0.082026193 | I29: ==Sheet1!N28 -> 0.093030624 | J29: ==Sheet1!O28 -> 0.094949232 | K29: ==G29 -> 0.097637828 | L29: ==H29 -> 0.082026193 | M29: ==I29 -> 0.093030624 | N29: ==J29 -> 0.094949232 | O29: ==K29 -> 0.097637828 | P29: ==L29 -> 0.082026193 | Q29: ==M29 -> 0.093030624 | R29: ==N29 -> 0.094949232 | S29: 0.07
D30: ==SUM(D4:D29) -> 1 | E30: ==SUM(E4:E29) -> 1 | F30: ==SUM(F4:F29) -> 1 | G30: ==SUM(G4:G29) -> 1 | H30: 1 | I30: 1 | J30: 1 | K30: ==SUM(K4:K29) -> 1 | L30: 1 | M30: 1 | N30: 1 | O30: ==SUM(O4:O29) -> 1 | P30: 1 | Q30: 1 | R30: 1
K33: 2.2451921e+09
K34: -2.0550783e+10
K35: ==K33-K34 -> 2.2795975e+10
K36: 2.6751843e+10
K37: 1.1283657

Sheet Sheet1
D1: 1231 | L1: 0 | M1: 1 | N1: 2 | O1: 3 | T1: 6844 | U1: 5280 | V1: 75
B2: 资产组合名称/PortfolioName | C2: 预期投资收益率/ExpectedReturn | D2: 预期投资收益率/ExpectedReturn | G2: 波动率 | H2: 波动率 | L2: ==SUM(L3:L28) -> 1 | M2: ==SUM(M3:M28) -> 1 | N2: ==SUM(N3:N28) -> 1 | O2: ==SUM(O3:O28) -> 1 | S2: 0 | T2: 1 | U2: 2 | V2: 3
B3: 国债_3Y | C3: 0.015636 | D3: 0.011872 | E3: 0.015636 | G3: 0.016212063 | H3: 0.016212063 | J3: 国债_3Y | K3: 0.14056818 | L3: ==IF(VLOOKUP(J3,$R$3:$W$28,2,0)<0.09%,0.001%,VLOOKUP(J3,$R$3:$W$28,2,0)) -> 0.0036988283 | M3: ==VLOOKUP($J3,$R$3:$V$28,3,0) -> 0.018250843 | N3: ==VLOOKUP($J3,$R$3:$V$28,4,0) -> 0.024032533 | O3: ==VLOOKUP($J3,$R$3:$V$28,5,0) -> 0.0049270319 | R3: A股 | S3: 0.00080247417 | T3: 0.0030906251 | U3: 0.023195612 | V3: 0.00013797208
B4: 国债_5Y | C4: 0.018388 | D4: 0.014152 | E4: 0.018388 | G4: 0.023841535 | H4: 0.023841535 | J4: 国债_5Y | K4: 0.023040759 | L4: ==IF(VLOOKUP(J4,$R$3:$W$28,2,0)<0.09%,0.001%,VLOOKUP(J4,$R$3:$W$28,2,0)) -> 0.0077904803 | M4: ==VLOOKUP($J4,$R$3:$V$28,3,0) -> 0.034165384 | N4: ==VLOOKUP($J4,$R$3:$V$28,4,0) -> 0.0025115748 | O4: ==VLOOKUP($J4,$R$3:$V$28,5,0) -> 0.0020925844 | R4: H股 | S4: 0.0033770961 | T4: 4.9218324e-09 | U4: 0.019530684 | V4: 0.0086970601
B5: 国债_10Y | C5: 0.02186 | D5: 0.016752 | E5: 0.021518 | G5: 0.046383119 | H5: 0.046383119 | J5: 国债_10Y | K5: 0.001 | L5: ==IF(VLOOKUP(J5,$R$3:$W$28,2,0)<0.09%,0.001%,VLOOKUP(J5,$R$3:$W$28,2,0)) -> 0.032496654 | M5: ==VLOOKUP($J5,$R$3:$V$28,3,0) -> 7.032092e-05 | N5: ==VLOOKUP($J5,$R$3:$V$28,4,0) -> 0.030616004 | O5: ==VLOOKUP($J5,$R$3:$V$28,5,0) -> 0.013735449 | R5: MSCI发达市场 | S5: 0.0047554241 | T5: 0.027372612 | U5: 0.017012064 | V5: 0.056394661
B6: 国债_20Y | C6: 0.0236 | D6: 0.019747 | E6: 0.0236 | G6: 0.088113389 | H6: 0.088113389 | J6: 国债_20Y | K6: 0.23083174 | L6: ==IF(VLOOKUP(J6,$R$3:$W$28,2,0)<0.09%,0.001%,VLOOKUP(J6,$R$3:$W$28,2,0)) -> 0.14212089 | M6: ==VLOOKUP($J6,$R$3:$V$28,3,0) -> 0.15746475 | N6: ==VLOOKUP($J6,$R$3:$V$28,4,0) -> 0.29297907 | O6: ==VLOOKUP($J6,$R$3:$V$28,5,0) -> 0.22835041 | R6: MSCI新兴市场 | S6: 0.025377513 | T6: 0.056412323 | U6: 0.037003146 | V6: 0.028298835
B7: 国债_50Y | C7: 0.0238 | D7: 0.019875 | E7: 0.0238 | G7: 0.16994384 | H7: 0.16994384 | J7: 国债_50Y | K7: ==1-SUM(K3:K6)-SUM(K8:K28) -> 0.11267768 | L7: ==1-SUM(L3:L6)-SUM(L8:L28) -> 0.20614768 | M7: ==VLOOKUP($J7,$R$3:$V$28,3,0) -> 0.20431444 | N7: ==VLOOKUP($J7,$R$3:$V$28,4,0) -> 0.13835296 | O7: ==VLOOKUP($J7,$R$3:$V$28,5,0) -> 0.17315448 | R7: 不动产 | S7: 0.097637828 | T7: 0.082026193 | U7: 0.093030624 | V7: 0.094949232
B8: 信用债_3Y | C8: 0.023248 | D8: 0.017501 | E8: 0.023248 | G8: 0.023967206 | H8: 0.023967206 | J8: 信用债_3Y | K8: 0.001 | L8: ==IF(VLOOKUP(J8,$R$3:$W$28,2,0)<0.09%,0.001%,VLOOKUP(J8,$R$3:$W$28,2,0)) -> 0.067977585 | M8: ==VLOOKUP($J8,$R$3:$V$28,3,0) -> 0.065288002 | N8: ==VLOOKUP($J8,$R$3:$V$28,4,0) -> 0.0092608415 | O8: ==VLOOKUP($J8,$R$3:$V$28,5,0) -> 0.0047362284 | R8: 优先股 | S8: 0 | T8: 5.9124551e-121 | U8: 1.5499145e-273 | V8: 2.6197307e-112
B9: 信用债_5Y | C9: 0.024018 | D9: 0.018727 | E9: 0.024018 | G9: 0.0346123 | H9: 0.0346123 | J9: 信用债_5Y | K9: 0.076444035 | L9: ==IF(VLOOKUP(J9,$R$3:$W$28,2,0)<0.09%,0.001%,VLOOKUP(J9,$R$3:$W$28,2,0)) -> 0.0059782634 | M9: ==VLOOKUP($J9,$R$3:$V$28,3,0) -> 4.1665381e-12 | N9: ==VLOOKUP($J9,$R$3:$V$28,4,0) -> 0.017289853 | O9: ==VLOOKUP($J9,$R$3:$V$28,5,0) -> 0.00087263177 | R9: 信用债_10Y | S9: 0.039135613 | T9: 0.065497096 | U9: 0.015324656 | V9: 0.027221905
B10: 信用债_10Y | C10: 0.025446 | D10: 0.021173 | E10: 0.025446 | G10: 0.055518462 | H10: 0.055518462 | J10: 信用债_10Y | K10: 0.12336229 | L10: ==IF(VLOOKUP(J10,$R$3:$W$28,2,0)<0.09%,0.001%,VLOOKUP(J10,$R$3:$W$28,2,0)) -> 0.039135613 | M10: ==VLOOKUP($J10,$R$3:$V$28,3,0) -> 0.065497096 | N10: ==VLOOKUP($J10,$R$3:$V$28,4,0) -> 0.015324656 | O10: ==VLOOKUP($J10,$R$3:$V$28,5,0) -> 0.027221905 | R10: 信用债_3Y | S10: 0.067977585 | T10: 0.065288002 | U10: 0.0092608415 | V10: 0.0047362284
B11: 非标资产_3Y | C11: 0.032266808 | D11: 0.024290322 | G11: 0.028760647 | H11: 0.028760647 | J11: 非标资产_3Y | K11: 0.043358988 | L11: ==IF(VLOOKUP(J11,$R$3:$W$28,2,0)<0.09%,0.001%,VLOOKUP(J11,$R$3:$W$28,2,0)) -> 0.028692128 | M11: ==VLOOKUP($J11,$R$3:$V$28,3,0) -> 0.00021312637 | N11: ==VLOOKUP($J11,$R$3:$V$28,4,0) -> 0.0074794708 | O11: ==VLOOKUP($J11,$R$3:$V$28,5,0) -> 0.0071535672 | R11: 信用债_5Y | S11: 0.0059782634 | T11: 4.1665381e-12 | U11: 0.017289853 | V11: 0.00087263177
B12: 非标资产_5Y | C12: 0.03287009 | D12: 0.025629035 | G12: 0.041534759 | H12: 0.041534759 | J12: 非标资产_5Y | K12: 0.0066242687 | L12: ==IF(VLOOKUP(J12,$R$3:$W$28,2,0)<0.09%,0.001%,VLOOKUP(J12,$R$3:$W$28,2,0)) -> 0.018801727 | M12: ==VLOOKUP($J12,$R$3:$V$28,3,0) -> 0.018435449 | N12: ==VLOOKUP($J12,$R$3:$V$28,4,0) -> 0.011006803 | O12: ==VLOOKUP($J12,$R$3:$V$28,5,0) -> 0.026071855 | R12: 债券基金 | S12: 8.183199e-61 | T12: 0.00039173317 | U12: 1.7707171e-07 | V12: 0.00029124044
B13: A股 | C13: 0.091774815 | D13: 0.091774815 | G13: 0.25066148 | H13: 0.25066148 | J13: A股 | K13: 0.001 | L13: ==IF(VLOOKUP(J13,$R$3:$W$28,2,0)<0.09%,0.001%,VLOOKUP(J13,$R$3:$W$28,2,0)) -> 1e-05 | M13: ==VLOOKUP($J13,$R$3:$V$28,3,0) -> 0.0030906251 | N13: ==VLOOKUP($J13,$R$3:$V$28,4,0) -> 0.023195612 | O13: ==VLOOKUP($J13,$R$3:$V$28,5,0) -> 0.00013797208 | R13: 其他信用产品 | S13: 0.12250776 | T13: 0.13250204 | U13: 0.10510801 | V13: 0.20277254
B14: H股 | C14: 0.1021779 | D14: 0.1021779 | G14: 0.21063241 | H14: 0.21063241 | J14: H股 | K14: 0.029760464 | L14: ==IF(VLOOKUP(J14,$R$3:$W$28,2,0)<0.09%,0.001%,VLOOKUP(J14,$R$3:$W$28,2,0)) -> 0.0033770961 | M14: ==VLOOKUP($J14,$R$3:$V$28,3,0) -> 4.9218324e-09 | N14: ==VLOOKUP($J14,$R$3:$V$28,4,0) -> 0.019530684 | O14: ==VLOOKUP($J14,$R$3:$V$28,5,0) -> 0.0086970601 | R14: 固收产品 | S14: 0.10046895 | T14: 0.074257634 | U14: 0.062730795 | V14: 0.0098338199
B15: MSCI发达市场 | C15: 0.06965 | D15: 0.06965 | G15: 0.1673502 | H15: 0.1673502 | J15: MSCI发达市场 | K15: 0.001 | L15: ==IF(VLOOKUP(J15,$R$3:$W$28,2,0)<0.09%,0.001%,VLOOKUP(J15,$R$3:$W$28,2,0)) -> 0.0047554241 | M15: ==VLOOKUP($J15,$R$3:$V$28,3,0) -> 0.027372612 | N15: ==VLOOKUP($J15,$R$3:$V$28,4,0) -> 0.017012064 | O15: ==VLOOKUP($J15,$R$3:$V$28,5,0) -> 0.056394661 | R15: 国债_10Y | S15: 0.032496654 | T15: 7.032092e-05 | U15: 0.030616004 | V15: 0.013735449
B16: MSCI新兴市场 | C16: 0.077 | D16: 0.077 | G16: 0.22586533 | H16: 0.22586533 | J16: MSCI新兴市场 | K16: 0.001 | L16: ==IF(VLOOKUP(J16,$R$3:$W$28,2,0)<0.09%,0.001%,VLOOKUP(J16,$R$3:$W$28,2,0)) -> 0.025377513 | M16: ==VLOOKUP($J16,$R$3:$V$28,3,0) -> 0.056412323 | N16: ==VLOOKUP($J16,$R$3:$V$28,4,0) -> 0.037003146 | O16: ==VLOOKUP($J16,$R$3:$V$28,5,0) -> 0.028298835 | R16: 国债_20Y | S16: 0.14212089 | T16: 0.15746475 | U16: 0.29297907 | V16: 0.22835041
B17: 债券基金 | C17: 0.028487288 | D17: 0.028487288 | G17: 0.035443014 | H17: 0.035443014 | J17: 债券基金 | K17: 0.001 | L17: ==IF(VLOOKUP(J17,$R$3:$W$28,2,0)<0.09%,0.001%,VLOOKUP(J17,$R$3:$W$28,2,0)) -> 1e-05 | M17: ==VLOOKUP($J17,$R$3:$V$28,3,0) -> 0.00039173317 | N17: ==VLOOKUP($J17,$R$3:$V$28,4,0) -> 1.7707171e-07 | O17: ==VLOOKUP($J17,$R$3:$V$28,5,0) -> 0.00029124044 | R17: 国债_3Y | S17: 0.0036988283 | T17: 0.018250843 | U17: 0.024032533 | V17: 0.0049270319
B18: 货币基金 | C18: 0.015 | D18: 0.015 | G18: 0.005 | H18: 0.005 | J18: 货币基金 | K18: 0.001 | L18: ==IF(VLOOKUP(J18,$R$3:$W$28,2,0)<0.09%,0.001%,VLOOKUP(J18,$R$3:$W$28,2,0)) -> 1e-05 | M18: ==VLOOKUP($J18,$R$3:$V$28,3,0) -> 1.0556649e-138 | N18: ==VLOOKUP($J18,$R$3:$V$28,4,0) -> 0 | O18: ==VLOOKUP($J18,$R$3:$V$28,5,0) -> 0 | R18: 国债_50Y | S18: 0.20537978 | T18: 0.20431444 | U18: 0.13835296 | V18: 0.17315448
B19: 混合基金 | C19: 0.066459804 | D19: 0.066459804 | G19: 0.17649996 | H19: 0.17649996 | J19: 混合基金 | K19: 0.001 | L19: ==IF(VLOOKUP(J19,$R$3:$W$28,2,0)<0.09%,0.001%,VLOOKUP(J19,$R$3:$W$28,2,0)) -> 0.010751247 | M19: ==VLOOKUP($J19,$R$3:$V$28,3,0) -> 0 | N19: ==VLOOKUP($J19,$R$3:$V$28,4,0) -> 2.1006208e-59 | O19: ==VLOOKUP($J19,$R$3:$V$28,5,0) -> 0 | R19: 国债_5Y | S19: 0.0077904803 | T19: 0.034165384 | U19: 0.0025115748 | V19: 0.0020925844
B20: 股票基金 | C20: 0.085446062 | D20: 0.085446062 | G20: 0.22425377 | H20: 0.22425377 | J20: 股票基金 | K20: 0.001 | L20: ==IF(VLOOKUP(J20,$R$3:$W$28,2,0)<0.09%,0.001%,VLOOKUP(J20,$R$3:$W$28,2,0)) -> 1e-05 | M20: ==VLOOKUP($J20,$R$3:$V$28,3,0) -> 4.1777806e-10 | N20: ==VLOOKUP($J20,$R$3:$V$28,4,0) -> 1.9288294e-07 | O20: ==VLOOKUP($J20,$R$3:$V$28,5,0) -> 0.00010022122 | R20: 存款 | S20: 0.044941143 | T20: 0.026846011 | U20: 0.023247765 | V20: 0.028305428
B21: 优先股 | C21: 0.055 | D21: 0.055 | G21: 0.16924168 | H21: 0.16924168 | J21: 优先股 | K21: 0.001 | L21: ==IF(VLOOKUP(J21,$R$3:$W$28,2,0)<0.09%,0.001%,VLOOKUP(J21,$R$3:$W$28,2,0)) -> 1e-05 | M21: ==VLOOKUP($J21,$R$3:$V$28,3,0) -> 5.9124551e-121 | N21: ==VLOOKUP($J21,$R$3:$V$28,4,0) -> 1.5499145e-273 | O21: ==VLOOKUP($J21,$R$3:$V$28,5,0) -> 2.6197307e-112 | R21: 未上市股权 | S21: 0.0062594927 | T21: 0.01509643 | U21: 0.045674309 | V21: 0.067780889
B22: 长期股权投资 | C22: 0.1044455 | D22: 0.1044455 | G22: 0.19302347 | H22: 0.19302347 | J22: 长期股权投资 | K22: 0.001 | L22: ==IF(VLOOKUP(J22,$R$3:$W$28,2,0)<0.09%,0.001%,VLOOKUP(J22,$R$3:$W$28,2,0)) -> 1e-05 | M22: ==VLOOKUP($J22,$R$3:$V$28,3,0) -> 0 | N22: ==VLOOKUP($J22,$R$3:$V$28,4,0) -> 1.7251875e-51 | O22: ==VLOOKUP($J22,$R$3:$V$28,5,0) -> 0 | R22: 混合基金 | S22: 0.010751247 | T22: 0 | U22: 2.1006208e-59 | V22: 0
... B28: 不动产 | C28: 0.065 | D28: 0.065 | G28: 0.07635184 | H28: 0.07635184 | J28: 不动产 | K28: 0.09544665 | L28: ==IF(VLOOKUP(J28,$R$3:$W$28,2,0)<0.09%,0.001%,VLOOKUP(J28,$R$3:$W$28,2,0)) -> 0.097637828 | M28: ==VLOOKUP($J28,$R$3:$V$28,3,0) -> 0.082026193 | N28: ==VLOOKUP($J28,$R$3:$V$28,4,0) -> 0.093030624 | O28: ==VLOOKUP($J28,$R$3:$V$28,5,0) -> 0.094949232 | R28: 非标资产_5Y | S28: 0.018801727 | T28: 0.018435449 | U28: 0.011006803 | V28: 0.026071855

Sheet 字段解释
B2: 字段 | C2: 描述 | D2: 校验
B3: 资产唯一识别码/AssetUniqueIdentification | C3: 资产在系统中的唯一编号，用于系统在个券层面进行识别。 | D3: 系统会在上传时校验，用户可自定义但不能重复。不能为空。
B4: 资产名称/AssetName | C4: 用于用户识别的资产名称。 | D4: 系统不会在上传时校验，用户可自定义并可以重复。可以为空。
B5: 保险账户分类/InsuranceAccountType | C5: 为分账户管理的标签，区分各账户内的资产，用于计算需要分账户的计算内容。在进行量化报表计算时，不可以自定义，需要按照监管要求填写保险账户名称。战略资产配置时，可以自定义。 | D5: 系统在上传时校验是否为空，用户可根据下拉框选择，也可自定义。不能为空。
B6: 资产配置分类一级/SAAAssetTypeLevel1 | C6: 用于对资产进行第一级分类。 | D6: 系统会在上传时校验，用户可自定义。【资产配置分类一级/SAAAssetTypeLevel1】是配置【资产配置分类二级/SAAAssetTypeLevel2】前置条件。.
B7: 资产配置分类二级/SAAAssetTypeLevel2 | C7: 用于对资产进行第二级分类。 | D7: 系统会在上传时校验，用户可自定义。资产配置分类二级/SAAAssetTypeLevel2】是配置【资产配置分类三级/SAAAssetTypeLevel3】前置条件。
B8: 资产配置分类三级/SAAAssetTypeLevel3 | C8: 用于对资产进行第三级分类。 | D8: 系统会在上传时校验，用户可自定义。可以为空。
B9: ALM五级分类/ALMClassificationLevel5 | C9: 用于识别卖出回购类资产。 | D9: 系统会在上传时校验，只能输入指定字段或为空。可以为空。
B10: 偿付能力分类/SolvencyType | C10: 个券层面在偿付能力分类上的标签，用于及偿付能力长期预测。 | D10: 系统不会校验，用户可自定义。可以为空。
B11: 会计分类/AccountingType | C11: 用于识别资产的会计分类 | D11: 系统会在上传时校验，需要按照下拉框填写，不可自定义。不可为空。
B12: 资产组合名称/PortfolioName | C12: 为资产组合层面的识别标签，用于对资产进行第四级分类，以及为资产配置优化大类资产标签。 | D12: 系统会在上传时校验是否为空，用户可自定义。不可为空。
B13: 建模类型/ModelType | C13: 为个券层面资产建模方法的区分，用于资产基础建模。 | D13: 系统会在上传时校验是否为空，需要按照下拉框填写，不可自定义。不可为空。
... B67: 预计信用变化/ExpectedCreditState | C67: 用于计算I9下信用减值的减值准备，资产信用阶段的变化情况。 | D67: 系统不会校验，但需要用户根据下拉框填写。

Sheet List
B2: 是或否 | D2: 币种 | F2: 境外市场 | H2: 境外资产类别 | J2: 穿透资产种类 | L2: ALM一级分类（寿险）/ALMClassificationLevel1 | N2: 保险账户分类/InsuranceAccountType | P2: 表1-2-5行业名称/Form1-2-5IndustrySector | R2: ALM表4流动性资产等级/Form4LiquidityLevel
B3: 是 | D3: 人民币 | F3: 发达市场 | H3: 同业存单、短期融资券 | J3: 股票（未套保及不符合条件套保） | L3: 1、现金及流动性管理工具 | N3: 传统保险账户 | P3: 1|农林牧渔 | R3: 高流动性资产
B4: 否 | D4: 美元和汇率跟美元挂钩的货币 | F4: 新兴市场 | H4: 其他境外固收资产 | J4: 股票（符合条件的套期保值） | L4: 2、固定收益类投资资产 | N4: 资本金账户 | P4: 2|煤炭 | R4: 中低流动性资产
D5: 欧元、英镑 | J5: 优先股 | L5: 3、权益类投资资产 | N5: 次级债和资本补充债 | P5: 3|基础化工 | R5: 现金及流动性管理工具
D6: 其他货币 | J6: 无固定期限资本债券 | L6: 4、投资性房地产 | N6: 分红保险账户 | P6: 4|黑色金属
J7: 未上市股权 | L7: 贷款 | N7: 万能保险账户 | P7: 5|有色金属 | R7: 预计信用变化/ExpectedCreditState
J8: 对子公司、合营企业和联营企业的长期股权投资 | L8: 金融衍生工具 | N8: 独立账户 | P8: 6|电子元器件 | R8: 维持阶段一
B9: 地理位置 | D9: 现金类别 | F9: 基金类型 | H9: 存款类型 | J9: 证券投资基金 | L9: 自用性不动产 | P9: 7|家用电器 | R9: 变差（由阶段一进入阶段二）
B10: 直辖市、省会城市、计划单列市 | D10: 现金、买入返售金融资产及其他 | F10: 债券基金 | H10: 定期存款、协议存款、大额存单 | J10: 可转债、可交换债 | N10: 表1-1-4分类/Form1-1-4Category | P10: 8|食品饮料 | R10: 维持阶段二
B11: 境内其他地区 | D11: 拆出资金 | F11: 股票基金 | H11: 保本结构性存款 | J11: 利率类金融衍生品 | L11: ALM二级分类（寿险）/ALMClassificationLevel2 | N11: 存款 | P11: 9|纺织服饰 | R11: 变好（由阶段二转回阶段一）
D12: 存放在第三方支付机构账户的资金 | F12: 混合基金、商品及金融衍生品基金 | H12: 非保本结构性存款 | J12: 其他金融衍生品-股指期货（不符合条件套保） | L12: 1.1境内现金及流动性管理工具 | N12: （准）政府债券 | P12: 10|轻工制造
F13: 货币市场基金 | H13: 存款 | J13: 投资性房地产 | L13: 1.2境外现金及流动性管理工具 | N13: 金融企业（公司）债券 | P13: 11|医药生物 | R13: 特殊条款/SpecialTerms
H14: 定期存款 | J14: 境外固定收益类投资资产 | L14: 2.1境内固定收益类投资资产 | N14: 非金融企业（公司）债券 | P14: 12|公共事业 | R14: 不适用
H15: 协议存款 | J15: 境外权益类投资资产（长期股权投资） | L15: 2.2境外固定收益类投资资产 | N15: 非标准固定收益类投资资产 | P15: 13|交通运输 | R15: 到期一次还本付息
B16: 存款机构类型 | D16: 债券种类 | F16: 股票类型/StockType | H16: 结构性存款 | J16: 套期保值的外汇远期和利率互换 | L16: 3.1境内权益类投资资产 | N16: 其他固定收益类金融产品 | P16: 14|房地产 | R16: 现金
B17: 国有商业银行 | D17: 政策性银行发行的金融债券 | F17: 沪深主板 | H17: 大额存单 | J17: 应收利息 | L17: 3.2境外权益类投资资产 | N17: 含保证条款的权益类资产 | P17: 15|商贸零售 | R17: 回售
B18: 股份制商业银行 | D18: 政府支持性机构债券 | F18: 创业板股、科创板股 | H18: 同业存单 | J18: 对企业或个人的债权资产 | L18: 4.1境内投资性房地产 | N18: 境外固定收益类投资资产 | P18: 16|社会服务 | R18: 赎回
B19: 邮政储蓄银行 | D19: 企业债、公司债 | J19: 权益类信托计划 | L19: 4.2境外投资性房地产 | P19: 17|综合 | R19: 提前偿还
B20: 城市商业银行 | D20: 金融企业债务融资工具 | J20: 组合类保险资产管理产品 | N20: 表1-2-4五级分类/Form1-2-4FiveLevels | P20: 18|建筑材料 | R20: 调整票面利率
B21: 国际信用评级在A级及以上的外资商业银行 | D21: 其他债券类资产 | H21: 商业银行理财产品种类 | J21: 股权投资计划 | L21: ALM三级分类（寿险）/ALMClassificationLevel3 | N21: 正常类 | P21: 19|建筑装饰 | R21: 提前偿还，调整票面利率
B22: 其他境内商业银行 | H22: 固定收益类 | J22: 股权投资基金 | L22: 2.1.1传统固定收益类投资资产 | N22: 关注类 | P22: 20|电力设备 | R22: 贴现
B23: 境外银行 | H23: 权益类 | J23: 债转股投资计划 | L23: 2.1.2非标准固定收益类投资资产 | N23: 次级类 | P23: 21|国防军工 | R23: 赎回，回售
B24: 其他存款机构 | H24: 混合类、商品及金融衍生品类 | J24: 商业银行理财产品 | L24: 2.1.3其他固定收益类金融产品 | N24: 可疑类 | P24: 22|计算机 | R24: 调整票面利率，提前偿还
B25: 政策性银行 | J25: 特殊目的载体SPV | L25: 2.1.4含保证条款的权益类投资资产及属于权益工具投资的企业（公司）债券 | N25: 损失类 | P25: 23|传媒 | R25: 回售，赎回
B26: 银行 | J26: 境外固定收益类基础资产 | L26: 3.1.1上市普通股票 | P26: 24|通信
B27: 企业集团财务公司 | J27: 境外权益类基础资产 | L27: 3.1.2证券投资基金（不含货币市场基金、债券型基金） | N27: 表1-2-4资产类型/Form1-2-4AssetType | P27: 25|银行
B28: 农村商业银行 | J28: 汇率风险所涉项目明细表 | L28: 3.1.3优先股权权益融资工具 | N28: 股权-有公允价格 | P28: 26|非银金融
J29: 固定收益类信托计划 | L29: 3.1.4可转债 | N29: 股权-无公允价格 | P29: 27|汽车
B30: 信用评级 | D30: 发行机构 | F30: 机构类型 | H30: 资本充足率 | J30: 债权投资计划 | L30: 3.1.5未上市企业股权 | N30: 股权金融产品 | P30: 28|机械设备
B31: 免评级 | D31: 政策性银行 | F31: 保险类子公司及与保险主业相关的养老、医疗、汽车服务等子公司 | H31: 14.5%或以上 | J31: 资产支持计划 | L31: 3.1.6不含保证条款的权益类和混合类保险资产管理产品 | N31: 债券 | P31: 29|Energy
B32: AAA | D32: 国有商业银行 | F32: 上市公司 | H32: 13.5%或以上 | L32: 3.1.7不含保证条款的股权投资计划、私募股权投资基金 | N32: 基础设施及不动产债权投资计划 | P32: 30|Materials
B33: AA | D33: 股份制银行 | F33: 非上市公司 | H33: 12%或以上 | J33: 会计分类(监管报表以现有会计准则为准) | L33: 3.1.8权益类信托计划 | N33: 其他 | P33: 31|Industrials
B34: A | D34: 城市商业银行 | F34: 其他 | H34: [13.5%, 14.5%) | J34: AFS | L34: 3.1.9债转股投资计划 | N34: 不动产类 | P34: 32|ConsumerDiscretionary
B35: BBB | D35: 其他商业银行 | H35: [12.5%, 13.5%) | J35: HTM | L35: 3.1.10其他权益类资产 | P35: 33|ConsumerStaples
B36: BBB以下 | D36: 金融资产管理公司 | H36: [12.0%, 12.5%) | J36: Trading | L36: 3.2.1普通股 | P36: 34|HealthCare
B37: 无评级 | D37: 保险公司 | H37: 13.5%及以下 | J37: LR | L37: 3.2.2证券投资基金（不含货币市场基金、债券型基金） | P37: 35|Financials
B38: AA+ | D38: 非金融机构 | H38: 12.5%及以下 | J38: DEPO | L38: 3.2.3优先股权益融资工具 | P38: 36|InformationTechnology
B39: AA- | H39: 12%以下 | J39: LTEC | L39: 3.2.4可转债 | P39: 37|TelecommunicationServices
B40: A+ | J40: LTEE | L40: 3.2.5全球存托凭证、美国存托凭证 | P40: 38|Utilities
B41: A- | J41: AMC | L41: 3.2.6房地产信托投资基金（REITs） | P41: 39|RealEstate
B42: BBB+ | J42: FVOCI | L42: 3.2.7未上市企业股权 | P42: 40|不适用
B43: BBB- | J43: FVPL | L43: 3.2.8股权投资基金 | P43: 41|美容护理
B44: 不适用 | L44: 3.2.9其他权益类资产 | P44: 42|石油石化
P45: 43|环保
B46: 持有形式 | D46: 资产风险分类等级 | F46: 套期有效性判断 | H46: 套保种类 | L46: ALM四级分类（寿险）/ALMClassificationLevel4
B47: 项目公司融资借款 | D47: 正常类 | F47: 符合套期有效性要求且期限不低于1个月 | H47: 多头 | L47: 2.1.2.1固定收益类保险资产管理产品
B48: 物权 | D48: 关注类 | F48: 符合套期有效性要求且期限低于1个月 | H48: 空头 | L48: 2.1.2.2另类保险资产管理产品
B49: 项目公司股权 | D49: 次级类 | F49: 不符合套期有效性要求 | L49: 2.1.2.3项目资产支持计划
B50: 境外房地产信托投资基金（公募） | D50: 可疑类 | L50: 2.1.2.4基础设施债权投资计划
D51: 损失类 | L51: 2.1.2.5不动产债权投资计划
L52: 2.1.2.6其他产品
B53: 汇率套期保值 | D53: 穿透标识 | F53: 基础资产种类 | H53: 建模类型/ModelType
B54: 不使用 | D54: 豁免穿透 | F54: 债权类资产 | H54: 标准固收类 | L54: ALM五级分类（寿险）/ALMClassificationLevel5
B55: 使用但符合 | D55: 无法穿透 | F55: 其他 | H55: 非标固收类 | L55: 其中：剩余期限不超过1年的政府债券、准政府债券
B56: 使用但不符合 | D56: 可以穿透 | H56: 权益类 | L56: 其中：债券型基金
D57: 表层资产 | H57: 现金类 | L57: 其中：融资类信托计划
D58: 底层资产 | L58: 其中：优先股债务融资工具
L59: 其中：基础资产为投资性房地产的含保证条款的权益投资资产
L60: 其中：基础资产为基础设施的含保证条款的权益投资资产
L61: 其中：剩余期限不超过1年的政府债券、国际金融组织债券、公司债券
L62: 其中：不具有银行保本承诺的结构性存款
L63: 其中：境内直接投资股权和间接投资股权形成的长期股权投资
L64: 其中：以自有资金对保险类企业的股权投资
L65: 其中：基础资产为投资性房地产的不含保证条款的股权投资计划、私募股权投资基金
L66: 其中：基础资产为基础设施的不含保证条款的股权投资计划、私募股权投资基金
L67: 其中：基础资产为投资性房地产的权益类信托计划
L68: 其中：基础资产为投资性房地产的其他权益类资产
L69: 其中：境外直接投资股权和间接投资股权形成的长期股权投资
L70: 其中：以自有资金对保险类企业的股权投资
... L77: 其中：基础资产为投资性房地产的不含保证条款的股权投资计划、私募股权投资基金/其中：境内直接投资股权和间接投资股权形成的长期股权投资
